<?xml version="1.0" encoding="utf-8"?>
<Trans>
  <TransInfo Description="Top" HashKey="464646848484848484">
    <MapTiles>
      <MapTile TileID="282" AltIDMod="0" />
      <MapTile TileID="283" AltIDMod="0" />
      <MapTile TileID="284" AltIDMod="0" />
      <MapTile TileID="285" AltIDMod="0" />
    </MapTiles>
    <StaticTiles>
      <StaticTile TileID="12916" AltIDMod="0" />
      <StaticTile TileID="12917" AltIDMod="0" />
    </StaticTiles>
  </TransInfo>
  <TransInfo Description="Top" HashKey="844646848484848484">
    <MapTiles>
      <MapTile TileID="282" AltIDMod="0" />
      <MapTile TileID="283" AltIDMod="0" />
      <MapTile TileID="284" AltIDMod="0" />
      <MapTile TileID="285" AltIDMod="0" />
    </MapTiles>
    <StaticTiles>
      <StaticTile TileID="12916" AltIDMod="0" />
      <StaticTile TileID="12917" AltIDMod="0" />
    </StaticTiles>
  </TransInfo>
  <TransInfo Description="Top" HashKey="464684848484848484">
    <MapTiles>
      <MapTile TileID="282" AltIDMod="0" />
      <MapTile TileID="283" AltIDMod="0" />
      <MapTile TileID="284" AltIDMod="0" />
      <MapTile TileID="285" AltIDMod="0" />
    </MapTiles>
    <StaticTiles>
      <StaticTile TileID="12916" AltIDMod="0" />
      <StaticTile TileID="12917" AltIDMod="0" />
    </StaticTiles>
  </TransInfo>
  <TransInfo Description="Top" HashKey="844684848484848484">
    <MapTiles>
      <MapTile TileID="282" AltIDMod="0" />
      <MapTile TileID="283" AltIDMod="0" />
      <MapTile TileID="284" AltIDMod="0" />
      <MapTile TileID="285" AltIDMod="0" />
    </MapTiles>
    <StaticTiles>
      <StaticTile TileID="12916" AltIDMod="0" />
      <StaticTile TileID="12917" AltIDMod="0" />
    </StaticTiles>
  </TransInfo>
  <TransInfo Description="Top" HashKey="468446848484848484">
    <MapTiles>
      <MapTile TileID="282" AltIDMod="0" />
      <MapTile TileID="283" AltIDMod="0" />
      <MapTile TileID="284" AltIDMod="0" />
      <MapTile TileID="285" AltIDMod="0" />
    </MapTiles>
    <StaticTiles>
      <StaticTile TileID="12916" AltIDMod="0" />
      <StaticTile TileID="12917" AltIDMod="0" />
    </StaticTiles>
  </TransInfo>
  <TransInfo Description="Left" HashKey="468484468484468484">
    <MapTiles>
      <MapTile TileID="282" AltIDMod="0" />
      <MapTile TileID="283" AltIDMod="0" />
      <MapTile TileID="284" AltIDMod="0" />
      <MapTile TileID="285" AltIDMod="0" />
    </MapTiles>
    <StaticTiles>
      <StaticTile TileID="12912" AltIDMod="0" />
      <StaticTile TileID="12913" AltIDMod="0" />
    </StaticTiles>
  </TransInfo>
  <TransInfo Description="Left" HashKey="468484468484848484">
    <MapTiles>
      <MapTile TileID="282" AltIDMod="0" />
      <MapTile TileID="283" AltIDMod="0" />
      <MapTile TileID="284" AltIDMod="0" />
      <MapTile TileID="285" AltIDMod="0" />
    </MapTiles>
    <StaticTiles>
      <StaticTile TileID="12912" AltIDMod="0" />
      <StaticTile TileID="12913" AltIDMod="0" />
    </StaticTiles>
  </TransInfo>
  <TransInfo Description="Left" HashKey="848484468484468484">
    <MapTiles>
      <MapTile TileID="282" AltIDMod="0" />
      <MapTile TileID="283" AltIDMod="0" />
      <MapTile TileID="284" AltIDMod="0" />
      <MapTile TileID="285" AltIDMod="0" />
    </MapTiles>
    <StaticTiles>
      <StaticTile TileID="12912" AltIDMod="0" />
      <StaticTile TileID="12913" AltIDMod="0" />
    </StaticTiles>
  </TransInfo>
  <TransInfo Description="Left" HashKey="848484468484848484">
    <MapTiles>
      <MapTile TileID="282" AltIDMod="0" />
      <MapTile TileID="283" AltIDMod="0" />
      <MapTile TileID="284" AltIDMod="0" />
      <MapTile TileID="285" AltIDMod="0" />
    </MapTiles>
    <StaticTiles>
      <StaticTile TileID="12912" AltIDMod="0" />
      <StaticTile TileID="12913" AltIDMod="0" />
    </StaticTiles>
  </TransInfo>
  <TransInfo Description="Left" HashKey="468484848484468484">
    <MapTiles>
      <MapTile TileID="282" AltIDMod="0" />
      <MapTile TileID="283" AltIDMod="0" />
      <MapTile TileID="284" AltIDMod="0" />
      <MapTile TileID="285" AltIDMod="0" />
    </MapTiles>
    <StaticTiles>
      <StaticTile TileID="12912" AltIDMod="0" />
      <StaticTile TileID="12913" AltIDMod="0" />
    </StaticTiles>
  </TransInfo>
  <TransInfo Description="Right" HashKey="848446848446848446">
    <MapTiles>
      <MapTile TileID="282" AltIDMod="0" />
      <MapTile TileID="283" AltIDMod="0" />
      <MapTile TileID="284" AltIDMod="0" />
      <MapTile TileID="285" AltIDMod="0" />
    </MapTiles>
    <StaticTiles>
      <StaticTile TileID="12918" AltIDMod="0" />
      <StaticTile TileID="12919" AltIDMod="0" />
    </StaticTiles>
  </TransInfo>
  <TransInfo Description="Right" HashKey="848484848446848446">
    <MapTiles>
      <MapTile TileID="282" AltIDMod="0" />
      <MapTile TileID="283" AltIDMod="0" />
      <MapTile TileID="284" AltIDMod="0" />
      <MapTile TileID="285" AltIDMod="0" />
    </MapTiles>
    <StaticTiles>
      <StaticTile TileID="12918" AltIDMod="0" />
      <StaticTile TileID="12919" AltIDMod="0" />
    </StaticTiles>
  </TransInfo>
  <TransInfo Description="Right" HashKey="848446848446848484">
    <MapTiles>
      <MapTile TileID="282" AltIDMod="0" />
      <MapTile TileID="283" AltIDMod="0" />
      <MapTile TileID="284" AltIDMod="0" />
      <MapTile TileID="285" AltIDMod="0" />
    </MapTiles>
    <StaticTiles>
      <StaticTile TileID="12918" AltIDMod="0" />
      <StaticTile TileID="12919" AltIDMod="0" />
    </StaticTiles>
  </TransInfo>
  <TransInfo Description="Right" HashKey="848484848446848484">
    <MapTiles>
      <MapTile TileID="282" AltIDMod="0" />
      <MapTile TileID="283" AltIDMod="0" />
      <MapTile TileID="284" AltIDMod="0" />
      <MapTile TileID="285" AltIDMod="0" />
    </MapTiles>
    <StaticTiles>
      <StaticTile TileID="12918" AltIDMod="0" />
      <StaticTile TileID="12919" AltIDMod="0" />
    </StaticTiles>
  </TransInfo>
  <TransInfo Description="Right" HashKey="848446848484848446">
    <MapTiles>
      <MapTile TileID="282" AltIDMod="0" />
      <MapTile TileID="283" AltIDMod="0" />
      <MapTile TileID="284" AltIDMod="0" />
      <MapTile TileID="285" AltIDMod="0" />
    </MapTiles>
    <StaticTiles>
      <StaticTile TileID="12918" AltIDMod="0" />
      <StaticTile TileID="12919" AltIDMod="0" />
    </StaticTiles>
  </TransInfo>
  <TransInfo Description="Bottom" HashKey="848484848484464646">
    <MapTiles>
      <MapTile TileID="282" AltIDMod="0" />
      <MapTile TileID="283" AltIDMod="0" />
      <MapTile TileID="284" AltIDMod="0" />
      <MapTile TileID="285" AltIDMod="0" />
    </MapTiles>
    <StaticTiles>
      <StaticTile TileID="12914" AltIDMod="0" />
      <StaticTile TileID="12915" AltIDMod="0" />
    </StaticTiles>
  </TransInfo>
  <TransInfo Description="Bottom" HashKey="848484848484464684">
    <MapTiles>
      <MapTile TileID="282" AltIDMod="0" />
      <MapTile TileID="283" AltIDMod="0" />
      <MapTile TileID="284" AltIDMod="0" />
      <MapTile TileID="285" AltIDMod="0" />
    </MapTiles>
    <StaticTiles>
      <StaticTile TileID="12914" AltIDMod="0" />
      <StaticTile TileID="12915" AltIDMod="0" />
    </StaticTiles>
  </TransInfo>
  <TransInfo Description="Bottom" HashKey="848484848484844646">
    <MapTiles>
      <MapTile TileID="282" AltIDMod="0" />
      <MapTile TileID="283" AltIDMod="0" />
      <MapTile TileID="284" AltIDMod="0" />
      <MapTile TileID="285" AltIDMod="0" />
    </MapTiles>
    <StaticTiles>
      <StaticTile TileID="12914" AltIDMod="0" />
      <StaticTile TileID="12915" AltIDMod="0" />
    </StaticTiles>
  </TransInfo>
  <TransInfo Description="Bottom" HashKey="848484848484844684">
    <MapTiles>
      <MapTile TileID="282" AltIDMod="0" />
      <MapTile TileID="283" AltIDMod="0" />
      <MapTile TileID="284" AltIDMod="0" />
      <MapTile TileID="285" AltIDMod="0" />
    </MapTiles>
    <StaticTiles>
      <StaticTile TileID="12914" AltIDMod="0" />
      <StaticTile TileID="12915" AltIDMod="0" />
    </StaticTiles>
  </TransInfo>
  <TransInfo Description="Bottom" HashKey="848484848484468446">
    <MapTiles>
      <MapTile TileID="282" AltIDMod="0" />
      <MapTile TileID="283" AltIDMod="0" />
      <MapTile TileID="284" AltIDMod="0" />
      <MapTile TileID="285" AltIDMod="0" />
    </MapTiles>
    <StaticTiles>
      <StaticTile TileID="12914" AltIDMod="0" />
      <StaticTile TileID="12915" AltIDMod="0" />
    </StaticTiles>
  </TransInfo>
  <TransInfo Description="Bottom Right" HashKey="848446848446464646">
    <MapTiles>
      <MapTile TileID="282" AltIDMod="0" />
      <MapTile TileID="283" AltIDMod="0" />
      <MapTile TileID="284" AltIDMod="0" />
      <MapTile TileID="285" AltIDMod="0" />
    </MapTiles>
    <StaticTiles>
      <StaticTile TileID="12927" AltIDMod="0" />
    </StaticTiles>
  </TransInfo>
  <TransInfo Description="Bottom Right" HashKey="848484848446464646">
    <MapTiles>
      <MapTile TileID="282" AltIDMod="0" />
      <MapTile TileID="283" AltIDMod="0" />
      <MapTile TileID="284" AltIDMod="0" />
      <MapTile TileID="285" AltIDMod="0" />
    </MapTiles>
    <StaticTiles>
      <StaticTile TileID="12927" AltIDMod="0" />
    </StaticTiles>
  </TransInfo>
  <TransInfo Description="Bottom Right" HashKey="848446848446844646">
    <MapTiles>
      <MapTile TileID="282" AltIDMod="0" />
      <MapTile TileID="283" AltIDMod="0" />
      <MapTile TileID="284" AltIDMod="0" />
      <MapTile TileID="285" AltIDMod="0" />
    </MapTiles>
    <StaticTiles>
      <StaticTile TileID="12927" AltIDMod="0" />
    </StaticTiles>
  </TransInfo>
  <TransInfo Description="Bottom Right" HashKey="848484848446844646">
    <MapTiles>
      <MapTile TileID="282" AltIDMod="0" />
      <MapTile TileID="283" AltIDMod="0" />
      <MapTile TileID="284" AltIDMod="0" />
      <MapTile TileID="285" AltIDMod="0" />
    </MapTiles>
    <StaticTiles>
      <StaticTile TileID="12927" AltIDMod="0" />
    </StaticTiles>
  </TransInfo>
  <TransInfo Description="Bottom Right" HashKey="848484848446844684">
    <MapTiles>
      <MapTile TileID="282" AltIDMod="0" />
      <MapTile TileID="283" AltIDMod="0" />
      <MapTile TileID="284" AltIDMod="0" />
      <MapTile TileID="285" AltIDMod="0" />
    </MapTiles>
    <StaticTiles>
      <StaticTile TileID="12927" AltIDMod="0" />
    </StaticTiles>
  </TransInfo>
  <TransInfo Description="Bottom Right" HashKey="848446848484844646">
    <MapTiles>
      <MapTile TileID="282" AltIDMod="0" />
      <MapTile TileID="283" AltIDMod="0" />
      <MapTile TileID="284" AltIDMod="0" />
      <MapTile TileID="285" AltIDMod="0" />
    </MapTiles>
    <StaticTiles>
      <StaticTile TileID="12927" AltIDMod="0" />
    </StaticTiles>
  </TransInfo>
  <TransInfo Description="Bottom Right" HashKey="848446848484464646">
    <MapTiles>
      <MapTile TileID="282" AltIDMod="0" />
      <MapTile TileID="283" AltIDMod="0" />
      <MapTile TileID="284" AltIDMod="0" />
      <MapTile TileID="285" AltIDMod="0" />
    </MapTiles>
    <StaticTiles>
      <StaticTile TileID="12927" AltIDMod="0" />
    </StaticTiles>
  </TransInfo>
  <TransInfo Description="Bottom Right" HashKey="848446848484464684">
    <MapTiles>
      <MapTile TileID="282" AltIDMod="0" />
      <MapTile TileID="283" AltIDMod="0" />
      <MapTile TileID="284" AltIDMod="0" />
      <MapTile TileID="285" AltIDMod="0" />
    </MapTiles>
    <StaticTiles>
      <StaticTile TileID="12927" AltIDMod="0" />
    </StaticTiles>
  </TransInfo>
  <TransInfo Description="Bottom Right" HashKey="848484848446468446">
    <MapTiles>
      <MapTile TileID="282" AltIDMod="0" />
      <MapTile TileID="283" AltIDMod="0" />
      <MapTile TileID="284" AltIDMod="0" />
      <MapTile TileID="285" AltIDMod="0" />
    </MapTiles>
    <StaticTiles>
      <StaticTile TileID="12927" AltIDMod="0" />
    </StaticTiles>
  </TransInfo>
  <TransInfo Description="Bottom Right" HashKey="848446848446468446">
    <MapTiles>
      <MapTile TileID="282" AltIDMod="0" />
      <MapTile TileID="283" AltIDMod="0" />
      <MapTile TileID="284" AltIDMod="0" />
      <MapTile TileID="285" AltIDMod="0" />
    </MapTiles>
    <StaticTiles>
      <StaticTile TileID="12927" AltIDMod="0" />
    </StaticTiles>
  </TransInfo>
  <TransInfo Description="Bottom Right" HashKey="848446848446464684">
    <MapTiles>
      <MapTile TileID="282" AltIDMod="0" />
      <MapTile TileID="283" AltIDMod="0" />
      <MapTile TileID="284" AltIDMod="0" />
      <MapTile TileID="285" AltIDMod="0" />
    </MapTiles>
    <StaticTiles>
      <StaticTile TileID="12927" AltIDMod="0" />
    </StaticTiles>
  </TransInfo>
  <TransInfo Description="Bottom Right" HashKey="848446848446468484">
    <MapTiles>
      <MapTile TileID="282" AltIDMod="0" />
      <MapTile TileID="283" AltIDMod="0" />
      <MapTile TileID="284" AltIDMod="0" />
      <MapTile TileID="285" AltIDMod="0" />
    </MapTiles>
    <StaticTiles>
      <StaticTile TileID="12927" AltIDMod="0" />
    </StaticTiles>
  </TransInfo>
  <TransInfo Description="Bottom Right" HashKey="848446848484844684">
    <MapTiles>
      <MapTile TileID="282" AltIDMod="0" />
      <MapTile TileID="283" AltIDMod="0" />
      <MapTile TileID="284" AltIDMod="0" />
      <MapTile TileID="285" AltIDMod="0" />
    </MapTiles>
    <StaticTiles>
      <StaticTile TileID="12927" AltIDMod="0" />
    </StaticTiles>
  </TransInfo>
  <TransInfo Description="Bottom Right" HashKey="848484848446468484">
    <MapTiles>
      <MapTile TileID="282" AltIDMod="0" />
      <MapTile TileID="283" AltIDMod="0" />
      <MapTile TileID="284" AltIDMod="0" />
      <MapTile TileID="285" AltIDMod="0" />
    </MapTiles>
    <StaticTiles>
      <StaticTile TileID="12927" AltIDMod="0" />
    </StaticTiles>
  </TransInfo>
  <TransInfo Description="Bottom Right" HashKey="848446848446844684">
    <MapTiles>
      <MapTile TileID="282" AltIDMod="0" />
      <MapTile TileID="283" AltIDMod="0" />
      <MapTile TileID="284" AltIDMod="0" />
      <MapTile TileID="285" AltIDMod="0" />
    </MapTiles>
    <StaticTiles>
      <StaticTile TileID="12927" AltIDMod="0" />
    </StaticTiles>
  </TransInfo>
  <TransInfo Description="Bottom Right" HashKey="848446848484468446">
    <MapTiles>
      <MapTile TileID="282" AltIDMod="0" />
      <MapTile TileID="283" AltIDMod="0" />
      <MapTile TileID="284" AltIDMod="0" />
      <MapTile TileID="285" AltIDMod="0" />
    </MapTiles>
    <StaticTiles>
      <StaticTile TileID="12927" AltIDMod="0" />
    </StaticTiles>
  </TransInfo>
  <TransInfo Description="Bottom Right" HashKey="848484848446464684">
    <MapTiles>
      <MapTile TileID="282" AltIDMod="0" />
      <MapTile TileID="283" AltIDMod="0" />
      <MapTile TileID="284" AltIDMod="0" />
      <MapTile TileID="285" AltIDMod="0" />
    </MapTiles>
    <StaticTiles>
      <StaticTile TileID="12927" AltIDMod="0" />
    </StaticTiles>
  </TransInfo>
  <TransInfo Description="Top Left" HashKey="464646468484468484">
    <MapTiles>
      <MapTile TileID="282" AltIDMod="0" />
      <MapTile TileID="283" AltIDMod="0" />
      <MapTile TileID="284" AltIDMod="0" />
      <MapTile TileID="285" AltIDMod="0" />
    </MapTiles>
    <StaticTiles>
      <StaticTile TileID="12925" AltIDMod="0" />
    </StaticTiles>
  </TransInfo>
  <TransInfo Description="Top Left" HashKey="464684468484468484">
    <MapTiles>
      <MapTile TileID="282" AltIDMod="0" />
      <MapTile TileID="283" AltIDMod="0" />
      <MapTile TileID="284" AltIDMod="0" />
      <MapTile TileID="285" AltIDMod="0" />
    </MapTiles>
    <StaticTiles>
      <StaticTile TileID="12925" AltIDMod="0" />
    </StaticTiles>
  </TransInfo>
  <TransInfo Description="Top Left" HashKey="464646468484848484">
    <MapTiles>
      <MapTile TileID="282" AltIDMod="0" />
      <MapTile TileID="283" AltIDMod="0" />
      <MapTile TileID="284" AltIDMod="0" />
      <MapTile TileID="285" AltIDMod="0" />
    </MapTiles>
    <StaticTiles>
      <StaticTile TileID="12925" AltIDMod="0" />
    </StaticTiles>
  </TransInfo>
  <TransInfo Description="Top Left" HashKey="464684468484848484">
    <MapTiles>
      <MapTile TileID="282" AltIDMod="0" />
      <MapTile TileID="283" AltIDMod="0" />
      <MapTile TileID="284" AltIDMod="0" />
      <MapTile TileID="285" AltIDMod="0" />
    </MapTiles>
    <StaticTiles>
      <StaticTile TileID="12925" AltIDMod="0" />
    </StaticTiles>
  </TransInfo>
  <TransInfo Description="Top Left" HashKey="468446468484848484">
    <MapTiles>
      <MapTile TileID="282" AltIDMod="0" />
      <MapTile TileID="283" AltIDMod="0" />
      <MapTile TileID="284" AltIDMod="0" />
      <MapTile TileID="285" AltIDMod="0" />
    </MapTiles>
    <StaticTiles>
      <StaticTile TileID="12925" AltIDMod="0" />
    </StaticTiles>
  </TransInfo>
  <TransInfo Description="Top Left" HashKey="464684848484468484">
    <MapTiles>
      <MapTile TileID="282" AltIDMod="0" />
      <MapTile TileID="283" AltIDMod="0" />
      <MapTile TileID="284" AltIDMod="0" />
      <MapTile TileID="285" AltIDMod="0" />
    </MapTiles>
    <StaticTiles>
      <StaticTile TileID="12925" AltIDMod="0" />
    </StaticTiles>
  </TransInfo>
  <TransInfo Description="Top Left" HashKey="844646848484468484">
    <MapTiles>
      <MapTile TileID="282" AltIDMod="0" />
      <MapTile TileID="283" AltIDMod="0" />
      <MapTile TileID="284" AltIDMod="0" />
      <MapTile TileID="285" AltIDMod="0" />
    </MapTiles>
    <StaticTiles>
      <StaticTile TileID="12925" AltIDMod="0" />
    </StaticTiles>
  </TransInfo>
  <TransInfo Description="Top Left" HashKey="468446848484468484">
    <MapTiles>
      <MapTile TileID="282" AltIDMod="0" />
      <MapTile TileID="283" AltIDMod="0" />
      <MapTile TileID="284" AltIDMod="0" />
      <MapTile TileID="285" AltIDMod="0" />
    </MapTiles>
    <StaticTiles>
      <StaticTile TileID="12925" AltIDMod="0" />
    </StaticTiles>
  </TransInfo>
  <TransInfo Description="Top Left" HashKey="464646848484468484">
    <MapTiles>
      <MapTile TileID="282" AltIDMod="0" />
      <MapTile TileID="283" AltIDMod="0" />
      <MapTile TileID="284" AltIDMod="0" />
      <MapTile TileID="285" AltIDMod="0" />
    </MapTiles>
    <StaticTiles>
      <StaticTile TileID="12925" AltIDMod="0" />
    </StaticTiles>
  </TransInfo>
  <TransInfo Description="Top Left" HashKey="844684468484848484">
    <MapTiles>
      <MapTile TileID="282" AltIDMod="0" />
      <MapTile TileID="283" AltIDMod="0" />
      <MapTile TileID="284" AltIDMod="0" />
      <MapTile TileID="285" AltIDMod="0" />
    </MapTiles>
    <StaticTiles>
      <StaticTile TileID="12925" AltIDMod="0" />
    </StaticTiles>
  </TransInfo>
  <TransInfo Description="Top Left" HashKey="468446468484468484">
    <MapTiles>
      <MapTile TileID="282" AltIDMod="0" />
      <MapTile TileID="283" AltIDMod="0" />
      <MapTile TileID="284" AltIDMod="0" />
      <MapTile TileID="285" AltIDMod="0" />
    </MapTiles>
    <StaticTiles>
      <StaticTile TileID="12925" AltIDMod="0" />
    </StaticTiles>
  </TransInfo>
  <TransInfo Description="Top Left" HashKey="848446468484468484">
    <MapTiles>
      <MapTile TileID="282" AltIDMod="0" />
      <MapTile TileID="283" AltIDMod="0" />
      <MapTile TileID="284" AltIDMod="0" />
      <MapTile TileID="285" AltIDMod="0" />
    </MapTiles>
    <StaticTiles>
      <StaticTile TileID="12925" AltIDMod="0" />
    </StaticTiles>
  </TransInfo>
  <TransInfo Description="Top Left" HashKey="844646468484468484">
    <MapTiles>
      <MapTile TileID="282" AltIDMod="0" />
      <MapTile TileID="283" AltIDMod="0" />
      <MapTile TileID="284" AltIDMod="0" />
      <MapTile TileID="285" AltIDMod="0" />
    </MapTiles>
    <StaticTiles>
      <StaticTile TileID="12925" AltIDMod="0" />
    </StaticTiles>
  </TransInfo>
  <TransInfo Description="Top Left" HashKey="848446468484848484">
    <MapTiles>
      <MapTile TileID="282" AltIDMod="0" />
      <MapTile TileID="283" AltIDMod="0" />
      <MapTile TileID="284" AltIDMod="0" />
      <MapTile TileID="285" AltIDMod="0" />
    </MapTiles>
    <StaticTiles>
      <StaticTile TileID="12925" AltIDMod="0" />
    </StaticTiles>
  </TransInfo>
  <TransInfo Description="Top Left" HashKey="844684468484468484">
    <MapTiles>
      <MapTile TileID="282" AltIDMod="0" />
      <MapTile TileID="283" AltIDMod="0" />
      <MapTile TileID="284" AltIDMod="0" />
      <MapTile TileID="285" AltIDMod="0" />
    </MapTiles>
    <StaticTiles>
      <StaticTile TileID="12925" AltIDMod="0" />
    </StaticTiles>
  </TransInfo>
  <TransInfo Description="Top Left" HashKey="844684848484468484">
    <MapTiles>
      <MapTile TileID="282" AltIDMod="0" />
      <MapTile TileID="283" AltIDMod="0" />
      <MapTile TileID="284" AltIDMod="0" />
      <MapTile TileID="285" AltIDMod="0" />
    </MapTiles>
    <StaticTiles>
      <StaticTile TileID="12925" AltIDMod="0" />
    </StaticTiles>
  </TransInfo>
  <TransInfo Description="Top Left" HashKey="844646468484848484">
    <MapTiles>
      <MapTile TileID="282" AltIDMod="0" />
      <MapTile TileID="283" AltIDMod="0" />
      <MapTile TileID="284" AltIDMod="0" />
      <MapTile TileID="285" AltIDMod="0" />
    </MapTiles>
    <StaticTiles>
      <StaticTile TileID="12925" AltIDMod="0" />
    </StaticTiles>
  </TransInfo>
  <TransInfo Description="Bottom Left" HashKey="468484468484464646">
    <MapTiles>
      <MapTile TileID="282" AltIDMod="0" />
      <MapTile TileID="283" AltIDMod="0" />
      <MapTile TileID="284" AltIDMod="0" />
      <MapTile TileID="285" AltIDMod="0" />
    </MapTiles>
    <StaticTiles>
      <StaticTile TileID="12924" AltIDMod="0" />
    </StaticTiles>
  </TransInfo>
  <TransInfo Description="Bottom Left" HashKey="848484468484464646">
    <MapTiles>
      <MapTile TileID="282" AltIDMod="0" />
      <MapTile TileID="283" AltIDMod="0" />
      <MapTile TileID="284" AltIDMod="0" />
      <MapTile TileID="285" AltIDMod="0" />
    </MapTiles>
    <StaticTiles>
      <StaticTile TileID="12924" AltIDMod="0" />
    </StaticTiles>
  </TransInfo>
  <TransInfo Description="Bottom Left" HashKey="468484468484464684">
    <MapTiles>
      <MapTile TileID="282" AltIDMod="0" />
      <MapTile TileID="283" AltIDMod="0" />
      <MapTile TileID="284" AltIDMod="0" />
      <MapTile TileID="285" AltIDMod="0" />
    </MapTiles>
    <StaticTiles>
      <StaticTile TileID="12924" AltIDMod="0" />
    </StaticTiles>
  </TransInfo>
  <TransInfo Description="Bottom Left" HashKey="848484468484464684">
    <MapTiles>
      <MapTile TileID="282" AltIDMod="0" />
      <MapTile TileID="283" AltIDMod="0" />
      <MapTile TileID="284" AltIDMod="0" />
      <MapTile TileID="285" AltIDMod="0" />
    </MapTiles>
    <StaticTiles>
      <StaticTile TileID="12924" AltIDMod="0" />
    </StaticTiles>
  </TransInfo>
  <TransInfo Description="Bottom Left" HashKey="848484468484844684">
    <MapTiles>
      <MapTile TileID="282" AltIDMod="0" />
      <MapTile TileID="283" AltIDMod="0" />
      <MapTile TileID="284" AltIDMod="0" />
      <MapTile TileID="285" AltIDMod="0" />
    </MapTiles>
    <StaticTiles>
      <StaticTile TileID="12924" AltIDMod="0" />
    </StaticTiles>
  </TransInfo>
  <TransInfo Description="Bottom Left" HashKey="468484468484848446">
    <MapTiles>
      <MapTile TileID="282" AltIDMod="0" />
      <MapTile TileID="283" AltIDMod="0" />
      <MapTile TileID="284" AltIDMod="0" />
      <MapTile TileID="285" AltIDMod="0" />
    </MapTiles>
    <StaticTiles>
      <StaticTile TileID="12924" AltIDMod="0" />
    </StaticTiles>
  </TransInfo>
  <TransInfo Description="Bottom Left" HashKey="468484848484464646">
    <MapTiles>
      <MapTile TileID="282" AltIDMod="0" />
      <MapTile TileID="283" AltIDMod="0" />
      <MapTile TileID="284" AltIDMod="0" />
      <MapTile TileID="285" AltIDMod="0" />
    </MapTiles>
    <StaticTiles>
      <StaticTile TileID="12924" AltIDMod="0" />
    </StaticTiles>
  </TransInfo>
  <TransInfo Description="Bottom Left" HashKey="468484848484464684">
    <MapTiles>
      <MapTile TileID="282" AltIDMod="0" />
      <MapTile TileID="283" AltIDMod="0" />
      <MapTile TileID="284" AltIDMod="0" />
      <MapTile TileID="285" AltIDMod="0" />
    </MapTiles>
    <StaticTiles>
      <StaticTile TileID="12924" AltIDMod="0" />
    </StaticTiles>
  </TransInfo>
  <TransInfo Description="Bottom Left" HashKey="468484848484844684">
    <MapTiles>
      <MapTile TileID="282" AltIDMod="0" />
      <MapTile TileID="283" AltIDMod="0" />
      <MapTile TileID="284" AltIDMod="0" />
      <MapTile TileID="285" AltIDMod="0" />
    </MapTiles>
    <StaticTiles>
      <StaticTile TileID="12924" AltIDMod="0" />
    </StaticTiles>
  </TransInfo>
  <TransInfo Description="Bottom Left" HashKey="848484468484468446">
    <MapTiles>
      <MapTile TileID="282" AltIDMod="0" />
      <MapTile TileID="283" AltIDMod="0" />
      <MapTile TileID="284" AltIDMod="0" />
      <MapTile TileID="285" AltIDMod="0" />
    </MapTiles>
    <StaticTiles>
      <StaticTile TileID="12924" AltIDMod="0" />
    </StaticTiles>
  </TransInfo>
  <TransInfo Description="Bottom Left" HashKey="468484468484468446">
    <MapTiles>
      <MapTile TileID="282" AltIDMod="0" />
      <MapTile TileID="283" AltIDMod="0" />
      <MapTile TileID="284" AltIDMod="0" />
      <MapTile TileID="285" AltIDMod="0" />
    </MapTiles>
    <StaticTiles>
      <StaticTile TileID="12924" AltIDMod="0" />
    </StaticTiles>
  </TransInfo>
  <TransInfo Description="Bottom Left" HashKey="468484848484844646">
    <MapTiles>
      <MapTile TileID="282" AltIDMod="0" />
      <MapTile TileID="283" AltIDMod="0" />
      <MapTile TileID="284" AltIDMod="0" />
      <MapTile TileID="285" AltIDMod="0" />
    </MapTiles>
    <StaticTiles>
      <StaticTile TileID="12924" AltIDMod="0" />
    </StaticTiles>
  </TransInfo>
  <TransInfo Description="Bottom Left" HashKey="468484468484844646">
    <MapTiles>
      <MapTile TileID="282" AltIDMod="0" />
      <MapTile TileID="283" AltIDMod="0" />
      <MapTile TileID="284" AltIDMod="0" />
      <MapTile TileID="285" AltIDMod="0" />
    </MapTiles>
    <StaticTiles>
      <StaticTile TileID="12924" AltIDMod="0" />
    </StaticTiles>
  </TransInfo>
  <TransInfo Description="Bottom Left" HashKey="848484468484844646">
    <MapTiles>
      <MapTile TileID="282" AltIDMod="0" />
      <MapTile TileID="283" AltIDMod="0" />
      <MapTile TileID="284" AltIDMod="0" />
      <MapTile TileID="285" AltIDMod="0" />
    </MapTiles>
    <StaticTiles>
      <StaticTile TileID="12924" AltIDMod="0" />
    </StaticTiles>
  </TransInfo>
  <TransInfo Description="Bottom Left" HashKey="848484468484848446">
    <MapTiles>
      <MapTile TileID="282" AltIDMod="0" />
      <MapTile TileID="283" AltIDMod="0" />
      <MapTile TileID="284" AltIDMod="0" />
      <MapTile TileID="285" AltIDMod="0" />
    </MapTiles>
    <StaticTiles>
      <StaticTile TileID="12924" AltIDMod="0" />
    </StaticTiles>
  </TransInfo>
  <TransInfo Description="Bottom Left" HashKey="468484848484468446">
    <MapTiles>
      <MapTile TileID="282" AltIDMod="0" />
      <MapTile TileID="283" AltIDMod="0" />
      <MapTile TileID="284" AltIDMod="0" />
      <MapTile TileID="285" AltIDMod="0" />
    </MapTiles>
    <StaticTiles>
      <StaticTile TileID="12924" AltIDMod="0" />
    </StaticTiles>
  </TransInfo>
  <TransInfo Description="Bottom Left" HashKey="468484468484844684">
    <MapTiles>
      <MapTile TileID="282" AltIDMod="0" />
      <MapTile TileID="283" AltIDMod="0" />
      <MapTile TileID="284" AltIDMod="0" />
      <MapTile TileID="285" AltIDMod="0" />
    </MapTiles>
    <StaticTiles>
      <StaticTile TileID="12924" AltIDMod="0" />
    </StaticTiles>
  </TransInfo>
  <TransInfo Description="Top Right" HashKey="464646848446848446">
    <MapTiles>
      <MapTile TileID="282" AltIDMod="0" />
      <MapTile TileID="283" AltIDMod="0" />
      <MapTile TileID="284" AltIDMod="0" />
      <MapTile TileID="285" AltIDMod="0" />
    </MapTiles>
    <StaticTiles>
      <StaticTile TileID="12926" AltIDMod="0" />
    </StaticTiles>
  </TransInfo>
  <TransInfo Description="Top Right" HashKey="464646848446848484">
    <MapTiles>
      <MapTile TileID="282" AltIDMod="0" />
      <MapTile TileID="283" AltIDMod="0" />
      <MapTile TileID="284" AltIDMod="0" />
      <MapTile TileID="285" AltIDMod="0" />
    </MapTiles>
    <StaticTiles>
      <StaticTile TileID="12926" AltIDMod="0" />
    </StaticTiles>
  </TransInfo>
  <TransInfo Description="Top Right" HashKey="844646848446848446">
    <MapTiles>
      <MapTile TileID="282" AltIDMod="0" />
      <MapTile TileID="283" AltIDMod="0" />
      <MapTile TileID="284" AltIDMod="0" />
      <MapTile TileID="285" AltIDMod="0" />
    </MapTiles>
    <StaticTiles>
      <StaticTile TileID="12926" AltIDMod="0" />
    </StaticTiles>
  </TransInfo>
  <TransInfo Description="Top Right" HashKey="844646848446848484">
    <MapTiles>
      <MapTile TileID="282" AltIDMod="0" />
      <MapTile TileID="283" AltIDMod="0" />
      <MapTile TileID="284" AltIDMod="0" />
      <MapTile TileID="285" AltIDMod="0" />
    </MapTiles>
    <StaticTiles>
      <StaticTile TileID="12926" AltIDMod="0" />
    </StaticTiles>
  </TransInfo>
  <TransInfo Description="Top Right" HashKey="468484848446848446">
    <MapTiles>
      <MapTile TileID="282" AltIDMod="0" />
      <MapTile TileID="283" AltIDMod="0" />
      <MapTile TileID="284" AltIDMod="0" />
      <MapTile TileID="285" AltIDMod="0" />
    </MapTiles>
    <StaticTiles>
      <StaticTile TileID="12926" AltIDMod="0" />
    </StaticTiles>
  </TransInfo>
  <TransInfo Description="Top Right" HashKey="468446848446848484">
    <MapTiles>
      <MapTile TileID="282" AltIDMod="0" />
      <MapTile TileID="283" AltIDMod="0" />
      <MapTile TileID="284" AltIDMod="0" />
      <MapTile TileID="285" AltIDMod="0" />
    </MapTiles>
    <StaticTiles>
      <StaticTile TileID="12926" AltIDMod="0" />
    </StaticTiles>
  </TransInfo>
  <TransInfo Description="Top Right" HashKey="468446848446848446">
    <MapTiles>
      <MapTile TileID="282" AltIDMod="0" />
      <MapTile TileID="283" AltIDMod="0" />
      <MapTile TileID="284" AltIDMod="0" />
      <MapTile TileID="285" AltIDMod="0" />
    </MapTiles>
    <StaticTiles>
      <StaticTile TileID="12926" AltIDMod="0" />
    </StaticTiles>
  </TransInfo>
  <TransInfo Description="Top Right" HashKey="464684848484848446">
    <MapTiles>
      <MapTile TileID="282" AltIDMod="0" />
      <MapTile TileID="283" AltIDMod="0" />
      <MapTile TileID="284" AltIDMod="0" />
      <MapTile TileID="285" AltIDMod="0" />
    </MapTiles>
    <StaticTiles>
      <StaticTile TileID="12926" AltIDMod="0" />
    </StaticTiles>
  </TransInfo>
  <TransInfo Description="Top Right" HashKey="844684848484848446">
    <MapTiles>
      <MapTile TileID="282" AltIDMod="0" />
      <MapTile TileID="283" AltIDMod="0" />
      <MapTile TileID="284" AltIDMod="0" />
      <MapTile TileID="285" AltIDMod="0" />
    </MapTiles>
    <StaticTiles>
      <StaticTile TileID="12926" AltIDMod="0" />
    </StaticTiles>
  </TransInfo>
  <TransInfo Description="Top Right" HashKey="464646848484848446">
    <MapTiles>
      <MapTile TileID="282" AltIDMod="0" />
      <MapTile TileID="283" AltIDMod="0" />
      <MapTile TileID="284" AltIDMod="0" />
      <MapTile TileID="285" AltIDMod="0" />
    </MapTiles>
    <StaticTiles>
      <StaticTile TileID="12926" AltIDMod="0" />
    </StaticTiles>
  </TransInfo>
  <TransInfo Description="Top Right" HashKey="464684848446848484">
    <MapTiles>
      <MapTile TileID="282" AltIDMod="0" />
      <MapTile TileID="283" AltIDMod="0" />
      <MapTile TileID="284" AltIDMod="0" />
      <MapTile TileID="285" AltIDMod="0" />
    </MapTiles>
    <StaticTiles>
      <StaticTile TileID="12926" AltIDMod="0" />
    </StaticTiles>
  </TransInfo>
  <TransInfo Description="Top Right" HashKey="844646848484848446">
    <MapTiles>
      <MapTile TileID="282" AltIDMod="0" />
      <MapTile TileID="283" AltIDMod="0" />
      <MapTile TileID="284" AltIDMod="0" />
      <MapTile TileID="285" AltIDMod="0" />
    </MapTiles>
    <StaticTiles>
      <StaticTile TileID="12926" AltIDMod="0" />
    </StaticTiles>
  </TransInfo>
  <TransInfo Description="Top Right" HashKey="844684848446848484">
    <MapTiles>
      <MapTile TileID="282" AltIDMod="0" />
      <MapTile TileID="283" AltIDMod="0" />
      <MapTile TileID="284" AltIDMod="0" />
      <MapTile TileID="285" AltIDMod="0" />
    </MapTiles>
    <StaticTiles>
      <StaticTile TileID="12926" AltIDMod="0" />
    </StaticTiles>
  </TransInfo>
  <TransInfo Description="Top Right" HashKey="468484848446848484">
    <MapTiles>
      <MapTile TileID="282" AltIDMod="0" />
      <MapTile TileID="283" AltIDMod="0" />
      <MapTile TileID="284" AltIDMod="0" />
      <MapTile TileID="285" AltIDMod="0" />
    </MapTiles>
    <StaticTiles>
      <StaticTile TileID="12926" AltIDMod="0" />
    </StaticTiles>
  </TransInfo>
  <TransInfo Description="Top Right" HashKey="468446848484848446">
    <MapTiles>
      <MapTile TileID="282" AltIDMod="0" />
      <MapTile TileID="283" AltIDMod="0" />
      <MapTile TileID="284" AltIDMod="0" />
      <MapTile TileID="285" AltIDMod="0" />
    </MapTiles>
    <StaticTiles>
      <StaticTile TileID="12926" AltIDMod="0" />
    </StaticTiles>
  </TransInfo>
  <TransInfo Description="Top Right" HashKey="844684848446848446">
    <MapTiles>
      <MapTile TileID="282" AltIDMod="0" />
      <MapTile TileID="283" AltIDMod="0" />
      <MapTile TileID="284" AltIDMod="0" />
      <MapTile TileID="285" AltIDMod="0" />
    </MapTiles>
    <StaticTiles>
      <StaticTile TileID="12926" AltIDMod="0" />
    </StaticTiles>
  </TransInfo>
  <TransInfo Description="Top Right" HashKey="464684848446848446">
    <MapTiles>
      <MapTile TileID="282" AltIDMod="0" />
      <MapTile TileID="283" AltIDMod="0" />
      <MapTile TileID="284" AltIDMod="0" />
      <MapTile TileID="285" AltIDMod="0" />
    </MapTiles>
    <StaticTiles>
      <StaticTile TileID="12926" AltIDMod="0" />
    </StaticTiles>
  </TransInfo>
  <TransInfo Description="Outer Top Left" HashKey="468484848484848484">
    <MapTiles>
      <MapTile TileID="282" AltIDMod="0" />
      <MapTile TileID="283" AltIDMod="0" />
      <MapTile TileID="284" AltIDMod="0" />
      <MapTile TileID="285" AltIDMod="0" />
    </MapTiles>
    <StaticTiles>
      <StaticTile TileID="12922" AltIDMod="0" />
      <StaticTile TileID="12932" AltIDMod="0" />
    </StaticTiles>
  </TransInfo>
  <TransInfo Description="Outer Bottom Right" HashKey="848484848484848446">
    <MapTiles>
      <MapTile TileID="282" AltIDMod="0" />
      <MapTile TileID="283" AltIDMod="0" />
      <MapTile TileID="284" AltIDMod="0" />
      <MapTile TileID="285" AltIDMod="0" />
    </MapTiles>
    <StaticTiles>
      <StaticTile TileID="12921" AltIDMod="0" />
      <StaticTile TileID="12930" AltIDMod="0" />
    </StaticTiles>
  </TransInfo>
  <TransInfo Description="Outer Top Right" HashKey="848446848484848484">
    <MapTiles>
      <MapTile TileID="282" AltIDMod="0" />
      <MapTile TileID="283" AltIDMod="0" />
      <MapTile TileID="284" AltIDMod="0" />
      <MapTile TileID="285" AltIDMod="0" />
    </MapTiles>
    <StaticTiles>
      <StaticTile TileID="12923" AltIDMod="0" />
      <StaticTile TileID="12931" AltIDMod="0" />
    </StaticTiles>
  </TransInfo>
  <TransInfo Description="Outer Bottom Left" HashKey="848484848484468484">
    <MapTiles>
      <MapTile TileID="282" AltIDMod="0" />
      <MapTile TileID="283" AltIDMod="0" />
      <MapTile TileID="284" AltIDMod="0" />
      <MapTile TileID="285" AltIDMod="0" />
    </MapTiles>
    <StaticTiles>
      <StaticTile TileID="12920" AltIDMod="0" />
    </StaticTiles>
  </TransInfo>
  <TransInfo Description="Autocorrect" HashKey="848484468446848484">
    <MapTiles>
      <MapTile TileID="15849" AltIDMod="0" />
      <MapTile TileID="15850" AltIDMod="0" />
      <MapTile TileID="15851" AltIDMod="0" />
      <MapTile TileID="15852" AltIDMod="0" />
    </MapTiles>
    <StaticTiles>
    </StaticTiles>
  </TransInfo>
  <TransInfo Description="Autocorrect" HashKey="848484468446468484">
    <MapTiles>
      <MapTile TileID="15849" AltIDMod="0" />
      <MapTile TileID="15850" AltIDMod="0" />
      <MapTile TileID="15851" AltIDMod="0" />
      <MapTile TileID="15852" AltIDMod="0" />
    </MapTiles>
    <StaticTiles>
    </StaticTiles>
  </TransInfo>
  <TransInfo Description="Autocorrect" HashKey="848484468446844684">
    <MapTiles>
      <MapTile TileID="15849" AltIDMod="0" />
      <MapTile TileID="15850" AltIDMod="0" />
      <MapTile TileID="15851" AltIDMod="0" />
      <MapTile TileID="15852" AltIDMod="0" />
    </MapTiles>
    <StaticTiles>
    </StaticTiles>
  </TransInfo>
  <TransInfo Description="Autocorrect" HashKey="848484468446464684">
    <MapTiles>
      <MapTile TileID="15849" AltIDMod="0" />
      <MapTile TileID="15850" AltIDMod="0" />
      <MapTile TileID="15851" AltIDMod="0" />
      <MapTile TileID="15852" AltIDMod="0" />
    </MapTiles>
    <StaticTiles>
    </StaticTiles>
  </TransInfo>
  <TransInfo Description="Autocorrect" HashKey="848484468446848446">
    <MapTiles>
      <MapTile TileID="15849" AltIDMod="0" />
      <MapTile TileID="15850" AltIDMod="0" />
      <MapTile TileID="15851" AltIDMod="0" />
      <MapTile TileID="15852" AltIDMod="0" />
    </MapTiles>
    <StaticTiles>
    </StaticTiles>
  </TransInfo>
  <TransInfo Description="Autocorrect" HashKey="848484468446468446">
    <MapTiles>
      <MapTile TileID="15849" AltIDMod="0" />
      <MapTile TileID="15850" AltIDMod="0" />
      <MapTile TileID="15851" AltIDMod="0" />
      <MapTile TileID="15852" AltIDMod="0" />
    </MapTiles>
    <StaticTiles>
    </StaticTiles>
  </TransInfo>
  <TransInfo Description="Autocorrect" HashKey="848484468446844646">
    <MapTiles>
      <MapTile TileID="15849" AltIDMod="0" />
      <MapTile TileID="15850" AltIDMod="0" />
      <MapTile TileID="15851" AltIDMod="0" />
      <MapTile TileID="15852" AltIDMod="0" />
    </MapTiles>
    <StaticTiles>
    </StaticTiles>
  </TransInfo>
  <TransInfo Description="Autocorrect" HashKey="848484468446464646">
    <MapTiles>
      <MapTile TileID="15849" AltIDMod="0" />
      <MapTile TileID="15850" AltIDMod="0" />
      <MapTile TileID="15851" AltIDMod="0" />
      <MapTile TileID="15852" AltIDMod="0" />
    </MapTiles>
    <StaticTiles>
    </StaticTiles>
  </TransInfo>
  <TransInfo Description="Autocorrect" HashKey="848446468484844684">
    <MapTiles>
      <MapTile TileID="15849" AltIDMod="0" />
      <MapTile TileID="15850" AltIDMod="0" />
      <MapTile TileID="15851" AltIDMod="0" />
      <MapTile TileID="15852" AltIDMod="0" />
    </MapTiles>
    <StaticTiles>
    </StaticTiles>
  </TransInfo>
  <TransInfo Description="Autocorrect" HashKey="848446468484464684">
    <MapTiles>
      <MapTile TileID="15849" AltIDMod="0" />
      <MapTile TileID="15850" AltIDMod="0" />
      <MapTile TileID="15851" AltIDMod="0" />
      <MapTile TileID="15852" AltIDMod="0" />
    </MapTiles>
    <StaticTiles>
    </StaticTiles>
  </TransInfo>
  <TransInfo Description="Autocorrect" HashKey="848446468484848446">
    <MapTiles>
      <MapTile TileID="15849" AltIDMod="0" />
      <MapTile TileID="15850" AltIDMod="0" />
      <MapTile TileID="15851" AltIDMod="0" />
      <MapTile TileID="15852" AltIDMod="0" />
    </MapTiles>
    <StaticTiles>
    </StaticTiles>
  </TransInfo>
  <TransInfo Description="Autocorrect" HashKey="848446468484468446">
    <MapTiles>
      <MapTile TileID="15849" AltIDMod="0" />
      <MapTile TileID="15850" AltIDMod="0" />
      <MapTile TileID="15851" AltIDMod="0" />
      <MapTile TileID="15852" AltIDMod="0" />
    </MapTiles>
    <StaticTiles>
    </StaticTiles>
  </TransInfo>
  <TransInfo Description="Autocorrect" HashKey="848446468484844646">
    <MapTiles>
      <MapTile TileID="15849" AltIDMod="0" />
      <MapTile TileID="15850" AltIDMod="0" />
      <MapTile TileID="15851" AltIDMod="0" />
      <MapTile TileID="15852" AltIDMod="0" />
    </MapTiles>
    <StaticTiles>
    </StaticTiles>
  </TransInfo>
  <TransInfo Description="Autocorrect" HashKey="848446468484464646">
    <MapTiles>
      <MapTile TileID="15849" AltIDMod="0" />
      <MapTile TileID="15850" AltIDMod="0" />
      <MapTile TileID="15851" AltIDMod="0" />
      <MapTile TileID="15852" AltIDMod="0" />
    </MapTiles>
    <StaticTiles>
    </StaticTiles>
  </TransInfo>
  <TransInfo Description="Autocorrect" HashKey="848446468446848484">
    <MapTiles>
      <MapTile TileID="15849" AltIDMod="0" />
      <MapTile TileID="15850" AltIDMod="0" />
      <MapTile TileID="15851" AltIDMod="0" />
      <MapTile TileID="15852" AltIDMod="0" />
    </MapTiles>
    <StaticTiles>
    </StaticTiles>
  </TransInfo>
  <TransInfo Description="Autocorrect" HashKey="848446468446468484">
    <MapTiles>
      <MapTile TileID="15849" AltIDMod="0" />
      <MapTile TileID="15850" AltIDMod="0" />
      <MapTile TileID="15851" AltIDMod="0" />
      <MapTile TileID="15852" AltIDMod="0" />
    </MapTiles>
    <StaticTiles>
    </StaticTiles>
  </TransInfo>
  <TransInfo Description="Autocorrect" HashKey="848446468446844684">
    <MapTiles>
      <MapTile TileID="15849" AltIDMod="0" />
      <MapTile TileID="15850" AltIDMod="0" />
      <MapTile TileID="15851" AltIDMod="0" />
      <MapTile TileID="15852" AltIDMod="0" />
    </MapTiles>
    <StaticTiles>
    </StaticTiles>
  </TransInfo>
  <TransInfo Description="Autocorrect" HashKey="848446468446464684">
    <MapTiles>
      <MapTile TileID="15849" AltIDMod="0" />
      <MapTile TileID="15850" AltIDMod="0" />
      <MapTile TileID="15851" AltIDMod="0" />
      <MapTile TileID="15852" AltIDMod="0" />
    </MapTiles>
    <StaticTiles>
    </StaticTiles>
  </TransInfo>
  <TransInfo Description="Autocorrect" HashKey="848446468446848446">
    <MapTiles>
      <MapTile TileID="15849" AltIDMod="0" />
      <MapTile TileID="15850" AltIDMod="0" />
      <MapTile TileID="15851" AltIDMod="0" />
      <MapTile TileID="15852" AltIDMod="0" />
    </MapTiles>
    <StaticTiles>
    </StaticTiles>
  </TransInfo>
  <TransInfo Description="Autocorrect" HashKey="848446468446468446">
    <MapTiles>
      <MapTile TileID="15849" AltIDMod="0" />
      <MapTile TileID="15850" AltIDMod="0" />
      <MapTile TileID="15851" AltIDMod="0" />
      <MapTile TileID="15852" AltIDMod="0" />
    </MapTiles>
    <StaticTiles>
    </StaticTiles>
  </TransInfo>
  <TransInfo Description="Autocorrect" HashKey="848446468446844646">
    <MapTiles>
      <MapTile TileID="15849" AltIDMod="0" />
      <MapTile TileID="15850" AltIDMod="0" />
      <MapTile TileID="15851" AltIDMod="0" />
      <MapTile TileID="15852" AltIDMod="0" />
    </MapTiles>
    <StaticTiles>
    </StaticTiles>
  </TransInfo>
  <TransInfo Description="Autocorrect" HashKey="848446468446464646">
    <MapTiles>
      <MapTile TileID="15849" AltIDMod="0" />
      <MapTile TileID="15850" AltIDMod="0" />
      <MapTile TileID="15851" AltIDMod="0" />
      <MapTile TileID="15852" AltIDMod="0" />
    </MapTiles>
    <StaticTiles>
    </StaticTiles>
  </TransInfo>
  <TransInfo Description="Autocorrect" HashKey="844684848484844684">
    <MapTiles>
      <MapTile TileID="15849" AltIDMod="0" />
      <MapTile TileID="15850" AltIDMod="0" />
      <MapTile TileID="15851" AltIDMod="0" />
      <MapTile TileID="15852" AltIDMod="0" />
    </MapTiles>
    <StaticTiles>
    </StaticTiles>
  </TransInfo>
  <TransInfo Description="Autocorrect" HashKey="844684468484844684">
    <MapTiles>
      <MapTile TileID="15849" AltIDMod="0" />
      <MapTile TileID="15850" AltIDMod="0" />
      <MapTile TileID="15851" AltIDMod="0" />
      <MapTile TileID="15852" AltIDMod="0" />
    </MapTiles>
    <StaticTiles>
    </StaticTiles>
  </TransInfo>
  <TransInfo Description="Autocorrect" HashKey="844684848484464684">
    <MapTiles>
      <MapTile TileID="15849" AltIDMod="0" />
      <MapTile TileID="15850" AltIDMod="0" />
      <MapTile TileID="15851" AltIDMod="0" />
      <MapTile TileID="15852" AltIDMod="0" />
    </MapTiles>
    <StaticTiles>
    </StaticTiles>
  </TransInfo>
  <TransInfo Description="Autocorrect" HashKey="844684468484464684">
    <MapTiles>
      <MapTile TileID="15849" AltIDMod="0" />
      <MapTile TileID="15850" AltIDMod="0" />
      <MapTile TileID="15851" AltIDMod="0" />
      <MapTile TileID="15852" AltIDMod="0" />
    </MapTiles>
    <StaticTiles>
    </StaticTiles>
  </TransInfo>
  <TransInfo Description="Autocorrect" HashKey="844684468484848446">
    <MapTiles>
      <MapTile TileID="15849" AltIDMod="0" />
      <MapTile TileID="15850" AltIDMod="0" />
      <MapTile TileID="15851" AltIDMod="0" />
      <MapTile TileID="15852" AltIDMod="0" />
    </MapTiles>
    <StaticTiles>
    </StaticTiles>
  </TransInfo>
  <TransInfo Description="Autocorrect" HashKey="844684848484468446">
    <MapTiles>
      <MapTile TileID="15849" AltIDMod="0" />
      <MapTile TileID="15850" AltIDMod="0" />
      <MapTile TileID="15851" AltIDMod="0" />
      <MapTile TileID="15852" AltIDMod="0" />
    </MapTiles>
    <StaticTiles>
    </StaticTiles>
  </TransInfo>
  <TransInfo Description="Autocorrect" HashKey="844684468484468446">
    <MapTiles>
      <MapTile TileID="15849" AltIDMod="0" />
      <MapTile TileID="15850" AltIDMod="0" />
      <MapTile TileID="15851" AltIDMod="0" />
      <MapTile TileID="15852" AltIDMod="0" />
    </MapTiles>
    <StaticTiles>
    </StaticTiles>
  </TransInfo>
  <TransInfo Description="Autocorrect" HashKey="844684848484844646">
    <MapTiles>
      <MapTile TileID="15849" AltIDMod="0" />
      <MapTile TileID="15850" AltIDMod="0" />
      <MapTile TileID="15851" AltIDMod="0" />
      <MapTile TileID="15852" AltIDMod="0" />
    </MapTiles>
    <StaticTiles>
    </StaticTiles>
  </TransInfo>
  <TransInfo Description="Autocorrect" HashKey="844684468484844646">
    <MapTiles>
      <MapTile TileID="15849" AltIDMod="0" />
      <MapTile TileID="15850" AltIDMod="0" />
      <MapTile TileID="15851" AltIDMod="0" />
      <MapTile TileID="15852" AltIDMod="0" />
    </MapTiles>
    <StaticTiles>
    </StaticTiles>
  </TransInfo>
  <TransInfo Description="Autocorrect" HashKey="844684848484464646">
    <MapTiles>
      <MapTile TileID="15849" AltIDMod="0" />
      <MapTile TileID="15850" AltIDMod="0" />
      <MapTile TileID="15851" AltIDMod="0" />
      <MapTile TileID="15852" AltIDMod="0" />
    </MapTiles>
    <StaticTiles>
    </StaticTiles>
  </TransInfo>
  <TransInfo Description="Autocorrect" HashKey="844684468484464646">
    <MapTiles>
      <MapTile TileID="15849" AltIDMod="0" />
      <MapTile TileID="15850" AltIDMod="0" />
      <MapTile TileID="15851" AltIDMod="0" />
      <MapTile TileID="15852" AltIDMod="0" />
    </MapTiles>
    <StaticTiles>
    </StaticTiles>
  </TransInfo>
  <TransInfo Description="Autocorrect" HashKey="844684468446848484">
    <MapTiles>
      <MapTile TileID="15849" AltIDMod="0" />
      <MapTile TileID="15850" AltIDMod="0" />
      <MapTile TileID="15851" AltIDMod="0" />
      <MapTile TileID="15852" AltIDMod="0" />
    </MapTiles>
    <StaticTiles>
    </StaticTiles>
  </TransInfo>
  <TransInfo Description="Autocorrect" HashKey="844684848446468484">
    <MapTiles>
      <MapTile TileID="15849" AltIDMod="0" />
      <MapTile TileID="15850" AltIDMod="0" />
      <MapTile TileID="15851" AltIDMod="0" />
      <MapTile TileID="15852" AltIDMod="0" />
    </MapTiles>
    <StaticTiles>
    </StaticTiles>
  </TransInfo>
  <TransInfo Description="Autocorrect" HashKey="844684468446468484">
    <MapTiles>
      <MapTile TileID="15849" AltIDMod="0" />
      <MapTile TileID="15850" AltIDMod="0" />
      <MapTile TileID="15851" AltIDMod="0" />
      <MapTile TileID="15852" AltIDMod="0" />
    </MapTiles>
    <StaticTiles>
    </StaticTiles>
  </TransInfo>
  <TransInfo Description="Autocorrect" HashKey="844684848446844684">
    <MapTiles>
      <MapTile TileID="15849" AltIDMod="0" />
      <MapTile TileID="15850" AltIDMod="0" />
      <MapTile TileID="15851" AltIDMod="0" />
      <MapTile TileID="15852" AltIDMod="0" />
    </MapTiles>
    <StaticTiles>
    </StaticTiles>
  </TransInfo>
  <TransInfo Description="Autocorrect" HashKey="844684468446844684">
    <MapTiles>
      <MapTile TileID="15849" AltIDMod="0" />
      <MapTile TileID="15850" AltIDMod="0" />
      <MapTile TileID="15851" AltIDMod="0" />
      <MapTile TileID="15852" AltIDMod="0" />
    </MapTiles>
    <StaticTiles>
    </StaticTiles>
  </TransInfo>
  <TransInfo Description="Autocorrect" HashKey="844684848446464684">
    <MapTiles>
      <MapTile TileID="15849" AltIDMod="0" />
      <MapTile TileID="15850" AltIDMod="0" />
      <MapTile TileID="15851" AltIDMod="0" />
      <MapTile TileID="15852" AltIDMod="0" />
    </MapTiles>
    <StaticTiles>
    </StaticTiles>
  </TransInfo>
  <TransInfo Description="Autocorrect" HashKey="844684468446464684">
    <MapTiles>
      <MapTile TileID="15849" AltIDMod="0" />
      <MapTile TileID="15850" AltIDMod="0" />
      <MapTile TileID="15851" AltIDMod="0" />
      <MapTile TileID="15852" AltIDMod="0" />
    </MapTiles>
    <StaticTiles>
    </StaticTiles>
  </TransInfo>
  <TransInfo Description="Autocorrect" HashKey="844684468446848446">
    <MapTiles>
      <MapTile TileID="15849" AltIDMod="0" />
      <MapTile TileID="15850" AltIDMod="0" />
      <MapTile TileID="15851" AltIDMod="0" />
      <MapTile TileID="15852" AltIDMod="0" />
    </MapTiles>
    <StaticTiles>
    </StaticTiles>
  </TransInfo>
  <TransInfo Description="Autocorrect" HashKey="844684848446468446">
    <MapTiles>
      <MapTile TileID="15849" AltIDMod="0" />
      <MapTile TileID="15850" AltIDMod="0" />
      <MapTile TileID="15851" AltIDMod="0" />
      <MapTile TileID="15852" AltIDMod="0" />
    </MapTiles>
    <StaticTiles>
    </StaticTiles>
  </TransInfo>
  <TransInfo Description="Autocorrect" HashKey="844684468446468446">
    <MapTiles>
      <MapTile TileID="15849" AltIDMod="0" />
      <MapTile TileID="15850" AltIDMod="0" />
      <MapTile TileID="15851" AltIDMod="0" />
      <MapTile TileID="15852" AltIDMod="0" />
    </MapTiles>
    <StaticTiles>
    </StaticTiles>
  </TransInfo>
  <TransInfo Description="Autocorrect" HashKey="844684848446844646">
    <MapTiles>
      <MapTile TileID="15849" AltIDMod="0" />
      <MapTile TileID="15850" AltIDMod="0" />
      <MapTile TileID="15851" AltIDMod="0" />
      <MapTile TileID="15852" AltIDMod="0" />
    </MapTiles>
    <StaticTiles>
    </StaticTiles>
  </TransInfo>
  <TransInfo Description="Autocorrect" HashKey="844684468446844646">
    <MapTiles>
      <MapTile TileID="15849" AltIDMod="0" />
      <MapTile TileID="15850" AltIDMod="0" />
      <MapTile TileID="15851" AltIDMod="0" />
      <MapTile TileID="15852" AltIDMod="0" />
    </MapTiles>
    <StaticTiles>
    </StaticTiles>
  </TransInfo>
  <TransInfo Description="Autocorrect" HashKey="844684848446464646">
    <MapTiles>
      <MapTile TileID="15849" AltIDMod="0" />
      <MapTile TileID="15850" AltIDMod="0" />
      <MapTile TileID="15851" AltIDMod="0" />
      <MapTile TileID="15852" AltIDMod="0" />
    </MapTiles>
    <StaticTiles>
    </StaticTiles>
  </TransInfo>
  <TransInfo Description="Autocorrect" HashKey="844684468446464646">
    <MapTiles>
      <MapTile TileID="15849" AltIDMod="0" />
      <MapTile TileID="15850" AltIDMod="0" />
      <MapTile TileID="15851" AltIDMod="0" />
      <MapTile TileID="15852" AltIDMod="0" />
    </MapTiles>
    <StaticTiles>
    </StaticTiles>
  </TransInfo>
  <TransInfo Description="Autocorrect" HashKey="844646848484844684">
    <MapTiles>
      <MapTile TileID="15849" AltIDMod="0" />
      <MapTile TileID="15850" AltIDMod="0" />
      <MapTile TileID="15851" AltIDMod="0" />
      <MapTile TileID="15852" AltIDMod="0" />
    </MapTiles>
    <StaticTiles>
    </StaticTiles>
  </TransInfo>
  <TransInfo Description="Autocorrect" HashKey="844646468484844684">
    <MapTiles>
      <MapTile TileID="15849" AltIDMod="0" />
      <MapTile TileID="15850" AltIDMod="0" />
      <MapTile TileID="15851" AltIDMod="0" />
      <MapTile TileID="15852" AltIDMod="0" />
    </MapTiles>
    <StaticTiles>
    </StaticTiles>
  </TransInfo>
  <TransInfo Description="Autocorrect" HashKey="844646848484464684">
    <MapTiles>
      <MapTile TileID="15849" AltIDMod="0" />
      <MapTile TileID="15850" AltIDMod="0" />
      <MapTile TileID="15851" AltIDMod="0" />
      <MapTile TileID="15852" AltIDMod="0" />
    </MapTiles>
    <StaticTiles>
    </StaticTiles>
  </TransInfo>
  <TransInfo Description="Autocorrect" HashKey="844646468484464684">
    <MapTiles>
      <MapTile TileID="15849" AltIDMod="0" />
      <MapTile TileID="15850" AltIDMod="0" />
      <MapTile TileID="15851" AltIDMod="0" />
      <MapTile TileID="15852" AltIDMod="0" />
    </MapTiles>
    <StaticTiles>
    </StaticTiles>
  </TransInfo>
  <TransInfo Description="Autocorrect" HashKey="844646468484848446">
    <MapTiles>
      <MapTile TileID="15849" AltIDMod="0" />
      <MapTile TileID="15850" AltIDMod="0" />
      <MapTile TileID="15851" AltIDMod="0" />
      <MapTile TileID="15852" AltIDMod="0" />
    </MapTiles>
    <StaticTiles>
    </StaticTiles>
  </TransInfo>
  <TransInfo Description="Autocorrect" HashKey="844646848484468446">
    <MapTiles>
      <MapTile TileID="15849" AltIDMod="0" />
      <MapTile TileID="15850" AltIDMod="0" />
      <MapTile TileID="15851" AltIDMod="0" />
      <MapTile TileID="15852" AltIDMod="0" />
    </MapTiles>
    <StaticTiles>
    </StaticTiles>
  </TransInfo>
  <TransInfo Description="Autocorrect" HashKey="844646468484468446">
    <MapTiles>
      <MapTile TileID="15849" AltIDMod="0" />
      <MapTile TileID="15850" AltIDMod="0" />
      <MapTile TileID="15851" AltIDMod="0" />
      <MapTile TileID="15852" AltIDMod="0" />
    </MapTiles>
    <StaticTiles>
    </StaticTiles>
  </TransInfo>
  <TransInfo Description="Autocorrect" HashKey="844646848484844646">
    <MapTiles>
      <MapTile TileID="15849" AltIDMod="0" />
      <MapTile TileID="15850" AltIDMod="0" />
      <MapTile TileID="15851" AltIDMod="0" />
      <MapTile TileID="15852" AltIDMod="0" />
    </MapTiles>
    <StaticTiles>
    </StaticTiles>
  </TransInfo>
  <TransInfo Description="Autocorrect" HashKey="844646468484844646">
    <MapTiles>
      <MapTile TileID="15849" AltIDMod="0" />
      <MapTile TileID="15850" AltIDMod="0" />
      <MapTile TileID="15851" AltIDMod="0" />
      <MapTile TileID="15852" AltIDMod="0" />
    </MapTiles>
    <StaticTiles>
    </StaticTiles>
  </TransInfo>
  <TransInfo Description="Autocorrect" HashKey="844646848484464646">
    <MapTiles>
      <MapTile TileID="15849" AltIDMod="0" />
      <MapTile TileID="15850" AltIDMod="0" />
      <MapTile TileID="15851" AltIDMod="0" />
      <MapTile TileID="15852" AltIDMod="0" />
    </MapTiles>
    <StaticTiles>
    </StaticTiles>
  </TransInfo>
  <TransInfo Description="Autocorrect" HashKey="844646468484464646">
    <MapTiles>
      <MapTile TileID="15849" AltIDMod="0" />
      <MapTile TileID="15850" AltIDMod="0" />
      <MapTile TileID="15851" AltIDMod="0" />
      <MapTile TileID="15852" AltIDMod="0" />
    </MapTiles>
    <StaticTiles>
    </StaticTiles>
  </TransInfo>
  <TransInfo Description="Autocorrect" HashKey="844646468446848484">
    <MapTiles>
      <MapTile TileID="15849" AltIDMod="0" />
      <MapTile TileID="15850" AltIDMod="0" />
      <MapTile TileID="15851" AltIDMod="0" />
      <MapTile TileID="15852" AltIDMod="0" />
    </MapTiles>
    <StaticTiles>
    </StaticTiles>
  </TransInfo>
  <TransInfo Description="Autocorrect" HashKey="844646848446468484">
    <MapTiles>
      <MapTile TileID="15849" AltIDMod="0" />
      <MapTile TileID="15850" AltIDMod="0" />
      <MapTile TileID="15851" AltIDMod="0" />
      <MapTile TileID="15852" AltIDMod="0" />
    </MapTiles>
    <StaticTiles>
    </StaticTiles>
  </TransInfo>
  <TransInfo Description="Autocorrect" HashKey="844646468446468484">
    <MapTiles>
      <MapTile TileID="15849" AltIDMod="0" />
      <MapTile TileID="15850" AltIDMod="0" />
      <MapTile TileID="15851" AltIDMod="0" />
      <MapTile TileID="15852" AltIDMod="0" />
    </MapTiles>
    <StaticTiles>
    </StaticTiles>
  </TransInfo>
  <TransInfo Description="Autocorrect" HashKey="844646848446844684">
    <MapTiles>
      <MapTile TileID="15849" AltIDMod="0" />
      <MapTile TileID="15850" AltIDMod="0" />
      <MapTile TileID="15851" AltIDMod="0" />
      <MapTile TileID="15852" AltIDMod="0" />
    </MapTiles>
    <StaticTiles>
    </StaticTiles>
  </TransInfo>
  <TransInfo Description="Autocorrect" HashKey="844646468446844684">
    <MapTiles>
      <MapTile TileID="15849" AltIDMod="0" />
      <MapTile TileID="15850" AltIDMod="0" />
      <MapTile TileID="15851" AltIDMod="0" />
      <MapTile TileID="15852" AltIDMod="0" />
    </MapTiles>
    <StaticTiles>
    </StaticTiles>
  </TransInfo>
  <TransInfo Description="Autocorrect" HashKey="844646848446464684">
    <MapTiles>
      <MapTile TileID="15849" AltIDMod="0" />
      <MapTile TileID="15850" AltIDMod="0" />
      <MapTile TileID="15851" AltIDMod="0" />
      <MapTile TileID="15852" AltIDMod="0" />
    </MapTiles>
    <StaticTiles>
    </StaticTiles>
  </TransInfo>
  <TransInfo Description="Autocorrect" HashKey="844646468446464684">
    <MapTiles>
      <MapTile TileID="15849" AltIDMod="0" />
      <MapTile TileID="15850" AltIDMod="0" />
      <MapTile TileID="15851" AltIDMod="0" />
      <MapTile TileID="15852" AltIDMod="0" />
    </MapTiles>
    <StaticTiles>
    </StaticTiles>
  </TransInfo>
  <TransInfo Description="Autocorrect" HashKey="844646468446848446">
    <MapTiles>
      <MapTile TileID="15849" AltIDMod="0" />
      <MapTile TileID="15850" AltIDMod="0" />
      <MapTile TileID="15851" AltIDMod="0" />
      <MapTile TileID="15852" AltIDMod="0" />
    </MapTiles>
    <StaticTiles>
    </StaticTiles>
  </TransInfo>
  <TransInfo Description="Autocorrect" HashKey="844646848446468446">
    <MapTiles>
      <MapTile TileID="15849" AltIDMod="0" />
      <MapTile TileID="15850" AltIDMod="0" />
      <MapTile TileID="15851" AltIDMod="0" />
      <MapTile TileID="15852" AltIDMod="0" />
    </MapTiles>
    <StaticTiles>
    </StaticTiles>
  </TransInfo>
  <TransInfo Description="Autocorrect" HashKey="844646468446468446">
    <MapTiles>
      <MapTile TileID="15849" AltIDMod="0" />
      <MapTile TileID="15850" AltIDMod="0" />
      <MapTile TileID="15851" AltIDMod="0" />
      <MapTile TileID="15852" AltIDMod="0" />
    </MapTiles>
    <StaticTiles>
    </StaticTiles>
  </TransInfo>
  <TransInfo Description="Autocorrect" HashKey="844646848446844646">
    <MapTiles>
      <MapTile TileID="15849" AltIDMod="0" />
      <MapTile TileID="15850" AltIDMod="0" />
      <MapTile TileID="15851" AltIDMod="0" />
      <MapTile TileID="15852" AltIDMod="0" />
    </MapTiles>
    <StaticTiles>
    </StaticTiles>
  </TransInfo>
  <TransInfo Description="Autocorrect" HashKey="844646468446844646">
    <MapTiles>
      <MapTile TileID="15849" AltIDMod="0" />
      <MapTile TileID="15850" AltIDMod="0" />
      <MapTile TileID="15851" AltIDMod="0" />
      <MapTile TileID="15852" AltIDMod="0" />
    </MapTiles>
    <StaticTiles>
    </StaticTiles>
  </TransInfo>
  <TransInfo Description="Autocorrect" HashKey="844646848446464646">
    <MapTiles>
      <MapTile TileID="15849" AltIDMod="0" />
      <MapTile TileID="15850" AltIDMod="0" />
      <MapTile TileID="15851" AltIDMod="0" />
      <MapTile TileID="15852" AltIDMod="0" />
    </MapTiles>
    <StaticTiles>
    </StaticTiles>
  </TransInfo>
  <TransInfo Description="Autocorrect" HashKey="844646468446464646">
    <MapTiles>
      <MapTile TileID="15849" AltIDMod="0" />
      <MapTile TileID="15850" AltIDMod="0" />
      <MapTile TileID="15851" AltIDMod="0" />
      <MapTile TileID="15852" AltIDMod="0" />
    </MapTiles>
    <StaticTiles>
    </StaticTiles>
  </TransInfo>
  <TransInfo Description="Autocorrect" HashKey="468484468446848484">
    <MapTiles>
      <MapTile TileID="15849" AltIDMod="0" />
      <MapTile TileID="15850" AltIDMod="0" />
      <MapTile TileID="15851" AltIDMod="0" />
      <MapTile TileID="15852" AltIDMod="0" />
    </MapTiles>
    <StaticTiles>
    </StaticTiles>
  </TransInfo>
  <TransInfo Description="Autocorrect" HashKey="468484848446468484">
    <MapTiles>
      <MapTile TileID="15849" AltIDMod="0" />
      <MapTile TileID="15850" AltIDMod="0" />
      <MapTile TileID="15851" AltIDMod="0" />
      <MapTile TileID="15852" AltIDMod="0" />
    </MapTiles>
    <StaticTiles>
    </StaticTiles>
  </TransInfo>
  <TransInfo Description="Autocorrect" HashKey="468484468446468484">
    <MapTiles>
      <MapTile TileID="15849" AltIDMod="0" />
      <MapTile TileID="15850" AltIDMod="0" />
      <MapTile TileID="15851" AltIDMod="0" />
      <MapTile TileID="15852" AltIDMod="0" />
    </MapTiles>
    <StaticTiles>
    </StaticTiles>
  </TransInfo>
  <TransInfo Description="Autocorrect" HashKey="468484848446844684">
    <MapTiles>
      <MapTile TileID="15849" AltIDMod="0" />
      <MapTile TileID="15850" AltIDMod="0" />
      <MapTile TileID="15851" AltIDMod="0" />
      <MapTile TileID="15852" AltIDMod="0" />
    </MapTiles>
    <StaticTiles>
    </StaticTiles>
  </TransInfo>
  <TransInfo Description="Autocorrect" HashKey="468484468446844684">
    <MapTiles>
      <MapTile TileID="15849" AltIDMod="0" />
      <MapTile TileID="15850" AltIDMod="0" />
      <MapTile TileID="15851" AltIDMod="0" />
      <MapTile TileID="15852" AltIDMod="0" />
    </MapTiles>
    <StaticTiles>
    </StaticTiles>
  </TransInfo>
  <TransInfo Description="Autocorrect" HashKey="468484848446464684">
    <MapTiles>
      <MapTile TileID="15849" AltIDMod="0" />
      <MapTile TileID="15850" AltIDMod="0" />
      <MapTile TileID="15851" AltIDMod="0" />
      <MapTile TileID="15852" AltIDMod="0" />
    </MapTiles>
    <StaticTiles>
    </StaticTiles>
  </TransInfo>
  <TransInfo Description="Autocorrect" HashKey="468484468446464684">
    <MapTiles>
      <MapTile TileID="15849" AltIDMod="0" />
      <MapTile TileID="15850" AltIDMod="0" />
      <MapTile TileID="15851" AltIDMod="0" />
      <MapTile TileID="15852" AltIDMod="0" />
    </MapTiles>
    <StaticTiles>
    </StaticTiles>
  </TransInfo>
  <TransInfo Description="Autocorrect" HashKey="468484468446848446">
    <MapTiles>
      <MapTile TileID="15849" AltIDMod="0" />
      <MapTile TileID="15850" AltIDMod="0" />
      <MapTile TileID="15851" AltIDMod="0" />
      <MapTile TileID="15852" AltIDMod="0" />
    </MapTiles>
    <StaticTiles>
    </StaticTiles>
  </TransInfo>
  <TransInfo Description="Autocorrect" HashKey="468484848446468446">
    <MapTiles>
      <MapTile TileID="15849" AltIDMod="0" />
      <MapTile TileID="15850" AltIDMod="0" />
      <MapTile TileID="15851" AltIDMod="0" />
      <MapTile TileID="15852" AltIDMod="0" />
    </MapTiles>
    <StaticTiles>
    </StaticTiles>
  </TransInfo>
  <TransInfo Description="Autocorrect" HashKey="468484468446468446">
    <MapTiles>
      <MapTile TileID="15849" AltIDMod="0" />
      <MapTile TileID="15850" AltIDMod="0" />
      <MapTile TileID="15851" AltIDMod="0" />
      <MapTile TileID="15852" AltIDMod="0" />
    </MapTiles>
    <StaticTiles>
    </StaticTiles>
  </TransInfo>
  <TransInfo Description="Autocorrect" HashKey="468484848446844646">
    <MapTiles>
      <MapTile TileID="15849" AltIDMod="0" />
      <MapTile TileID="15850" AltIDMod="0" />
      <MapTile TileID="15851" AltIDMod="0" />
      <MapTile TileID="15852" AltIDMod="0" />
    </MapTiles>
    <StaticTiles>
    </StaticTiles>
  </TransInfo>
  <TransInfo Description="Autocorrect" HashKey="468484468446844646">
    <MapTiles>
      <MapTile TileID="15849" AltIDMod="0" />
      <MapTile TileID="15850" AltIDMod="0" />
      <MapTile TileID="15851" AltIDMod="0" />
      <MapTile TileID="15852" AltIDMod="0" />
    </MapTiles>
    <StaticTiles>
    </StaticTiles>
  </TransInfo>
  <TransInfo Description="Autocorrect" HashKey="468484848446464646">
    <MapTiles>
      <MapTile TileID="15849" AltIDMod="0" />
      <MapTile TileID="15850" AltIDMod="0" />
      <MapTile TileID="15851" AltIDMod="0" />
      <MapTile TileID="15852" AltIDMod="0" />
    </MapTiles>
    <StaticTiles>
    </StaticTiles>
  </TransInfo>
  <TransInfo Description="Autocorrect" HashKey="468484468446464646">
    <MapTiles>
      <MapTile TileID="15849" AltIDMod="0" />
      <MapTile TileID="15850" AltIDMod="0" />
      <MapTile TileID="15851" AltIDMod="0" />
      <MapTile TileID="15852" AltIDMod="0" />
    </MapTiles>
    <StaticTiles>
    </StaticTiles>
  </TransInfo>
  <TransInfo Description="Autocorrect" HashKey="468446848484844684">
    <MapTiles>
      <MapTile TileID="15849" AltIDMod="0" />
      <MapTile TileID="15850" AltIDMod="0" />
      <MapTile TileID="15851" AltIDMod="0" />
      <MapTile TileID="15852" AltIDMod="0" />
    </MapTiles>
    <StaticTiles>
    </StaticTiles>
  </TransInfo>
  <TransInfo Description="Autocorrect" HashKey="468446468484844684">
    <MapTiles>
      <MapTile TileID="15849" AltIDMod="0" />
      <MapTile TileID="15850" AltIDMod="0" />
      <MapTile TileID="15851" AltIDMod="0" />
      <MapTile TileID="15852" AltIDMod="0" />
    </MapTiles>
    <StaticTiles>
    </StaticTiles>
  </TransInfo>
  <TransInfo Description="Autocorrect" HashKey="468446848484464684">
    <MapTiles>
      <MapTile TileID="15849" AltIDMod="0" />
      <MapTile TileID="15850" AltIDMod="0" />
      <MapTile TileID="15851" AltIDMod="0" />
      <MapTile TileID="15852" AltIDMod="0" />
    </MapTiles>
    <StaticTiles>
    </StaticTiles>
  </TransInfo>
  <TransInfo Description="Autocorrect" HashKey="468446468484464684">
    <MapTiles>
      <MapTile TileID="15849" AltIDMod="0" />
      <MapTile TileID="15850" AltIDMod="0" />
      <MapTile TileID="15851" AltIDMod="0" />
      <MapTile TileID="15852" AltIDMod="0" />
    </MapTiles>
    <StaticTiles>
    </StaticTiles>
  </TransInfo>
  <TransInfo Description="Autocorrect" HashKey="468446468484848446">
    <MapTiles>
      <MapTile TileID="15849" AltIDMod="0" />
      <MapTile TileID="15850" AltIDMod="0" />
      <MapTile TileID="15851" AltIDMod="0" />
      <MapTile TileID="15852" AltIDMod="0" />
    </MapTiles>
    <StaticTiles>
    </StaticTiles>
  </TransInfo>
  <TransInfo Description="Autocorrect" HashKey="468446848484468446">
    <MapTiles>
      <MapTile TileID="15849" AltIDMod="0" />
      <MapTile TileID="15850" AltIDMod="0" />
      <MapTile TileID="15851" AltIDMod="0" />
      <MapTile TileID="15852" AltIDMod="0" />
    </MapTiles>
    <StaticTiles>
    </StaticTiles>
  </TransInfo>
  <TransInfo Description="Autocorrect" HashKey="468446468484468446">
    <MapTiles>
      <MapTile TileID="15849" AltIDMod="0" />
      <MapTile TileID="15850" AltIDMod="0" />
      <MapTile TileID="15851" AltIDMod="0" />
      <MapTile TileID="15852" AltIDMod="0" />
    </MapTiles>
    <StaticTiles>
    </StaticTiles>
  </TransInfo>
  <TransInfo Description="Autocorrect" HashKey="468446848484844646">
    <MapTiles>
      <MapTile TileID="15849" AltIDMod="0" />
      <MapTile TileID="15850" AltIDMod="0" />
      <MapTile TileID="15851" AltIDMod="0" />
      <MapTile TileID="15852" AltIDMod="0" />
    </MapTiles>
    <StaticTiles>
    </StaticTiles>
  </TransInfo>
  <TransInfo Description="Autocorrect" HashKey="468446468484844646">
    <MapTiles>
      <MapTile TileID="15849" AltIDMod="0" />
      <MapTile TileID="15850" AltIDMod="0" />
      <MapTile TileID="15851" AltIDMod="0" />
      <MapTile TileID="15852" AltIDMod="0" />
    </MapTiles>
    <StaticTiles>
    </StaticTiles>
  </TransInfo>
  <TransInfo Description="Autocorrect" HashKey="468446848484464646">
    <MapTiles>
      <MapTile TileID="15849" AltIDMod="0" />
      <MapTile TileID="15850" AltIDMod="0" />
      <MapTile TileID="15851" AltIDMod="0" />
      <MapTile TileID="15852" AltIDMod="0" />
    </MapTiles>
    <StaticTiles>
    </StaticTiles>
  </TransInfo>
  <TransInfo Description="Autocorrect" HashKey="468446468484464646">
    <MapTiles>
      <MapTile TileID="15849" AltIDMod="0" />
      <MapTile TileID="15850" AltIDMod="0" />
      <MapTile TileID="15851" AltIDMod="0" />
      <MapTile TileID="15852" AltIDMod="0" />
    </MapTiles>
    <StaticTiles>
    </StaticTiles>
  </TransInfo>
  <TransInfo Description="Autocorrect" HashKey="468446468446848484">
    <MapTiles>
      <MapTile TileID="15849" AltIDMod="0" />
      <MapTile TileID="15850" AltIDMod="0" />
      <MapTile TileID="15851" AltIDMod="0" />
      <MapTile TileID="15852" AltIDMod="0" />
    </MapTiles>
    <StaticTiles>
    </StaticTiles>
  </TransInfo>
  <TransInfo Description="Autocorrect" HashKey="468446848446468484">
    <MapTiles>
      <MapTile TileID="15849" AltIDMod="0" />
      <MapTile TileID="15850" AltIDMod="0" />
      <MapTile TileID="15851" AltIDMod="0" />
      <MapTile TileID="15852" AltIDMod="0" />
    </MapTiles>
    <StaticTiles>
    </StaticTiles>
  </TransInfo>
  <TransInfo Description="Autocorrect" HashKey="468446468446468484">
    <MapTiles>
      <MapTile TileID="15849" AltIDMod="0" />
      <MapTile TileID="15850" AltIDMod="0" />
      <MapTile TileID="15851" AltIDMod="0" />
      <MapTile TileID="15852" AltIDMod="0" />
    </MapTiles>
    <StaticTiles>
    </StaticTiles>
  </TransInfo>
  <TransInfo Description="Autocorrect" HashKey="468446848446844684">
    <MapTiles>
      <MapTile TileID="15849" AltIDMod="0" />
      <MapTile TileID="15850" AltIDMod="0" />
      <MapTile TileID="15851" AltIDMod="0" />
      <MapTile TileID="15852" AltIDMod="0" />
    </MapTiles>
    <StaticTiles>
    </StaticTiles>
  </TransInfo>
  <TransInfo Description="Autocorrect" HashKey="468446468446844684">
    <MapTiles>
      <MapTile TileID="15849" AltIDMod="0" />
      <MapTile TileID="15850" AltIDMod="0" />
      <MapTile TileID="15851" AltIDMod="0" />
      <MapTile TileID="15852" AltIDMod="0" />
    </MapTiles>
    <StaticTiles>
    </StaticTiles>
  </TransInfo>
  <TransInfo Description="Autocorrect" HashKey="468446848446464684">
    <MapTiles>
      <MapTile TileID="15849" AltIDMod="0" />
      <MapTile TileID="15850" AltIDMod="0" />
      <MapTile TileID="15851" AltIDMod="0" />
      <MapTile TileID="15852" AltIDMod="0" />
    </MapTiles>
    <StaticTiles>
    </StaticTiles>
  </TransInfo>
  <TransInfo Description="Autocorrect" HashKey="468446468446464684">
    <MapTiles>
      <MapTile TileID="15849" AltIDMod="0" />
      <MapTile TileID="15850" AltIDMod="0" />
      <MapTile TileID="15851" AltIDMod="0" />
      <MapTile TileID="15852" AltIDMod="0" />
    </MapTiles>
    <StaticTiles>
    </StaticTiles>
  </TransInfo>
  <TransInfo Description="Autocorrect" HashKey="468446468446848446">
    <MapTiles>
      <MapTile TileID="15849" AltIDMod="0" />
      <MapTile TileID="15850" AltIDMod="0" />
      <MapTile TileID="15851" AltIDMod="0" />
      <MapTile TileID="15852" AltIDMod="0" />
    </MapTiles>
    <StaticTiles>
    </StaticTiles>
  </TransInfo>
  <TransInfo Description="Autocorrect" HashKey="468446848446468446">
    <MapTiles>
      <MapTile TileID="15849" AltIDMod="0" />
      <MapTile TileID="15850" AltIDMod="0" />
      <MapTile TileID="15851" AltIDMod="0" />
      <MapTile TileID="15852" AltIDMod="0" />
    </MapTiles>
    <StaticTiles>
    </StaticTiles>
  </TransInfo>
  <TransInfo Description="Autocorrect" HashKey="468446468446468446">
    <MapTiles>
      <MapTile TileID="15849" AltIDMod="0" />
      <MapTile TileID="15850" AltIDMod="0" />
      <MapTile TileID="15851" AltIDMod="0" />
      <MapTile TileID="15852" AltIDMod="0" />
    </MapTiles>
    <StaticTiles>
    </StaticTiles>
  </TransInfo>
  <TransInfo Description="Autocorrect" HashKey="468446848446844646">
    <MapTiles>
      <MapTile TileID="15849" AltIDMod="0" />
      <MapTile TileID="15850" AltIDMod="0" />
      <MapTile TileID="15851" AltIDMod="0" />
      <MapTile TileID="15852" AltIDMod="0" />
    </MapTiles>
    <StaticTiles>
    </StaticTiles>
  </TransInfo>
  <TransInfo Description="Autocorrect" HashKey="468446468446844646">
    <MapTiles>
      <MapTile TileID="15849" AltIDMod="0" />
      <MapTile TileID="15850" AltIDMod="0" />
      <MapTile TileID="15851" AltIDMod="0" />
      <MapTile TileID="15852" AltIDMod="0" />
    </MapTiles>
    <StaticTiles>
    </StaticTiles>
  </TransInfo>
  <TransInfo Description="Autocorrect" HashKey="468446848446464646">
    <MapTiles>
      <MapTile TileID="15849" AltIDMod="0" />
      <MapTile TileID="15850" AltIDMod="0" />
      <MapTile TileID="15851" AltIDMod="0" />
      <MapTile TileID="15852" AltIDMod="0" />
    </MapTiles>
    <StaticTiles>
    </StaticTiles>
  </TransInfo>
  <TransInfo Description="Autocorrect" HashKey="468446468446464646">
    <MapTiles>
      <MapTile TileID="15849" AltIDMod="0" />
      <MapTile TileID="15850" AltIDMod="0" />
      <MapTile TileID="15851" AltIDMod="0" />
      <MapTile TileID="15852" AltIDMod="0" />
    </MapTiles>
    <StaticTiles>
    </StaticTiles>
  </TransInfo>
  <TransInfo Description="Autocorrect" HashKey="464684848484844684">
    <MapTiles>
      <MapTile TileID="15849" AltIDMod="0" />
      <MapTile TileID="15850" AltIDMod="0" />
      <MapTile TileID="15851" AltIDMod="0" />
      <MapTile TileID="15852" AltIDMod="0" />
    </MapTiles>
    <StaticTiles>
    </StaticTiles>
  </TransInfo>
  <TransInfo Description="Autocorrect" HashKey="464684468484844684">
    <MapTiles>
      <MapTile TileID="15849" AltIDMod="0" />
      <MapTile TileID="15850" AltIDMod="0" />
      <MapTile TileID="15851" AltIDMod="0" />
      <MapTile TileID="15852" AltIDMod="0" />
    </MapTiles>
    <StaticTiles>
    </StaticTiles>
  </TransInfo>
  <TransInfo Description="Autocorrect" HashKey="464684848484464684">
    <MapTiles>
      <MapTile TileID="15849" AltIDMod="0" />
      <MapTile TileID="15850" AltIDMod="0" />
      <MapTile TileID="15851" AltIDMod="0" />
      <MapTile TileID="15852" AltIDMod="0" />
    </MapTiles>
    <StaticTiles>
    </StaticTiles>
  </TransInfo>
  <TransInfo Description="Autocorrect" HashKey="464684468484464684">
    <MapTiles>
      <MapTile TileID="15849" AltIDMod="0" />
      <MapTile TileID="15850" AltIDMod="0" />
      <MapTile TileID="15851" AltIDMod="0" />
      <MapTile TileID="15852" AltIDMod="0" />
    </MapTiles>
    <StaticTiles>
    </StaticTiles>
  </TransInfo>
  <TransInfo Description="Autocorrect" HashKey="464684468484848446">
    <MapTiles>
      <MapTile TileID="15849" AltIDMod="0" />
      <MapTile TileID="15850" AltIDMod="0" />
      <MapTile TileID="15851" AltIDMod="0" />
      <MapTile TileID="15852" AltIDMod="0" />
    </MapTiles>
    <StaticTiles>
    </StaticTiles>
  </TransInfo>
  <TransInfo Description="Autocorrect" HashKey="464684848484468446">
    <MapTiles>
      <MapTile TileID="15849" AltIDMod="0" />
      <MapTile TileID="15850" AltIDMod="0" />
      <MapTile TileID="15851" AltIDMod="0" />
      <MapTile TileID="15852" AltIDMod="0" />
    </MapTiles>
    <StaticTiles>
    </StaticTiles>
  </TransInfo>
  <TransInfo Description="Autocorrect" HashKey="464684468484468446">
    <MapTiles>
      <MapTile TileID="15849" AltIDMod="0" />
      <MapTile TileID="15850" AltIDMod="0" />
      <MapTile TileID="15851" AltIDMod="0" />
      <MapTile TileID="15852" AltIDMod="0" />
    </MapTiles>
    <StaticTiles>
    </StaticTiles>
  </TransInfo>
  <TransInfo Description="Autocorrect" HashKey="464684848484844646">
    <MapTiles>
      <MapTile TileID="15849" AltIDMod="0" />
      <MapTile TileID="15850" AltIDMod="0" />
      <MapTile TileID="15851" AltIDMod="0" />
      <MapTile TileID="15852" AltIDMod="0" />
    </MapTiles>
    <StaticTiles>
    </StaticTiles>
  </TransInfo>
  <TransInfo Description="Autocorrect" HashKey="464684468484844646">
    <MapTiles>
      <MapTile TileID="15849" AltIDMod="0" />
      <MapTile TileID="15850" AltIDMod="0" />
      <MapTile TileID="15851" AltIDMod="0" />
      <MapTile TileID="15852" AltIDMod="0" />
    </MapTiles>
    <StaticTiles>
    </StaticTiles>
  </TransInfo>
  <TransInfo Description="Autocorrect" HashKey="464684848484464646">
    <MapTiles>
      <MapTile TileID="15849" AltIDMod="0" />
      <MapTile TileID="15850" AltIDMod="0" />
      <MapTile TileID="15851" AltIDMod="0" />
      <MapTile TileID="15852" AltIDMod="0" />
    </MapTiles>
    <StaticTiles>
    </StaticTiles>
  </TransInfo>
  <TransInfo Description="Autocorrect" HashKey="464684468484464646">
    <MapTiles>
      <MapTile TileID="15849" AltIDMod="0" />
      <MapTile TileID="15850" AltIDMod="0" />
      <MapTile TileID="15851" AltIDMod="0" />
      <MapTile TileID="15852" AltIDMod="0" />
    </MapTiles>
    <StaticTiles>
    </StaticTiles>
  </TransInfo>
  <TransInfo Description="Autocorrect" HashKey="464684468446848484">
    <MapTiles>
      <MapTile TileID="15849" AltIDMod="0" />
      <MapTile TileID="15850" AltIDMod="0" />
      <MapTile TileID="15851" AltIDMod="0" />
      <MapTile TileID="15852" AltIDMod="0" />
    </MapTiles>
    <StaticTiles>
    </StaticTiles>
  </TransInfo>
  <TransInfo Description="Autocorrect" HashKey="464684848446468484">
    <MapTiles>
      <MapTile TileID="15849" AltIDMod="0" />
      <MapTile TileID="15850" AltIDMod="0" />
      <MapTile TileID="15851" AltIDMod="0" />
      <MapTile TileID="15852" AltIDMod="0" />
    </MapTiles>
    <StaticTiles>
    </StaticTiles>
  </TransInfo>
  <TransInfo Description="Autocorrect" HashKey="464684468446468484">
    <MapTiles>
      <MapTile TileID="15849" AltIDMod="0" />
      <MapTile TileID="15850" AltIDMod="0" />
      <MapTile TileID="15851" AltIDMod="0" />
      <MapTile TileID="15852" AltIDMod="0" />
    </MapTiles>
    <StaticTiles>
    </StaticTiles>
  </TransInfo>
  <TransInfo Description="Autocorrect" HashKey="464684848446844684">
    <MapTiles>
      <MapTile TileID="15849" AltIDMod="0" />
      <MapTile TileID="15850" AltIDMod="0" />
      <MapTile TileID="15851" AltIDMod="0" />
      <MapTile TileID="15852" AltIDMod="0" />
    </MapTiles>
    <StaticTiles>
    </StaticTiles>
  </TransInfo>
  <TransInfo Description="Autocorrect" HashKey="464684468446844684">
    <MapTiles>
      <MapTile TileID="15849" AltIDMod="0" />
      <MapTile TileID="15850" AltIDMod="0" />
      <MapTile TileID="15851" AltIDMod="0" />
      <MapTile TileID="15852" AltIDMod="0" />
    </MapTiles>
    <StaticTiles>
    </StaticTiles>
  </TransInfo>
  <TransInfo Description="Autocorrect" HashKey="464684848446464684">
    <MapTiles>
      <MapTile TileID="15849" AltIDMod="0" />
      <MapTile TileID="15850" AltIDMod="0" />
      <MapTile TileID="15851" AltIDMod="0" />
      <MapTile TileID="15852" AltIDMod="0" />
    </MapTiles>
    <StaticTiles>
    </StaticTiles>
  </TransInfo>
  <TransInfo Description="Autocorrect" HashKey="464684468446464684">
    <MapTiles>
      <MapTile TileID="15849" AltIDMod="0" />
      <MapTile TileID="15850" AltIDMod="0" />
      <MapTile TileID="15851" AltIDMod="0" />
      <MapTile TileID="15852" AltIDMod="0" />
    </MapTiles>
    <StaticTiles>
    </StaticTiles>
  </TransInfo>
  <TransInfo Description="Autocorrect" HashKey="464684468446848446">
    <MapTiles>
      <MapTile TileID="15849" AltIDMod="0" />
      <MapTile TileID="15850" AltIDMod="0" />
      <MapTile TileID="15851" AltIDMod="0" />
      <MapTile TileID="15852" AltIDMod="0" />
    </MapTiles>
    <StaticTiles>
    </StaticTiles>
  </TransInfo>
  <TransInfo Description="Autocorrect" HashKey="464684848446468446">
    <MapTiles>
      <MapTile TileID="15849" AltIDMod="0" />
      <MapTile TileID="15850" AltIDMod="0" />
      <MapTile TileID="15851" AltIDMod="0" />
      <MapTile TileID="15852" AltIDMod="0" />
    </MapTiles>
    <StaticTiles>
    </StaticTiles>
  </TransInfo>
  <TransInfo Description="Autocorrect" HashKey="464684468446468446">
    <MapTiles>
      <MapTile TileID="15849" AltIDMod="0" />
      <MapTile TileID="15850" AltIDMod="0" />
      <MapTile TileID="15851" AltIDMod="0" />
      <MapTile TileID="15852" AltIDMod="0" />
    </MapTiles>
    <StaticTiles>
    </StaticTiles>
  </TransInfo>
  <TransInfo Description="Autocorrect" HashKey="464684848446844646">
    <MapTiles>
      <MapTile TileID="15849" AltIDMod="0" />
      <MapTile TileID="15850" AltIDMod="0" />
      <MapTile TileID="15851" AltIDMod="0" />
      <MapTile TileID="15852" AltIDMod="0" />
    </MapTiles>
    <StaticTiles>
    </StaticTiles>
  </TransInfo>
  <TransInfo Description="Autocorrect" HashKey="464684468446844646">
    <MapTiles>
      <MapTile TileID="15849" AltIDMod="0" />
      <MapTile TileID="15850" AltIDMod="0" />
      <MapTile TileID="15851" AltIDMod="0" />
      <MapTile TileID="15852" AltIDMod="0" />
    </MapTiles>
    <StaticTiles>
    </StaticTiles>
  </TransInfo>
  <TransInfo Description="Autocorrect" HashKey="464684848446464646">
    <MapTiles>
      <MapTile TileID="15849" AltIDMod="0" />
      <MapTile TileID="15850" AltIDMod="0" />
      <MapTile TileID="15851" AltIDMod="0" />
      <MapTile TileID="15852" AltIDMod="0" />
    </MapTiles>
    <StaticTiles>
    </StaticTiles>
  </TransInfo>
  <TransInfo Description="Autocorrect" HashKey="464684468446464646">
    <MapTiles>
      <MapTile TileID="15849" AltIDMod="0" />
      <MapTile TileID="15850" AltIDMod="0" />
      <MapTile TileID="15851" AltIDMod="0" />
      <MapTile TileID="15852" AltIDMod="0" />
    </MapTiles>
    <StaticTiles>
    </StaticTiles>
  </TransInfo>
  <TransInfo Description="Autocorrect" HashKey="464646848484844684">
    <MapTiles>
      <MapTile TileID="15849" AltIDMod="0" />
      <MapTile TileID="15850" AltIDMod="0" />
      <MapTile TileID="15851" AltIDMod="0" />
      <MapTile TileID="15852" AltIDMod="0" />
    </MapTiles>
    <StaticTiles>
    </StaticTiles>
  </TransInfo>
  <TransInfo Description="Autocorrect" HashKey="464646468484844684">
    <MapTiles>
      <MapTile TileID="15849" AltIDMod="0" />
      <MapTile TileID="15850" AltIDMod="0" />
      <MapTile TileID="15851" AltIDMod="0" />
      <MapTile TileID="15852" AltIDMod="0" />
    </MapTiles>
    <StaticTiles>
    </StaticTiles>
  </TransInfo>
  <TransInfo Description="Autocorrect" HashKey="464646848484464684">
    <MapTiles>
      <MapTile TileID="15849" AltIDMod="0" />
      <MapTile TileID="15850" AltIDMod="0" />
      <MapTile TileID="15851" AltIDMod="0" />
      <MapTile TileID="15852" AltIDMod="0" />
    </MapTiles>
    <StaticTiles>
    </StaticTiles>
  </TransInfo>
  <TransInfo Description="Autocorrect" HashKey="464646468484464684">
    <MapTiles>
      <MapTile TileID="15849" AltIDMod="0" />
      <MapTile TileID="15850" AltIDMod="0" />
      <MapTile TileID="15851" AltIDMod="0" />
      <MapTile TileID="15852" AltIDMod="0" />
    </MapTiles>
    <StaticTiles>
    </StaticTiles>
  </TransInfo>
  <TransInfo Description="Autocorrect" HashKey="464646468484848446">
    <MapTiles>
      <MapTile TileID="15849" AltIDMod="0" />
      <MapTile TileID="15850" AltIDMod="0" />
      <MapTile TileID="15851" AltIDMod="0" />
      <MapTile TileID="15852" AltIDMod="0" />
    </MapTiles>
    <StaticTiles>
    </StaticTiles>
  </TransInfo>
  <TransInfo Description="Autocorrect" HashKey="464646848484468446">
    <MapTiles>
      <MapTile TileID="15849" AltIDMod="0" />
      <MapTile TileID="15850" AltIDMod="0" />
      <MapTile TileID="15851" AltIDMod="0" />
      <MapTile TileID="15852" AltIDMod="0" />
    </MapTiles>
    <StaticTiles>
    </StaticTiles>
  </TransInfo>
  <TransInfo Description="Autocorrect" HashKey="464646468484468446">
    <MapTiles>
      <MapTile TileID="15849" AltIDMod="0" />
      <MapTile TileID="15850" AltIDMod="0" />
      <MapTile TileID="15851" AltIDMod="0" />
      <MapTile TileID="15852" AltIDMod="0" />
    </MapTiles>
    <StaticTiles>
    </StaticTiles>
  </TransInfo>
  <TransInfo Description="Autocorrect" HashKey="464646848484844646">
    <MapTiles>
      <MapTile TileID="15849" AltIDMod="0" />
      <MapTile TileID="15850" AltIDMod="0" />
      <MapTile TileID="15851" AltIDMod="0" />
      <MapTile TileID="15852" AltIDMod="0" />
    </MapTiles>
    <StaticTiles>
    </StaticTiles>
  </TransInfo>
  <TransInfo Description="Autocorrect" HashKey="464646468484844646">
    <MapTiles>
      <MapTile TileID="15849" AltIDMod="0" />
      <MapTile TileID="15850" AltIDMod="0" />
      <MapTile TileID="15851" AltIDMod="0" />
      <MapTile TileID="15852" AltIDMod="0" />
    </MapTiles>
    <StaticTiles>
    </StaticTiles>
  </TransInfo>
  <TransInfo Description="Autocorrect" HashKey="464646848484464646">
    <MapTiles>
      <MapTile TileID="15849" AltIDMod="0" />
      <MapTile TileID="15850" AltIDMod="0" />
      <MapTile TileID="15851" AltIDMod="0" />
      <MapTile TileID="15852" AltIDMod="0" />
    </MapTiles>
    <StaticTiles>
    </StaticTiles>
  </TransInfo>
  <TransInfo Description="Autocorrect" HashKey="464646468484464646">
    <MapTiles>
      <MapTile TileID="15849" AltIDMod="0" />
      <MapTile TileID="15850" AltIDMod="0" />
      <MapTile TileID="15851" AltIDMod="0" />
      <MapTile TileID="15852" AltIDMod="0" />
    </MapTiles>
    <StaticTiles>
    </StaticTiles>
  </TransInfo>
  <TransInfo Description="Autocorrect" HashKey="464646468446848484">
    <MapTiles>
      <MapTile TileID="15849" AltIDMod="0" />
      <MapTile TileID="15850" AltIDMod="0" />
      <MapTile TileID="15851" AltIDMod="0" />
      <MapTile TileID="15852" AltIDMod="0" />
    </MapTiles>
    <StaticTiles>
    </StaticTiles>
  </TransInfo>
  <TransInfo Description="Autocorrect" HashKey="464646848446468484">
    <MapTiles>
      <MapTile TileID="15849" AltIDMod="0" />
      <MapTile TileID="15850" AltIDMod="0" />
      <MapTile TileID="15851" AltIDMod="0" />
      <MapTile TileID="15852" AltIDMod="0" />
    </MapTiles>
    <StaticTiles>
    </StaticTiles>
  </TransInfo>
  <TransInfo Description="Autocorrect" HashKey="464646468446468484">
    <MapTiles>
      <MapTile TileID="15849" AltIDMod="0" />
      <MapTile TileID="15850" AltIDMod="0" />
      <MapTile TileID="15851" AltIDMod="0" />
      <MapTile TileID="15852" AltIDMod="0" />
    </MapTiles>
    <StaticTiles>
    </StaticTiles>
  </TransInfo>
  <TransInfo Description="Autocorrect" HashKey="464646848446844684">
    <MapTiles>
      <MapTile TileID="15849" AltIDMod="0" />
      <MapTile TileID="15850" AltIDMod="0" />
      <MapTile TileID="15851" AltIDMod="0" />
      <MapTile TileID="15852" AltIDMod="0" />
    </MapTiles>
    <StaticTiles>
    </StaticTiles>
  </TransInfo>
  <TransInfo Description="Autocorrect" HashKey="464646468446844684">
    <MapTiles>
      <MapTile TileID="15849" AltIDMod="0" />
      <MapTile TileID="15850" AltIDMod="0" />
      <MapTile TileID="15851" AltIDMod="0" />
      <MapTile TileID="15852" AltIDMod="0" />
    </MapTiles>
    <StaticTiles>
    </StaticTiles>
  </TransInfo>
  <TransInfo Description="Autocorrect" HashKey="464646848446464684">
    <MapTiles>
      <MapTile TileID="15849" AltIDMod="0" />
      <MapTile TileID="15850" AltIDMod="0" />
      <MapTile TileID="15851" AltIDMod="0" />
      <MapTile TileID="15852" AltIDMod="0" />
    </MapTiles>
    <StaticTiles>
    </StaticTiles>
  </TransInfo>
  <TransInfo Description="Autocorrect" HashKey="464646468446464684">
    <MapTiles>
      <MapTile TileID="15849" AltIDMod="0" />
      <MapTile TileID="15850" AltIDMod="0" />
      <MapTile TileID="15851" AltIDMod="0" />
      <MapTile TileID="15852" AltIDMod="0" />
    </MapTiles>
    <StaticTiles>
    </StaticTiles>
  </TransInfo>
  <TransInfo Description="Autocorrect" HashKey="464646468446848446">
    <MapTiles>
      <MapTile TileID="15849" AltIDMod="0" />
      <MapTile TileID="15850" AltIDMod="0" />
      <MapTile TileID="15851" AltIDMod="0" />
      <MapTile TileID="15852" AltIDMod="0" />
    </MapTiles>
    <StaticTiles>
    </StaticTiles>
  </TransInfo>
  <TransInfo Description="Autocorrect" HashKey="464646848446468446">
    <MapTiles>
      <MapTile TileID="15849" AltIDMod="0" />
      <MapTile TileID="15850" AltIDMod="0" />
      <MapTile TileID="15851" AltIDMod="0" />
      <MapTile TileID="15852" AltIDMod="0" />
    </MapTiles>
    <StaticTiles>
    </StaticTiles>
  </TransInfo>
  <TransInfo Description="Autocorrect" HashKey="464646468446468446">
    <MapTiles>
      <MapTile TileID="15849" AltIDMod="0" />
      <MapTile TileID="15850" AltIDMod="0" />
      <MapTile TileID="15851" AltIDMod="0" />
      <MapTile TileID="15852" AltIDMod="0" />
    </MapTiles>
    <StaticTiles>
    </StaticTiles>
  </TransInfo>
  <TransInfo Description="Autocorrect" HashKey="464646848446844646">
    <MapTiles>
      <MapTile TileID="15849" AltIDMod="0" />
      <MapTile TileID="15850" AltIDMod="0" />
      <MapTile TileID="15851" AltIDMod="0" />
      <MapTile TileID="15852" AltIDMod="0" />
    </MapTiles>
    <StaticTiles>
    </StaticTiles>
  </TransInfo>
  <TransInfo Description="Autocorrect" HashKey="464646468446844646">
    <MapTiles>
      <MapTile TileID="15849" AltIDMod="0" />
      <MapTile TileID="15850" AltIDMod="0" />
      <MapTile TileID="15851" AltIDMod="0" />
      <MapTile TileID="15852" AltIDMod="0" />
    </MapTiles>
    <StaticTiles>
    </StaticTiles>
  </TransInfo>
  <TransInfo Description="Autocorrect" HashKey="464646848446464646">
    <MapTiles>
      <MapTile TileID="15849" AltIDMod="0" />
      <MapTile TileID="15850" AltIDMod="0" />
      <MapTile TileID="15851" AltIDMod="0" />
      <MapTile TileID="15852" AltIDMod="0" />
    </MapTiles>
    <StaticTiles>
    </StaticTiles>
  </TransInfo>
  <TransInfo Description="Autocorrect" HashKey="464646468446464646">
    <MapTiles>
      <MapTile TileID="15849" AltIDMod="0" />
      <MapTile TileID="15850" AltIDMod="0" />
      <MapTile TileID="15851" AltIDMod="0" />
      <MapTile TileID="15852" AltIDMod="0" />
    </MapTiles>
    <StaticTiles>
    </StaticTiles>
  </TransInfo>
  <TransInfo Description="Invalid" HashKey="468484848484848446">
    <MapTiles>
      <MapTile TileID="282" AltIDMod="0" />
      <MapTile TileID="283" AltIDMod="0" />
      <MapTile TileID="284" AltIDMod="0" />
      <MapTile TileID="285" AltIDMod="0" />
    </MapTiles>
    <StaticTiles>
    </StaticTiles>
  </TransInfo>
  <TransInfo Description="Invalid" HashKey="848446848484468484">
    <MapTiles>
      <MapTile TileID="282" AltIDMod="0" />
      <MapTile TileID="283" AltIDMod="0" />
      <MapTile TileID="284" AltIDMod="0" />
      <MapTile TileID="285" AltIDMod="0" />
    </MapTiles>
    <StaticTiles>
    </StaticTiles>
  </TransInfo>
</Trans>