<?xml version="1.0" encoding="utf-8"?>
<Trans>
  <TransInfo Description="Top" HashKey="808080121212121212">
    <MapTiles>
      <MapTile TileID="569" AltIDMod="0" />
    </MapTiles>
    <StaticTiles>
    </StaticTiles>
  </TransInfo>
  <TransInfo Description="Top" HashKey="128080121212121212">
    <MapTiles>
      <MapTile TileID="569" AltIDMod="0" />
    </MapTiles>
    <StaticTiles>
    </StaticTiles>
  </TransInfo>
  <TransInfo Description="Top" HashKey="808012121212121212">
    <MapTiles>
      <MapTile TileID="569" AltIDMod="0" />
    </MapTiles>
    <StaticTiles>
    </StaticTiles>
  </TransInfo>
  <TransInfo Description="Top" HashKey="128012121212121212">
    <MapTiles>
      <MapTile TileID="569" AltIDMod="0" />
    </MapTiles>
    <StaticTiles>
    </StaticTiles>
  </TransInfo>
  <TransInfo Description="Top" HashKey="801280121212121212">
    <MapTiles>
      <MapTile TileID="569" AltIDMod="0" />
    </MapTiles>
    <StaticTiles>
    </StaticTiles>
  </TransInfo>
  <TransInfo Description="Left" HashKey="801212801212801212">
    <MapTiles>
      <MapTile TileID="572" AltIDMod="0" />
    </MapTiles>
    <StaticTiles>
    </StaticTiles>
  </TransInfo>
  <TransInfo Description="Left" HashKey="801212801212121212">
    <MapTiles>
      <MapTile TileID="572" AltIDMod="0" />
    </MapTiles>
    <StaticTiles>
    </StaticTiles>
  </TransInfo>
  <TransInfo Description="Left" HashKey="121212801212801212">
    <MapTiles>
      <MapTile TileID="572" AltIDMod="0" />
    </MapTiles>
    <StaticTiles>
    </StaticTiles>
  </TransInfo>
  <TransInfo Description="Left" HashKey="121212801212121212">
    <MapTiles>
      <MapTile TileID="572" AltIDMod="0" />
    </MapTiles>
    <StaticTiles>
    </StaticTiles>
  </TransInfo>
  <TransInfo Description="Left" HashKey="801212121212801212">
    <MapTiles>
      <MapTile TileID="572" AltIDMod="0" />
    </MapTiles>
    <StaticTiles>
    </StaticTiles>
  </TransInfo>
  <TransInfo Description="Right" HashKey="121280121280121280">
    <MapTiles>
      <MapTile TileID="570" AltIDMod="0" />
    </MapTiles>
    <StaticTiles>
    </StaticTiles>
  </TransInfo>
  <TransInfo Description="Right" HashKey="121212121280121280">
    <MapTiles>
      <MapTile TileID="570" AltIDMod="0" />
    </MapTiles>
    <StaticTiles>
    </StaticTiles>
  </TransInfo>
  <TransInfo Description="Right" HashKey="121280121280121212">
    <MapTiles>
      <MapTile TileID="570" AltIDMod="0" />
    </MapTiles>
    <StaticTiles>
    </StaticTiles>
  </TransInfo>
  <TransInfo Description="Right" HashKey="121212121280121212">
    <MapTiles>
      <MapTile TileID="570" AltIDMod="0" />
    </MapTiles>
    <StaticTiles>
    </StaticTiles>
  </TransInfo>
  <TransInfo Description="Right" HashKey="121280121212121280">
    <MapTiles>
      <MapTile TileID="570" AltIDMod="0" />
    </MapTiles>
    <StaticTiles>
    </StaticTiles>
  </TransInfo>
  <TransInfo Description="Bottom" HashKey="121212121212808080">
    <MapTiles>
      <MapTile TileID="571" AltIDMod="0" />
    </MapTiles>
    <StaticTiles>
    </StaticTiles>
  </TransInfo>
  <TransInfo Description="Bottom" HashKey="121212121212808012">
    <MapTiles>
      <MapTile TileID="571" AltIDMod="0" />
    </MapTiles>
    <StaticTiles>
    </StaticTiles>
  </TransInfo>
  <TransInfo Description="Bottom" HashKey="121212121212128080">
    <MapTiles>
      <MapTile TileID="571" AltIDMod="0" />
    </MapTiles>
    <StaticTiles>
    </StaticTiles>
  </TransInfo>
  <TransInfo Description="Bottom" HashKey="121212121212128012">
    <MapTiles>
      <MapTile TileID="571" AltIDMod="0" />
    </MapTiles>
    <StaticTiles>
    </StaticTiles>
  </TransInfo>
  <TransInfo Description="Bottom" HashKey="121212121212801280">
    <MapTiles>
      <MapTile TileID="571" AltIDMod="0" />
    </MapTiles>
    <StaticTiles>
    </StaticTiles>
  </TransInfo>
  <TransInfo Description="Bottom Right" HashKey="121280121280808080">
    <MapTiles>
      <MapTile TileID="563" AltIDMod="0" />
    </MapTiles>
    <StaticTiles>
    </StaticTiles>
  </TransInfo>
  <TransInfo Description="Bottom Right" HashKey="121212121280808080">
    <MapTiles>
      <MapTile TileID="563" AltIDMod="0" />
    </MapTiles>
    <StaticTiles>
    </StaticTiles>
  </TransInfo>
  <TransInfo Description="Bottom Right" HashKey="121280121280128080">
    <MapTiles>
      <MapTile TileID="563" AltIDMod="0" />
    </MapTiles>
    <StaticTiles>
    </StaticTiles>
  </TransInfo>
  <TransInfo Description="Bottom Right" HashKey="121212121280128080">
    <MapTiles>
      <MapTile TileID="563" AltIDMod="0" />
    </MapTiles>
    <StaticTiles>
    </StaticTiles>
  </TransInfo>
  <TransInfo Description="Bottom Right" HashKey="121212121280128012">
    <MapTiles>
      <MapTile TileID="563" AltIDMod="0" />
    </MapTiles>
    <StaticTiles>
    </StaticTiles>
  </TransInfo>
  <TransInfo Description="Bottom Right" HashKey="121280121212128080">
    <MapTiles>
      <MapTile TileID="563" AltIDMod="0" />
    </MapTiles>
    <StaticTiles>
    </StaticTiles>
  </TransInfo>
  <TransInfo Description="Bottom Right" HashKey="121280121212808080">
    <MapTiles>
      <MapTile TileID="563" AltIDMod="0" />
    </MapTiles>
    <StaticTiles>
    </StaticTiles>
  </TransInfo>
  <TransInfo Description="Bottom Right" HashKey="121280121212808012">
    <MapTiles>
      <MapTile TileID="563" AltIDMod="0" />
    </MapTiles>
    <StaticTiles>
    </StaticTiles>
  </TransInfo>
  <TransInfo Description="Bottom Right" HashKey="121212121280801280">
    <MapTiles>
      <MapTile TileID="563" AltIDMod="0" />
    </MapTiles>
    <StaticTiles>
    </StaticTiles>
  </TransInfo>
  <TransInfo Description="Bottom Right" HashKey="121280121280801280">
    <MapTiles>
      <MapTile TileID="563" AltIDMod="0" />
    </MapTiles>
    <StaticTiles>
    </StaticTiles>
  </TransInfo>
  <TransInfo Description="Bottom Right" HashKey="121280121280808012">
    <MapTiles>
      <MapTile TileID="563" AltIDMod="0" />
    </MapTiles>
    <StaticTiles>
    </StaticTiles>
  </TransInfo>
  <TransInfo Description="Bottom Right" HashKey="121280121280801212">
    <MapTiles>
      <MapTile TileID="563" AltIDMod="0" />
    </MapTiles>
    <StaticTiles>
    </StaticTiles>
  </TransInfo>
  <TransInfo Description="Bottom Right" HashKey="121280121212128012">
    <MapTiles>
      <MapTile TileID="563" AltIDMod="0" />
    </MapTiles>
    <StaticTiles>
    </StaticTiles>
  </TransInfo>
  <TransInfo Description="Bottom Right" HashKey="121212121280801212">
    <MapTiles>
      <MapTile TileID="563" AltIDMod="0" />
    </MapTiles>
    <StaticTiles>
    </StaticTiles>
  </TransInfo>
  <TransInfo Description="Bottom Right" HashKey="121280121280128012">
    <MapTiles>
      <MapTile TileID="563" AltIDMod="0" />
    </MapTiles>
    <StaticTiles>
    </StaticTiles>
  </TransInfo>
  <TransInfo Description="Bottom Right" HashKey="121280121212801280">
    <MapTiles>
      <MapTile TileID="563" AltIDMod="0" />
    </MapTiles>
    <StaticTiles>
    </StaticTiles>
  </TransInfo>
  <TransInfo Description="Bottom Right" HashKey="121212121280808012">
    <MapTiles>
      <MapTile TileID="563" AltIDMod="0" />
    </MapTiles>
    <StaticTiles>
    </StaticTiles>
  </TransInfo>
  <TransInfo Description="Top Left" HashKey="808080801212801212">
    <MapTiles>
      <MapTile TileID="561" AltIDMod="0" />
    </MapTiles>
    <StaticTiles>
    </StaticTiles>
  </TransInfo>
  <TransInfo Description="Top Left" HashKey="808012801212801212">
    <MapTiles>
      <MapTile TileID="561" AltIDMod="0" />
    </MapTiles>
    <StaticTiles>
    </StaticTiles>
  </TransInfo>
  <TransInfo Description="Top Left" HashKey="808080801212121212">
    <MapTiles>
      <MapTile TileID="561" AltIDMod="0" />
    </MapTiles>
    <StaticTiles>
    </StaticTiles>
  </TransInfo>
  <TransInfo Description="Top Left" HashKey="808012801212121212">
    <MapTiles>
      <MapTile TileID="561" AltIDMod="0" />
    </MapTiles>
    <StaticTiles>
    </StaticTiles>
  </TransInfo>
  <TransInfo Description="Top Left" HashKey="801280801212121212">
    <MapTiles>
      <MapTile TileID="561" AltIDMod="0" />
    </MapTiles>
    <StaticTiles>
    </StaticTiles>
  </TransInfo>
  <TransInfo Description="Top Left" HashKey="808012121212801212">
    <MapTiles>
      <MapTile TileID="561" AltIDMod="0" />
    </MapTiles>
    <StaticTiles>
    </StaticTiles>
  </TransInfo>
  <TransInfo Description="Top Left" HashKey="128080121212801212">
    <MapTiles>
      <MapTile TileID="561" AltIDMod="0" />
    </MapTiles>
    <StaticTiles>
    </StaticTiles>
  </TransInfo>
  <TransInfo Description="Top Left" HashKey="801280121212801212">
    <MapTiles>
      <MapTile TileID="561" AltIDMod="0" />
    </MapTiles>
    <StaticTiles>
    </StaticTiles>
  </TransInfo>
  <TransInfo Description="Top Left" HashKey="808080121212801212">
    <MapTiles>
      <MapTile TileID="561" AltIDMod="0" />
    </MapTiles>
    <StaticTiles>
    </StaticTiles>
  </TransInfo>
  <TransInfo Description="Top Left" HashKey="128012801212121212">
    <MapTiles>
      <MapTile TileID="561" AltIDMod="0" />
    </MapTiles>
    <StaticTiles>
    </StaticTiles>
  </TransInfo>
  <TransInfo Description="Top Left" HashKey="801280801212801212">
    <MapTiles>
      <MapTile TileID="561" AltIDMod="0" />
    </MapTiles>
    <StaticTiles>
    </StaticTiles>
  </TransInfo>
  <TransInfo Description="Top Left" HashKey="121280801212801212">
    <MapTiles>
      <MapTile TileID="561" AltIDMod="0" />
    </MapTiles>
    <StaticTiles>
    </StaticTiles>
  </TransInfo>
  <TransInfo Description="Top Left" HashKey="128080801212801212">
    <MapTiles>
      <MapTile TileID="561" AltIDMod="0" />
    </MapTiles>
    <StaticTiles>
    </StaticTiles>
  </TransInfo>
  <TransInfo Description="Top Left" HashKey="121280801212121212">
    <MapTiles>
      <MapTile TileID="561" AltIDMod="0" />
    </MapTiles>
    <StaticTiles>
    </StaticTiles>
  </TransInfo>
  <TransInfo Description="Top Left" HashKey="128012801212801212">
    <MapTiles>
      <MapTile TileID="561" AltIDMod="0" />
    </MapTiles>
    <StaticTiles>
    </StaticTiles>
  </TransInfo>
  <TransInfo Description="Top Left" HashKey="128012121212801212">
    <MapTiles>
      <MapTile TileID="561" AltIDMod="0" />
    </MapTiles>
    <StaticTiles>
    </StaticTiles>
  </TransInfo>
  <TransInfo Description="Top Left" HashKey="128080801212121212">
    <MapTiles>
      <MapTile TileID="561" AltIDMod="0" />
    </MapTiles>
    <StaticTiles>
    </StaticTiles>
  </TransInfo>
  <TransInfo Description="Bottom Left" HashKey="801212801212808080">
    <MapTiles>
      <MapTile TileID="564" AltIDMod="0" />
    </MapTiles>
    <StaticTiles>
    </StaticTiles>
  </TransInfo>
  <TransInfo Description="Bottom Left" HashKey="121212801212808080">
    <MapTiles>
      <MapTile TileID="564" AltIDMod="0" />
    </MapTiles>
    <StaticTiles>
    </StaticTiles>
  </TransInfo>
  <TransInfo Description="Bottom Left" HashKey="801212801212808012">
    <MapTiles>
      <MapTile TileID="564" AltIDMod="0" />
    </MapTiles>
    <StaticTiles>
    </StaticTiles>
  </TransInfo>
  <TransInfo Description="Bottom Left" HashKey="121212801212808012">
    <MapTiles>
      <MapTile TileID="564" AltIDMod="0" />
    </MapTiles>
    <StaticTiles>
    </StaticTiles>
  </TransInfo>
  <TransInfo Description="Bottom Left" HashKey="121212801212128012">
    <MapTiles>
      <MapTile TileID="564" AltIDMod="0" />
    </MapTiles>
    <StaticTiles>
    </StaticTiles>
  </TransInfo>
  <TransInfo Description="Bottom Left" HashKey="801212801212121280">
    <MapTiles>
      <MapTile TileID="564" AltIDMod="0" />
    </MapTiles>
    <StaticTiles>
    </StaticTiles>
  </TransInfo>
  <TransInfo Description="Bottom Left" HashKey="801212121212808080">
    <MapTiles>
      <MapTile TileID="564" AltIDMod="0" />
    </MapTiles>
    <StaticTiles>
    </StaticTiles>
  </TransInfo>
  <TransInfo Description="Bottom Left" HashKey="801212121212808012">
    <MapTiles>
      <MapTile TileID="564" AltIDMod="0" />
    </MapTiles>
    <StaticTiles>
    </StaticTiles>
  </TransInfo>
  <TransInfo Description="Bottom Left" HashKey="801212121212128012">
    <MapTiles>
      <MapTile TileID="564" AltIDMod="0" />
    </MapTiles>
    <StaticTiles>
    </StaticTiles>
  </TransInfo>
  <TransInfo Description="Bottom Left" HashKey="121212801212801280">
    <MapTiles>
      <MapTile TileID="564" AltIDMod="0" />
    </MapTiles>
    <StaticTiles>
    </StaticTiles>
  </TransInfo>
  <TransInfo Description="Bottom Left" HashKey="801212801212801280">
    <MapTiles>
      <MapTile TileID="564" AltIDMod="0" />
    </MapTiles>
    <StaticTiles>
    </StaticTiles>
  </TransInfo>
  <TransInfo Description="Bottom Left" HashKey="801212121212128080">
    <MapTiles>
      <MapTile TileID="564" AltIDMod="0" />
    </MapTiles>
    <StaticTiles>
    </StaticTiles>
  </TransInfo>
  <TransInfo Description="Bottom Left" HashKey="801212801212128080">
    <MapTiles>
      <MapTile TileID="564" AltIDMod="0" />
    </MapTiles>
    <StaticTiles>
    </StaticTiles>
  </TransInfo>
  <TransInfo Description="Bottom Left" HashKey="121212801212128080">
    <MapTiles>
      <MapTile TileID="564" AltIDMod="0" />
    </MapTiles>
    <StaticTiles>
    </StaticTiles>
  </TransInfo>
  <TransInfo Description="Bottom Left" HashKey="121212801212121280">
    <MapTiles>
      <MapTile TileID="564" AltIDMod="0" />
    </MapTiles>
    <StaticTiles>
    </StaticTiles>
  </TransInfo>
  <TransInfo Description="Bottom Left" HashKey="801212121212801280">
    <MapTiles>
      <MapTile TileID="564" AltIDMod="0" />
    </MapTiles>
    <StaticTiles>
    </StaticTiles>
  </TransInfo>
  <TransInfo Description="Bottom Left" HashKey="801212801212128012">
    <MapTiles>
      <MapTile TileID="564" AltIDMod="0" />
    </MapTiles>
    <StaticTiles>
    </StaticTiles>
  </TransInfo>
  <TransInfo Description="Top Right" HashKey="808080121280121280">
    <MapTiles>
      <MapTile TileID="562" AltIDMod="0" />
    </MapTiles>
    <StaticTiles>
    </StaticTiles>
  </TransInfo>
  <TransInfo Description="Top Right" HashKey="808080121280121212">
    <MapTiles>
      <MapTile TileID="562" AltIDMod="0" />
    </MapTiles>
    <StaticTiles>
    </StaticTiles>
  </TransInfo>
  <TransInfo Description="Top Right" HashKey="128080121280121280">
    <MapTiles>
      <MapTile TileID="562" AltIDMod="0" />
    </MapTiles>
    <StaticTiles>
    </StaticTiles>
  </TransInfo>
  <TransInfo Description="Top Right" HashKey="128080121280121212">
    <MapTiles>
      <MapTile TileID="562" AltIDMod="0" />
    </MapTiles>
    <StaticTiles>
    </StaticTiles>
  </TransInfo>
  <TransInfo Description="Top Right" HashKey="801212121280121280">
    <MapTiles>
      <MapTile TileID="562" AltIDMod="0" />
    </MapTiles>
    <StaticTiles>
    </StaticTiles>
  </TransInfo>
  <TransInfo Description="Top Right" HashKey="801280121280121212">
    <MapTiles>
      <MapTile TileID="562" AltIDMod="0" />
    </MapTiles>
    <StaticTiles>
    </StaticTiles>
  </TransInfo>
  <TransInfo Description="Top Right" HashKey="801280121280121280">
    <MapTiles>
      <MapTile TileID="562" AltIDMod="0" />
    </MapTiles>
    <StaticTiles>
    </StaticTiles>
  </TransInfo>
  <TransInfo Description="Top Right" HashKey="808012121212121280">
    <MapTiles>
      <MapTile TileID="562" AltIDMod="0" />
    </MapTiles>
    <StaticTiles>
    </StaticTiles>
  </TransInfo>
  <TransInfo Description="Top Right" HashKey="128012121212121280">
    <MapTiles>
      <MapTile TileID="562" AltIDMod="0" />
    </MapTiles>
    <StaticTiles>
    </StaticTiles>
  </TransInfo>
  <TransInfo Description="Top Right" HashKey="808080121212121280">
    <MapTiles>
      <MapTile TileID="562" AltIDMod="0" />
    </MapTiles>
    <StaticTiles>
    </StaticTiles>
  </TransInfo>
  <TransInfo Description="Top Right" HashKey="808012121280121212">
    <MapTiles>
      <MapTile TileID="562" AltIDMod="0" />
    </MapTiles>
    <StaticTiles>
    </StaticTiles>
  </TransInfo>
  <TransInfo Description="Top Right" HashKey="128080121212121280">
    <MapTiles>
      <MapTile TileID="562" AltIDMod="0" />
    </MapTiles>
    <StaticTiles>
    </StaticTiles>
  </TransInfo>
  <TransInfo Description="Top Right" HashKey="128012121280121212">
    <MapTiles>
      <MapTile TileID="562" AltIDMod="0" />
    </MapTiles>
    <StaticTiles>
    </StaticTiles>
  </TransInfo>
  <TransInfo Description="Top Right" HashKey="801212121280121212">
    <MapTiles>
      <MapTile TileID="562" AltIDMod="0" />
    </MapTiles>
    <StaticTiles>
    </StaticTiles>
  </TransInfo>
  <TransInfo Description="Top Right" HashKey="801280121212121280">
    <MapTiles>
      <MapTile TileID="562" AltIDMod="0" />
    </MapTiles>
    <StaticTiles>
    </StaticTiles>
  </TransInfo>
  <TransInfo Description="Top Right" HashKey="128012121280121280">
    <MapTiles>
      <MapTile TileID="562" AltIDMod="0" />
    </MapTiles>
    <StaticTiles>
    </StaticTiles>
  </TransInfo>
  <TransInfo Description="Top Right" HashKey="808012121280121280">
    <MapTiles>
      <MapTile TileID="562" AltIDMod="0" />
    </MapTiles>
    <StaticTiles>
    </StaticTiles>
  </TransInfo>
  <TransInfo Description="Outer Top Left" HashKey="801212121212121212">
    <MapTiles>
      <MapTile TileID="567" AltIDMod="0" />
    </MapTiles>
    <StaticTiles>
    </StaticTiles>
  </TransInfo>
  <TransInfo Description="Outer Bottom Right" HashKey="121212121212121280">
    <MapTiles>
      <MapTile TileID="565" AltIDMod="0" />
    </MapTiles>
    <StaticTiles>
    </StaticTiles>
  </TransInfo>
  <TransInfo Description="Outer Top Right" HashKey="121280121212121212">
    <MapTiles>
      <MapTile TileID="568" AltIDMod="0" />
    </MapTiles>
    <StaticTiles>
    </StaticTiles>
  </TransInfo>
  <TransInfo Description="Outer Bottom Left" HashKey="121212121212801212">
    <MapTiles>
      <MapTile TileID="566" AltIDMod="0" />
    </MapTiles>
    <StaticTiles>
    </StaticTiles>
  </TransInfo>
  <TransInfo Description="Autocorrect" HashKey="121212801280121212">
    <MapTiles>
      <MapTile TileID="3" AltIDMod="0" />
      <MapTile TileID="4" AltIDMod="0" />
      <MapTile TileID="5" AltIDMod="0" />
      <MapTile TileID="6" AltIDMod="0" />
    </MapTiles>
    <StaticTiles>
    </StaticTiles>
  </TransInfo>
  <TransInfo Description="Autocorrect" HashKey="121212801280801212">
    <MapTiles>
      <MapTile TileID="3" AltIDMod="0" />
      <MapTile TileID="4" AltIDMod="0" />
      <MapTile TileID="5" AltIDMod="0" />
      <MapTile TileID="6" AltIDMod="0" />
    </MapTiles>
    <StaticTiles>
    </StaticTiles>
  </TransInfo>
  <TransInfo Description="Autocorrect" HashKey="121212801280128012">
    <MapTiles>
      <MapTile TileID="3" AltIDMod="0" />
      <MapTile TileID="4" AltIDMod="0" />
      <MapTile TileID="5" AltIDMod="0" />
      <MapTile TileID="6" AltIDMod="0" />
    </MapTiles>
    <StaticTiles>
    </StaticTiles>
  </TransInfo>
  <TransInfo Description="Autocorrect" HashKey="121212801280808012">
    <MapTiles>
      <MapTile TileID="3" AltIDMod="0" />
      <MapTile TileID="4" AltIDMod="0" />
      <MapTile TileID="5" AltIDMod="0" />
      <MapTile TileID="6" AltIDMod="0" />
    </MapTiles>
    <StaticTiles>
    </StaticTiles>
  </TransInfo>
  <TransInfo Description="Autocorrect" HashKey="121212801280121280">
    <MapTiles>
      <MapTile TileID="3" AltIDMod="0" />
      <MapTile TileID="4" AltIDMod="0" />
      <MapTile TileID="5" AltIDMod="0" />
      <MapTile TileID="6" AltIDMod="0" />
    </MapTiles>
    <StaticTiles>
    </StaticTiles>
  </TransInfo>
  <TransInfo Description="Autocorrect" HashKey="121212801280801280">
    <MapTiles>
      <MapTile TileID="3" AltIDMod="0" />
      <MapTile TileID="4" AltIDMod="0" />
      <MapTile TileID="5" AltIDMod="0" />
      <MapTile TileID="6" AltIDMod="0" />
    </MapTiles>
    <StaticTiles>
    </StaticTiles>
  </TransInfo>
  <TransInfo Description="Autocorrect" HashKey="121212801280128080">
    <MapTiles>
      <MapTile TileID="3" AltIDMod="0" />
      <MapTile TileID="4" AltIDMod="0" />
      <MapTile TileID="5" AltIDMod="0" />
      <MapTile TileID="6" AltIDMod="0" />
    </MapTiles>
    <StaticTiles>
    </StaticTiles>
  </TransInfo>
  <TransInfo Description="Autocorrect" HashKey="121212801280808080">
    <MapTiles>
      <MapTile TileID="3" AltIDMod="0" />
      <MapTile TileID="4" AltIDMod="0" />
      <MapTile TileID="5" AltIDMod="0" />
      <MapTile TileID="6" AltIDMod="0" />
    </MapTiles>
    <StaticTiles>
    </StaticTiles>
  </TransInfo>
  <TransInfo Description="Autocorrect" HashKey="121280801212128012">
    <MapTiles>
      <MapTile TileID="3" AltIDMod="0" />
      <MapTile TileID="4" AltIDMod="0" />
      <MapTile TileID="5" AltIDMod="0" />
      <MapTile TileID="6" AltIDMod="0" />
    </MapTiles>
    <StaticTiles>
    </StaticTiles>
  </TransInfo>
  <TransInfo Description="Autocorrect" HashKey="121280801212808012">
    <MapTiles>
      <MapTile TileID="3" AltIDMod="0" />
      <MapTile TileID="4" AltIDMod="0" />
      <MapTile TileID="5" AltIDMod="0" />
      <MapTile TileID="6" AltIDMod="0" />
    </MapTiles>
    <StaticTiles>
    </StaticTiles>
  </TransInfo>
  <TransInfo Description="Autocorrect" HashKey="121280801212121280">
    <MapTiles>
      <MapTile TileID="3" AltIDMod="0" />
      <MapTile TileID="4" AltIDMod="0" />
      <MapTile TileID="5" AltIDMod="0" />
      <MapTile TileID="6" AltIDMod="0" />
    </MapTiles>
    <StaticTiles>
    </StaticTiles>
  </TransInfo>
  <TransInfo Description="Autocorrect" HashKey="121280801212801280">
    <MapTiles>
      <MapTile TileID="3" AltIDMod="0" />
      <MapTile TileID="4" AltIDMod="0" />
      <MapTile TileID="5" AltIDMod="0" />
      <MapTile TileID="6" AltIDMod="0" />
    </MapTiles>
    <StaticTiles>
    </StaticTiles>
  </TransInfo>
  <TransInfo Description="Autocorrect" HashKey="121280801212128080">
    <MapTiles>
      <MapTile TileID="3" AltIDMod="0" />
      <MapTile TileID="4" AltIDMod="0" />
      <MapTile TileID="5" AltIDMod="0" />
      <MapTile TileID="6" AltIDMod="0" />
    </MapTiles>
    <StaticTiles>
    </StaticTiles>
  </TransInfo>
  <TransInfo Description="Autocorrect" HashKey="121280801212808080">
    <MapTiles>
      <MapTile TileID="3" AltIDMod="0" />
      <MapTile TileID="4" AltIDMod="0" />
      <MapTile TileID="5" AltIDMod="0" />
      <MapTile TileID="6" AltIDMod="0" />
    </MapTiles>
    <StaticTiles>
    </StaticTiles>
  </TransInfo>
  <TransInfo Description="Autocorrect" HashKey="121280801280121212">
    <MapTiles>
      <MapTile TileID="3" AltIDMod="0" />
      <MapTile TileID="4" AltIDMod="0" />
      <MapTile TileID="5" AltIDMod="0" />
      <MapTile TileID="6" AltIDMod="0" />
    </MapTiles>
    <StaticTiles>
    </StaticTiles>
  </TransInfo>
  <TransInfo Description="Autocorrect" HashKey="121280801280801212">
    <MapTiles>
      <MapTile TileID="3" AltIDMod="0" />
      <MapTile TileID="4" AltIDMod="0" />
      <MapTile TileID="5" AltIDMod="0" />
      <MapTile TileID="6" AltIDMod="0" />
    </MapTiles>
    <StaticTiles>
    </StaticTiles>
  </TransInfo>
  <TransInfo Description="Autocorrect" HashKey="121280801280128012">
    <MapTiles>
      <MapTile TileID="3" AltIDMod="0" />
      <MapTile TileID="4" AltIDMod="0" />
      <MapTile TileID="5" AltIDMod="0" />
      <MapTile TileID="6" AltIDMod="0" />
    </MapTiles>
    <StaticTiles>
    </StaticTiles>
  </TransInfo>
  <TransInfo Description="Autocorrect" HashKey="121280801280808012">
    <MapTiles>
      <MapTile TileID="3" AltIDMod="0" />
      <MapTile TileID="4" AltIDMod="0" />
      <MapTile TileID="5" AltIDMod="0" />
      <MapTile TileID="6" AltIDMod="0" />
    </MapTiles>
    <StaticTiles>
    </StaticTiles>
  </TransInfo>
  <TransInfo Description="Autocorrect" HashKey="121280801280121280">
    <MapTiles>
      <MapTile TileID="3" AltIDMod="0" />
      <MapTile TileID="4" AltIDMod="0" />
      <MapTile TileID="5" AltIDMod="0" />
      <MapTile TileID="6" AltIDMod="0" />
    </MapTiles>
    <StaticTiles>
    </StaticTiles>
  </TransInfo>
  <TransInfo Description="Autocorrect" HashKey="121280801280801280">
    <MapTiles>
      <MapTile TileID="3" AltIDMod="0" />
      <MapTile TileID="4" AltIDMod="0" />
      <MapTile TileID="5" AltIDMod="0" />
      <MapTile TileID="6" AltIDMod="0" />
    </MapTiles>
    <StaticTiles>
    </StaticTiles>
  </TransInfo>
  <TransInfo Description="Autocorrect" HashKey="121280801280128080">
    <MapTiles>
      <MapTile TileID="3" AltIDMod="0" />
      <MapTile TileID="4" AltIDMod="0" />
      <MapTile TileID="5" AltIDMod="0" />
      <MapTile TileID="6" AltIDMod="0" />
    </MapTiles>
    <StaticTiles>
    </StaticTiles>
  </TransInfo>
  <TransInfo Description="Autocorrect" HashKey="121280801280808080">
    <MapTiles>
      <MapTile TileID="3" AltIDMod="0" />
      <MapTile TileID="4" AltIDMod="0" />
      <MapTile TileID="5" AltIDMod="0" />
      <MapTile TileID="6" AltIDMod="0" />
    </MapTiles>
    <StaticTiles>
    </StaticTiles>
  </TransInfo>
  <TransInfo Description="Autocorrect" HashKey="128012121212128012">
    <MapTiles>
      <MapTile TileID="3" AltIDMod="0" />
      <MapTile TileID="4" AltIDMod="0" />
      <MapTile TileID="5" AltIDMod="0" />
      <MapTile TileID="6" AltIDMod="0" />
    </MapTiles>
    <StaticTiles>
    </StaticTiles>
  </TransInfo>
  <TransInfo Description="Autocorrect" HashKey="128012801212128012">
    <MapTiles>
      <MapTile TileID="3" AltIDMod="0" />
      <MapTile TileID="4" AltIDMod="0" />
      <MapTile TileID="5" AltIDMod="0" />
      <MapTile TileID="6" AltIDMod="0" />
    </MapTiles>
    <StaticTiles>
    </StaticTiles>
  </TransInfo>
  <TransInfo Description="Autocorrect" HashKey="128012121212808012">
    <MapTiles>
      <MapTile TileID="3" AltIDMod="0" />
      <MapTile TileID="4" AltIDMod="0" />
      <MapTile TileID="5" AltIDMod="0" />
      <MapTile TileID="6" AltIDMod="0" />
    </MapTiles>
    <StaticTiles>
    </StaticTiles>
  </TransInfo>
  <TransInfo Description="Autocorrect" HashKey="128012801212808012">
    <MapTiles>
      <MapTile TileID="3" AltIDMod="0" />
      <MapTile TileID="4" AltIDMod="0" />
      <MapTile TileID="5" AltIDMod="0" />
      <MapTile TileID="6" AltIDMod="0" />
    </MapTiles>
    <StaticTiles>
    </StaticTiles>
  </TransInfo>
  <TransInfo Description="Autocorrect" HashKey="128012801212121280">
    <MapTiles>
      <MapTile TileID="3" AltIDMod="0" />
      <MapTile TileID="4" AltIDMod="0" />
      <MapTile TileID="5" AltIDMod="0" />
      <MapTile TileID="6" AltIDMod="0" />
    </MapTiles>
    <StaticTiles>
    </StaticTiles>
  </TransInfo>
  <TransInfo Description="Autocorrect" HashKey="128012121212801280">
    <MapTiles>
      <MapTile TileID="3" AltIDMod="0" />
      <MapTile TileID="4" AltIDMod="0" />
      <MapTile TileID="5" AltIDMod="0" />
      <MapTile TileID="6" AltIDMod="0" />
    </MapTiles>
    <StaticTiles>
    </StaticTiles>
  </TransInfo>
  <TransInfo Description="Autocorrect" HashKey="128012801212801280">
    <MapTiles>
      <MapTile TileID="3" AltIDMod="0" />
      <MapTile TileID="4" AltIDMod="0" />
      <MapTile TileID="5" AltIDMod="0" />
      <MapTile TileID="6" AltIDMod="0" />
    </MapTiles>
    <StaticTiles>
    </StaticTiles>
  </TransInfo>
  <TransInfo Description="Autocorrect" HashKey="128012121212128080">
    <MapTiles>
      <MapTile TileID="3" AltIDMod="0" />
      <MapTile TileID="4" AltIDMod="0" />
      <MapTile TileID="5" AltIDMod="0" />
      <MapTile TileID="6" AltIDMod="0" />
    </MapTiles>
    <StaticTiles>
    </StaticTiles>
  </TransInfo>
  <TransInfo Description="Autocorrect" HashKey="128012801212128080">
    <MapTiles>
      <MapTile TileID="3" AltIDMod="0" />
      <MapTile TileID="4" AltIDMod="0" />
      <MapTile TileID="5" AltIDMod="0" />
      <MapTile TileID="6" AltIDMod="0" />
    </MapTiles>
    <StaticTiles>
    </StaticTiles>
  </TransInfo>
  <TransInfo Description="Autocorrect" HashKey="128012121212808080">
    <MapTiles>
      <MapTile TileID="3" AltIDMod="0" />
      <MapTile TileID="4" AltIDMod="0" />
      <MapTile TileID="5" AltIDMod="0" />
      <MapTile TileID="6" AltIDMod="0" />
    </MapTiles>
    <StaticTiles>
    </StaticTiles>
  </TransInfo>
  <TransInfo Description="Autocorrect" HashKey="128012801212808080">
    <MapTiles>
      <MapTile TileID="3" AltIDMod="0" />
      <MapTile TileID="4" AltIDMod="0" />
      <MapTile TileID="5" AltIDMod="0" />
      <MapTile TileID="6" AltIDMod="0" />
    </MapTiles>
    <StaticTiles>
    </StaticTiles>
  </TransInfo>
  <TransInfo Description="Autocorrect" HashKey="128012801280121212">
    <MapTiles>
      <MapTile TileID="3" AltIDMod="0" />
      <MapTile TileID="4" AltIDMod="0" />
      <MapTile TileID="5" AltIDMod="0" />
      <MapTile TileID="6" AltIDMod="0" />
    </MapTiles>
    <StaticTiles>
    </StaticTiles>
  </TransInfo>
  <TransInfo Description="Autocorrect" HashKey="128012121280801212">
    <MapTiles>
      <MapTile TileID="3" AltIDMod="0" />
      <MapTile TileID="4" AltIDMod="0" />
      <MapTile TileID="5" AltIDMod="0" />
      <MapTile TileID="6" AltIDMod="0" />
    </MapTiles>
    <StaticTiles>
    </StaticTiles>
  </TransInfo>
  <TransInfo Description="Autocorrect" HashKey="128012801280801212">
    <MapTiles>
      <MapTile TileID="3" AltIDMod="0" />
      <MapTile TileID="4" AltIDMod="0" />
      <MapTile TileID="5" AltIDMod="0" />
      <MapTile TileID="6" AltIDMod="0" />
    </MapTiles>
    <StaticTiles>
    </StaticTiles>
  </TransInfo>
  <TransInfo Description="Autocorrect" HashKey="128012121280128012">
    <MapTiles>
      <MapTile TileID="3" AltIDMod="0" />
      <MapTile TileID="4" AltIDMod="0" />
      <MapTile TileID="5" AltIDMod="0" />
      <MapTile TileID="6" AltIDMod="0" />
    </MapTiles>
    <StaticTiles>
    </StaticTiles>
  </TransInfo>
  <TransInfo Description="Autocorrect" HashKey="128012801280128012">
    <MapTiles>
      <MapTile TileID="3" AltIDMod="0" />
      <MapTile TileID="4" AltIDMod="0" />
      <MapTile TileID="5" AltIDMod="0" />
      <MapTile TileID="6" AltIDMod="0" />
    </MapTiles>
    <StaticTiles>
    </StaticTiles>
  </TransInfo>
  <TransInfo Description="Autocorrect" HashKey="128012121280808012">
    <MapTiles>
      <MapTile TileID="3" AltIDMod="0" />
      <MapTile TileID="4" AltIDMod="0" />
      <MapTile TileID="5" AltIDMod="0" />
      <MapTile TileID="6" AltIDMod="0" />
    </MapTiles>
    <StaticTiles>
    </StaticTiles>
  </TransInfo>
  <TransInfo Description="Autocorrect" HashKey="128012801280808012">
    <MapTiles>
      <MapTile TileID="3" AltIDMod="0" />
      <MapTile TileID="4" AltIDMod="0" />
      <MapTile TileID="5" AltIDMod="0" />
      <MapTile TileID="6" AltIDMod="0" />
    </MapTiles>
    <StaticTiles>
    </StaticTiles>
  </TransInfo>
  <TransInfo Description="Autocorrect" HashKey="128012801280121280">
    <MapTiles>
      <MapTile TileID="3" AltIDMod="0" />
      <MapTile TileID="4" AltIDMod="0" />
      <MapTile TileID="5" AltIDMod="0" />
      <MapTile TileID="6" AltIDMod="0" />
    </MapTiles>
    <StaticTiles>
    </StaticTiles>
  </TransInfo>
  <TransInfo Description="Autocorrect" HashKey="128012121280801280">
    <MapTiles>
      <MapTile TileID="3" AltIDMod="0" />
      <MapTile TileID="4" AltIDMod="0" />
      <MapTile TileID="5" AltIDMod="0" />
      <MapTile TileID="6" AltIDMod="0" />
    </MapTiles>
    <StaticTiles>
    </StaticTiles>
  </TransInfo>
  <TransInfo Description="Autocorrect" HashKey="128012801280801280">
    <MapTiles>
      <MapTile TileID="3" AltIDMod="0" />
      <MapTile TileID="4" AltIDMod="0" />
      <MapTile TileID="5" AltIDMod="0" />
      <MapTile TileID="6" AltIDMod="0" />
    </MapTiles>
    <StaticTiles>
    </StaticTiles>
  </TransInfo>
  <TransInfo Description="Autocorrect" HashKey="128012121280128080">
    <MapTiles>
      <MapTile TileID="3" AltIDMod="0" />
      <MapTile TileID="4" AltIDMod="0" />
      <MapTile TileID="5" AltIDMod="0" />
      <MapTile TileID="6" AltIDMod="0" />
    </MapTiles>
    <StaticTiles>
    </StaticTiles>
  </TransInfo>
  <TransInfo Description="Autocorrect" HashKey="128012801280128080">
    <MapTiles>
      <MapTile TileID="3" AltIDMod="0" />
      <MapTile TileID="4" AltIDMod="0" />
      <MapTile TileID="5" AltIDMod="0" />
      <MapTile TileID="6" AltIDMod="0" />
    </MapTiles>
    <StaticTiles>
    </StaticTiles>
  </TransInfo>
  <TransInfo Description="Autocorrect" HashKey="128012121280808080">
    <MapTiles>
      <MapTile TileID="3" AltIDMod="0" />
      <MapTile TileID="4" AltIDMod="0" />
      <MapTile TileID="5" AltIDMod="0" />
      <MapTile TileID="6" AltIDMod="0" />
    </MapTiles>
    <StaticTiles>
    </StaticTiles>
  </TransInfo>
  <TransInfo Description="Autocorrect" HashKey="128012801280808080">
    <MapTiles>
      <MapTile TileID="3" AltIDMod="0" />
      <MapTile TileID="4" AltIDMod="0" />
      <MapTile TileID="5" AltIDMod="0" />
      <MapTile TileID="6" AltIDMod="0" />
    </MapTiles>
    <StaticTiles>
    </StaticTiles>
  </TransInfo>
  <TransInfo Description="Autocorrect" HashKey="128080121212128012">
    <MapTiles>
      <MapTile TileID="3" AltIDMod="0" />
      <MapTile TileID="4" AltIDMod="0" />
      <MapTile TileID="5" AltIDMod="0" />
      <MapTile TileID="6" AltIDMod="0" />
    </MapTiles>
    <StaticTiles>
    </StaticTiles>
  </TransInfo>
  <TransInfo Description="Autocorrect" HashKey="128080801212128012">
    <MapTiles>
      <MapTile TileID="3" AltIDMod="0" />
      <MapTile TileID="4" AltIDMod="0" />
      <MapTile TileID="5" AltIDMod="0" />
      <MapTile TileID="6" AltIDMod="0" />
    </MapTiles>
    <StaticTiles>
    </StaticTiles>
  </TransInfo>
  <TransInfo Description="Autocorrect" HashKey="128080121212808012">
    <MapTiles>
      <MapTile TileID="3" AltIDMod="0" />
      <MapTile TileID="4" AltIDMod="0" />
      <MapTile TileID="5" AltIDMod="0" />
      <MapTile TileID="6" AltIDMod="0" />
    </MapTiles>
    <StaticTiles>
    </StaticTiles>
  </TransInfo>
  <TransInfo Description="Autocorrect" HashKey="128080801212808012">
    <MapTiles>
      <MapTile TileID="3" AltIDMod="0" />
      <MapTile TileID="4" AltIDMod="0" />
      <MapTile TileID="5" AltIDMod="0" />
      <MapTile TileID="6" AltIDMod="0" />
    </MapTiles>
    <StaticTiles>
    </StaticTiles>
  </TransInfo>
  <TransInfo Description="Autocorrect" HashKey="128080801212121280">
    <MapTiles>
      <MapTile TileID="3" AltIDMod="0" />
      <MapTile TileID="4" AltIDMod="0" />
      <MapTile TileID="5" AltIDMod="0" />
      <MapTile TileID="6" AltIDMod="0" />
    </MapTiles>
    <StaticTiles>
    </StaticTiles>
  </TransInfo>
  <TransInfo Description="Autocorrect" HashKey="128080121212801280">
    <MapTiles>
      <MapTile TileID="3" AltIDMod="0" />
      <MapTile TileID="4" AltIDMod="0" />
      <MapTile TileID="5" AltIDMod="0" />
      <MapTile TileID="6" AltIDMod="0" />
    </MapTiles>
    <StaticTiles>
    </StaticTiles>
  </TransInfo>
  <TransInfo Description="Autocorrect" HashKey="128080801212801280">
    <MapTiles>
      <MapTile TileID="3" AltIDMod="0" />
      <MapTile TileID="4" AltIDMod="0" />
      <MapTile TileID="5" AltIDMod="0" />
      <MapTile TileID="6" AltIDMod="0" />
    </MapTiles>
    <StaticTiles>
    </StaticTiles>
  </TransInfo>
  <TransInfo Description="Autocorrect" HashKey="128080121212128080">
    <MapTiles>
      <MapTile TileID="3" AltIDMod="0" />
      <MapTile TileID="4" AltIDMod="0" />
      <MapTile TileID="5" AltIDMod="0" />
      <MapTile TileID="6" AltIDMod="0" />
    </MapTiles>
    <StaticTiles>
    </StaticTiles>
  </TransInfo>
  <TransInfo Description="Autocorrect" HashKey="128080801212128080">
    <MapTiles>
      <MapTile TileID="3" AltIDMod="0" />
      <MapTile TileID="4" AltIDMod="0" />
      <MapTile TileID="5" AltIDMod="0" />
      <MapTile TileID="6" AltIDMod="0" />
    </MapTiles>
    <StaticTiles>
    </StaticTiles>
  </TransInfo>
  <TransInfo Description="Autocorrect" HashKey="128080121212808080">
    <MapTiles>
      <MapTile TileID="3" AltIDMod="0" />
      <MapTile TileID="4" AltIDMod="0" />
      <MapTile TileID="5" AltIDMod="0" />
      <MapTile TileID="6" AltIDMod="0" />
    </MapTiles>
    <StaticTiles>
    </StaticTiles>
  </TransInfo>
  <TransInfo Description="Autocorrect" HashKey="128080801212808080">
    <MapTiles>
      <MapTile TileID="3" AltIDMod="0" />
      <MapTile TileID="4" AltIDMod="0" />
      <MapTile TileID="5" AltIDMod="0" />
      <MapTile TileID="6" AltIDMod="0" />
    </MapTiles>
    <StaticTiles>
    </StaticTiles>
  </TransInfo>
  <TransInfo Description="Autocorrect" HashKey="128080801280121212">
    <MapTiles>
      <MapTile TileID="3" AltIDMod="0" />
      <MapTile TileID="4" AltIDMod="0" />
      <MapTile TileID="5" AltIDMod="0" />
      <MapTile TileID="6" AltIDMod="0" />
    </MapTiles>
    <StaticTiles>
    </StaticTiles>
  </TransInfo>
  <TransInfo Description="Autocorrect" HashKey="128080121280801212">
    <MapTiles>
      <MapTile TileID="3" AltIDMod="0" />
      <MapTile TileID="4" AltIDMod="0" />
      <MapTile TileID="5" AltIDMod="0" />
      <MapTile TileID="6" AltIDMod="0" />
    </MapTiles>
    <StaticTiles>
    </StaticTiles>
  </TransInfo>
  <TransInfo Description="Autocorrect" HashKey="128080801280801212">
    <MapTiles>
      <MapTile TileID="3" AltIDMod="0" />
      <MapTile TileID="4" AltIDMod="0" />
      <MapTile TileID="5" AltIDMod="0" />
      <MapTile TileID="6" AltIDMod="0" />
    </MapTiles>
    <StaticTiles>
    </StaticTiles>
  </TransInfo>
  <TransInfo Description="Autocorrect" HashKey="128080121280128012">
    <MapTiles>
      <MapTile TileID="3" AltIDMod="0" />
      <MapTile TileID="4" AltIDMod="0" />
      <MapTile TileID="5" AltIDMod="0" />
      <MapTile TileID="6" AltIDMod="0" />
    </MapTiles>
    <StaticTiles>
    </StaticTiles>
  </TransInfo>
  <TransInfo Description="Autocorrect" HashKey="128080801280128012">
    <MapTiles>
      <MapTile TileID="3" AltIDMod="0" />
      <MapTile TileID="4" AltIDMod="0" />
      <MapTile TileID="5" AltIDMod="0" />
      <MapTile TileID="6" AltIDMod="0" />
    </MapTiles>
    <StaticTiles>
    </StaticTiles>
  </TransInfo>
  <TransInfo Description="Autocorrect" HashKey="128080121280808012">
    <MapTiles>
      <MapTile TileID="3" AltIDMod="0" />
      <MapTile TileID="4" AltIDMod="0" />
      <MapTile TileID="5" AltIDMod="0" />
      <MapTile TileID="6" AltIDMod="0" />
    </MapTiles>
    <StaticTiles>
    </StaticTiles>
  </TransInfo>
  <TransInfo Description="Autocorrect" HashKey="128080801280808012">
    <MapTiles>
      <MapTile TileID="3" AltIDMod="0" />
      <MapTile TileID="4" AltIDMod="0" />
      <MapTile TileID="5" AltIDMod="0" />
      <MapTile TileID="6" AltIDMod="0" />
    </MapTiles>
    <StaticTiles>
    </StaticTiles>
  </TransInfo>
  <TransInfo Description="Autocorrect" HashKey="128080801280121280">
    <MapTiles>
      <MapTile TileID="3" AltIDMod="0" />
      <MapTile TileID="4" AltIDMod="0" />
      <MapTile TileID="5" AltIDMod="0" />
      <MapTile TileID="6" AltIDMod="0" />
    </MapTiles>
    <StaticTiles>
    </StaticTiles>
  </TransInfo>
  <TransInfo Description="Autocorrect" HashKey="128080121280801280">
    <MapTiles>
      <MapTile TileID="3" AltIDMod="0" />
      <MapTile TileID="4" AltIDMod="0" />
      <MapTile TileID="5" AltIDMod="0" />
      <MapTile TileID="6" AltIDMod="0" />
    </MapTiles>
    <StaticTiles>
    </StaticTiles>
  </TransInfo>
  <TransInfo Description="Autocorrect" HashKey="128080801280801280">
    <MapTiles>
      <MapTile TileID="3" AltIDMod="0" />
      <MapTile TileID="4" AltIDMod="0" />
      <MapTile TileID="5" AltIDMod="0" />
      <MapTile TileID="6" AltIDMod="0" />
    </MapTiles>
    <StaticTiles>
    </StaticTiles>
  </TransInfo>
  <TransInfo Description="Autocorrect" HashKey="128080121280128080">
    <MapTiles>
      <MapTile TileID="3" AltIDMod="0" />
      <MapTile TileID="4" AltIDMod="0" />
      <MapTile TileID="5" AltIDMod="0" />
      <MapTile TileID="6" AltIDMod="0" />
    </MapTiles>
    <StaticTiles>
    </StaticTiles>
  </TransInfo>
  <TransInfo Description="Autocorrect" HashKey="128080801280128080">
    <MapTiles>
      <MapTile TileID="3" AltIDMod="0" />
      <MapTile TileID="4" AltIDMod="0" />
      <MapTile TileID="5" AltIDMod="0" />
      <MapTile TileID="6" AltIDMod="0" />
    </MapTiles>
    <StaticTiles>
    </StaticTiles>
  </TransInfo>
  <TransInfo Description="Autocorrect" HashKey="128080121280808080">
    <MapTiles>
      <MapTile TileID="3" AltIDMod="0" />
      <MapTile TileID="4" AltIDMod="0" />
      <MapTile TileID="5" AltIDMod="0" />
      <MapTile TileID="6" AltIDMod="0" />
    </MapTiles>
    <StaticTiles>
    </StaticTiles>
  </TransInfo>
  <TransInfo Description="Autocorrect" HashKey="128080801280808080">
    <MapTiles>
      <MapTile TileID="3" AltIDMod="0" />
      <MapTile TileID="4" AltIDMod="0" />
      <MapTile TileID="5" AltIDMod="0" />
      <MapTile TileID="6" AltIDMod="0" />
    </MapTiles>
    <StaticTiles>
    </StaticTiles>
  </TransInfo>
  <TransInfo Description="Autocorrect" HashKey="801212801280121212">
    <MapTiles>
      <MapTile TileID="3" AltIDMod="0" />
      <MapTile TileID="4" AltIDMod="0" />
      <MapTile TileID="5" AltIDMod="0" />
      <MapTile TileID="6" AltIDMod="0" />
    </MapTiles>
    <StaticTiles>
    </StaticTiles>
  </TransInfo>
  <TransInfo Description="Autocorrect" HashKey="801212121280801212">
    <MapTiles>
      <MapTile TileID="3" AltIDMod="0" />
      <MapTile TileID="4" AltIDMod="0" />
      <MapTile TileID="5" AltIDMod="0" />
      <MapTile TileID="6" AltIDMod="0" />
    </MapTiles>
    <StaticTiles>
    </StaticTiles>
  </TransInfo>
  <TransInfo Description="Autocorrect" HashKey="801212801280801212">
    <MapTiles>
      <MapTile TileID="3" AltIDMod="0" />
      <MapTile TileID="4" AltIDMod="0" />
      <MapTile TileID="5" AltIDMod="0" />
      <MapTile TileID="6" AltIDMod="0" />
    </MapTiles>
    <StaticTiles>
    </StaticTiles>
  </TransInfo>
  <TransInfo Description="Autocorrect" HashKey="801212121280128012">
    <MapTiles>
      <MapTile TileID="3" AltIDMod="0" />
      <MapTile TileID="4" AltIDMod="0" />
      <MapTile TileID="5" AltIDMod="0" />
      <MapTile TileID="6" AltIDMod="0" />
    </MapTiles>
    <StaticTiles>
    </StaticTiles>
  </TransInfo>
  <TransInfo Description="Autocorrect" HashKey="801212801280128012">
    <MapTiles>
      <MapTile TileID="3" AltIDMod="0" />
      <MapTile TileID="4" AltIDMod="0" />
      <MapTile TileID="5" AltIDMod="0" />
      <MapTile TileID="6" AltIDMod="0" />
    </MapTiles>
    <StaticTiles>
    </StaticTiles>
  </TransInfo>
  <TransInfo Description="Autocorrect" HashKey="801212121280808012">
    <MapTiles>
      <MapTile TileID="3" AltIDMod="0" />
      <MapTile TileID="4" AltIDMod="0" />
      <MapTile TileID="5" AltIDMod="0" />
      <MapTile TileID="6" AltIDMod="0" />
    </MapTiles>
    <StaticTiles>
    </StaticTiles>
  </TransInfo>
  <TransInfo Description="Autocorrect" HashKey="801212801280808012">
    <MapTiles>
      <MapTile TileID="3" AltIDMod="0" />
      <MapTile TileID="4" AltIDMod="0" />
      <MapTile TileID="5" AltIDMod="0" />
      <MapTile TileID="6" AltIDMod="0" />
    </MapTiles>
    <StaticTiles>
    </StaticTiles>
  </TransInfo>
  <TransInfo Description="Autocorrect" HashKey="801212801280121280">
    <MapTiles>
      <MapTile TileID="3" AltIDMod="0" />
      <MapTile TileID="4" AltIDMod="0" />
      <MapTile TileID="5" AltIDMod="0" />
      <MapTile TileID="6" AltIDMod="0" />
    </MapTiles>
    <StaticTiles>
    </StaticTiles>
  </TransInfo>
  <TransInfo Description="Autocorrect" HashKey="801212121280801280">
    <MapTiles>
      <MapTile TileID="3" AltIDMod="0" />
      <MapTile TileID="4" AltIDMod="0" />
      <MapTile TileID="5" AltIDMod="0" />
      <MapTile TileID="6" AltIDMod="0" />
    </MapTiles>
    <StaticTiles>
    </StaticTiles>
  </TransInfo>
  <TransInfo Description="Autocorrect" HashKey="801212801280801280">
    <MapTiles>
      <MapTile TileID="3" AltIDMod="0" />
      <MapTile TileID="4" AltIDMod="0" />
      <MapTile TileID="5" AltIDMod="0" />
      <MapTile TileID="6" AltIDMod="0" />
    </MapTiles>
    <StaticTiles>
    </StaticTiles>
  </TransInfo>
  <TransInfo Description="Autocorrect" HashKey="801212121280128080">
    <MapTiles>
      <MapTile TileID="3" AltIDMod="0" />
      <MapTile TileID="4" AltIDMod="0" />
      <MapTile TileID="5" AltIDMod="0" />
      <MapTile TileID="6" AltIDMod="0" />
    </MapTiles>
    <StaticTiles>
    </StaticTiles>
  </TransInfo>
  <TransInfo Description="Autocorrect" HashKey="801212801280128080">
    <MapTiles>
      <MapTile TileID="3" AltIDMod="0" />
      <MapTile TileID="4" AltIDMod="0" />
      <MapTile TileID="5" AltIDMod="0" />
      <MapTile TileID="6" AltIDMod="0" />
    </MapTiles>
    <StaticTiles>
    </StaticTiles>
  </TransInfo>
  <TransInfo Description="Autocorrect" HashKey="801212121280808080">
    <MapTiles>
      <MapTile TileID="3" AltIDMod="0" />
      <MapTile TileID="4" AltIDMod="0" />
      <MapTile TileID="5" AltIDMod="0" />
      <MapTile TileID="6" AltIDMod="0" />
    </MapTiles>
    <StaticTiles>
    </StaticTiles>
  </TransInfo>
  <TransInfo Description="Autocorrect" HashKey="801212801280808080">
    <MapTiles>
      <MapTile TileID="3" AltIDMod="0" />
      <MapTile TileID="4" AltIDMod="0" />
      <MapTile TileID="5" AltIDMod="0" />
      <MapTile TileID="6" AltIDMod="0" />
    </MapTiles>
    <StaticTiles>
    </StaticTiles>
  </TransInfo>
  <TransInfo Description="Autocorrect" HashKey="801280121212128012">
    <MapTiles>
      <MapTile TileID="3" AltIDMod="0" />
      <MapTile TileID="4" AltIDMod="0" />
      <MapTile TileID="5" AltIDMod="0" />
      <MapTile TileID="6" AltIDMod="0" />
    </MapTiles>
    <StaticTiles>
    </StaticTiles>
  </TransInfo>
  <TransInfo Description="Autocorrect" HashKey="801280801212128012">
    <MapTiles>
      <MapTile TileID="3" AltIDMod="0" />
      <MapTile TileID="4" AltIDMod="0" />
      <MapTile TileID="5" AltIDMod="0" />
      <MapTile TileID="6" AltIDMod="0" />
    </MapTiles>
    <StaticTiles>
    </StaticTiles>
  </TransInfo>
  <TransInfo Description="Autocorrect" HashKey="801280121212808012">
    <MapTiles>
      <MapTile TileID="3" AltIDMod="0" />
      <MapTile TileID="4" AltIDMod="0" />
      <MapTile TileID="5" AltIDMod="0" />
      <MapTile TileID="6" AltIDMod="0" />
    </MapTiles>
    <StaticTiles>
    </StaticTiles>
  </TransInfo>
  <TransInfo Description="Autocorrect" HashKey="801280801212808012">
    <MapTiles>
      <MapTile TileID="3" AltIDMod="0" />
      <MapTile TileID="4" AltIDMod="0" />
      <MapTile TileID="5" AltIDMod="0" />
      <MapTile TileID="6" AltIDMod="0" />
    </MapTiles>
    <StaticTiles>
    </StaticTiles>
  </TransInfo>
  <TransInfo Description="Autocorrect" HashKey="801280801212121280">
    <MapTiles>
      <MapTile TileID="3" AltIDMod="0" />
      <MapTile TileID="4" AltIDMod="0" />
      <MapTile TileID="5" AltIDMod="0" />
      <MapTile TileID="6" AltIDMod="0" />
    </MapTiles>
    <StaticTiles>
    </StaticTiles>
  </TransInfo>
  <TransInfo Description="Autocorrect" HashKey="801280121212801280">
    <MapTiles>
      <MapTile TileID="3" AltIDMod="0" />
      <MapTile TileID="4" AltIDMod="0" />
      <MapTile TileID="5" AltIDMod="0" />
      <MapTile TileID="6" AltIDMod="0" />
    </MapTiles>
    <StaticTiles>
    </StaticTiles>
  </TransInfo>
  <TransInfo Description="Autocorrect" HashKey="801280801212801280">
    <MapTiles>
      <MapTile TileID="3" AltIDMod="0" />
      <MapTile TileID="4" AltIDMod="0" />
      <MapTile TileID="5" AltIDMod="0" />
      <MapTile TileID="6" AltIDMod="0" />
    </MapTiles>
    <StaticTiles>
    </StaticTiles>
  </TransInfo>
  <TransInfo Description="Autocorrect" HashKey="801280121212128080">
    <MapTiles>
      <MapTile TileID="3" AltIDMod="0" />
      <MapTile TileID="4" AltIDMod="0" />
      <MapTile TileID="5" AltIDMod="0" />
      <MapTile TileID="6" AltIDMod="0" />
    </MapTiles>
    <StaticTiles>
    </StaticTiles>
  </TransInfo>
  <TransInfo Description="Autocorrect" HashKey="801280801212128080">
    <MapTiles>
      <MapTile TileID="3" AltIDMod="0" />
      <MapTile TileID="4" AltIDMod="0" />
      <MapTile TileID="5" AltIDMod="0" />
      <MapTile TileID="6" AltIDMod="0" />
    </MapTiles>
    <StaticTiles>
    </StaticTiles>
  </TransInfo>
  <TransInfo Description="Autocorrect" HashKey="801280121212808080">
    <MapTiles>
      <MapTile TileID="3" AltIDMod="0" />
      <MapTile TileID="4" AltIDMod="0" />
      <MapTile TileID="5" AltIDMod="0" />
      <MapTile TileID="6" AltIDMod="0" />
    </MapTiles>
    <StaticTiles>
    </StaticTiles>
  </TransInfo>
  <TransInfo Description="Autocorrect" HashKey="801280801212808080">
    <MapTiles>
      <MapTile TileID="3" AltIDMod="0" />
      <MapTile TileID="4" AltIDMod="0" />
      <MapTile TileID="5" AltIDMod="0" />
      <MapTile TileID="6" AltIDMod="0" />
    </MapTiles>
    <StaticTiles>
    </StaticTiles>
  </TransInfo>
  <TransInfo Description="Autocorrect" HashKey="801280801280121212">
    <MapTiles>
      <MapTile TileID="3" AltIDMod="0" />
      <MapTile TileID="4" AltIDMod="0" />
      <MapTile TileID="5" AltIDMod="0" />
      <MapTile TileID="6" AltIDMod="0" />
    </MapTiles>
    <StaticTiles>
    </StaticTiles>
  </TransInfo>
  <TransInfo Description="Autocorrect" HashKey="801280121280801212">
    <MapTiles>
      <MapTile TileID="3" AltIDMod="0" />
      <MapTile TileID="4" AltIDMod="0" />
      <MapTile TileID="5" AltIDMod="0" />
      <MapTile TileID="6" AltIDMod="0" />
    </MapTiles>
    <StaticTiles>
    </StaticTiles>
  </TransInfo>
  <TransInfo Description="Autocorrect" HashKey="801280801280801212">
    <MapTiles>
      <MapTile TileID="3" AltIDMod="0" />
      <MapTile TileID="4" AltIDMod="0" />
      <MapTile TileID="5" AltIDMod="0" />
      <MapTile TileID="6" AltIDMod="0" />
    </MapTiles>
    <StaticTiles>
    </StaticTiles>
  </TransInfo>
  <TransInfo Description="Autocorrect" HashKey="801280121280128012">
    <MapTiles>
      <MapTile TileID="3" AltIDMod="0" />
      <MapTile TileID="4" AltIDMod="0" />
      <MapTile TileID="5" AltIDMod="0" />
      <MapTile TileID="6" AltIDMod="0" />
    </MapTiles>
    <StaticTiles>
    </StaticTiles>
  </TransInfo>
  <TransInfo Description="Autocorrect" HashKey="801280801280128012">
    <MapTiles>
      <MapTile TileID="3" AltIDMod="0" />
      <MapTile TileID="4" AltIDMod="0" />
      <MapTile TileID="5" AltIDMod="0" />
      <MapTile TileID="6" AltIDMod="0" />
    </MapTiles>
    <StaticTiles>
    </StaticTiles>
  </TransInfo>
  <TransInfo Description="Autocorrect" HashKey="801280121280808012">
    <MapTiles>
      <MapTile TileID="3" AltIDMod="0" />
      <MapTile TileID="4" AltIDMod="0" />
      <MapTile TileID="5" AltIDMod="0" />
      <MapTile TileID="6" AltIDMod="0" />
    </MapTiles>
    <StaticTiles>
    </StaticTiles>
  </TransInfo>
  <TransInfo Description="Autocorrect" HashKey="801280801280808012">
    <MapTiles>
      <MapTile TileID="3" AltIDMod="0" />
      <MapTile TileID="4" AltIDMod="0" />
      <MapTile TileID="5" AltIDMod="0" />
      <MapTile TileID="6" AltIDMod="0" />
    </MapTiles>
    <StaticTiles>
    </StaticTiles>
  </TransInfo>
  <TransInfo Description="Autocorrect" HashKey="801280801280121280">
    <MapTiles>
      <MapTile TileID="3" AltIDMod="0" />
      <MapTile TileID="4" AltIDMod="0" />
      <MapTile TileID="5" AltIDMod="0" />
      <MapTile TileID="6" AltIDMod="0" />
    </MapTiles>
    <StaticTiles>
    </StaticTiles>
  </TransInfo>
  <TransInfo Description="Autocorrect" HashKey="801280121280801280">
    <MapTiles>
      <MapTile TileID="3" AltIDMod="0" />
      <MapTile TileID="4" AltIDMod="0" />
      <MapTile TileID="5" AltIDMod="0" />
      <MapTile TileID="6" AltIDMod="0" />
    </MapTiles>
    <StaticTiles>
    </StaticTiles>
  </TransInfo>
  <TransInfo Description="Autocorrect" HashKey="801280801280801280">
    <MapTiles>
      <MapTile TileID="3" AltIDMod="0" />
      <MapTile TileID="4" AltIDMod="0" />
      <MapTile TileID="5" AltIDMod="0" />
      <MapTile TileID="6" AltIDMod="0" />
    </MapTiles>
    <StaticTiles>
    </StaticTiles>
  </TransInfo>
  <TransInfo Description="Autocorrect" HashKey="801280121280128080">
    <MapTiles>
      <MapTile TileID="3" AltIDMod="0" />
      <MapTile TileID="4" AltIDMod="0" />
      <MapTile TileID="5" AltIDMod="0" />
      <MapTile TileID="6" AltIDMod="0" />
    </MapTiles>
    <StaticTiles>
    </StaticTiles>
  </TransInfo>
  <TransInfo Description="Autocorrect" HashKey="801280801280128080">
    <MapTiles>
      <MapTile TileID="3" AltIDMod="0" />
      <MapTile TileID="4" AltIDMod="0" />
      <MapTile TileID="5" AltIDMod="0" />
      <MapTile TileID="6" AltIDMod="0" />
    </MapTiles>
    <StaticTiles>
    </StaticTiles>
  </TransInfo>
  <TransInfo Description="Autocorrect" HashKey="801280121280808080">
    <MapTiles>
      <MapTile TileID="3" AltIDMod="0" />
      <MapTile TileID="4" AltIDMod="0" />
      <MapTile TileID="5" AltIDMod="0" />
      <MapTile TileID="6" AltIDMod="0" />
    </MapTiles>
    <StaticTiles>
    </StaticTiles>
  </TransInfo>
  <TransInfo Description="Autocorrect" HashKey="801280801280808080">
    <MapTiles>
      <MapTile TileID="3" AltIDMod="0" />
      <MapTile TileID="4" AltIDMod="0" />
      <MapTile TileID="5" AltIDMod="0" />
      <MapTile TileID="6" AltIDMod="0" />
    </MapTiles>
    <StaticTiles>
    </StaticTiles>
  </TransInfo>
  <TransInfo Description="Autocorrect" HashKey="808012121212128012">
    <MapTiles>
      <MapTile TileID="3" AltIDMod="0" />
      <MapTile TileID="4" AltIDMod="0" />
      <MapTile TileID="5" AltIDMod="0" />
      <MapTile TileID="6" AltIDMod="0" />
    </MapTiles>
    <StaticTiles>
    </StaticTiles>
  </TransInfo>
  <TransInfo Description="Autocorrect" HashKey="808012801212128012">
    <MapTiles>
      <MapTile TileID="3" AltIDMod="0" />
      <MapTile TileID="4" AltIDMod="0" />
      <MapTile TileID="5" AltIDMod="0" />
      <MapTile TileID="6" AltIDMod="0" />
    </MapTiles>
    <StaticTiles>
    </StaticTiles>
  </TransInfo>
  <TransInfo Description="Autocorrect" HashKey="808012121212808012">
    <MapTiles>
      <MapTile TileID="3" AltIDMod="0" />
      <MapTile TileID="4" AltIDMod="0" />
      <MapTile TileID="5" AltIDMod="0" />
      <MapTile TileID="6" AltIDMod="0" />
    </MapTiles>
    <StaticTiles>
    </StaticTiles>
  </TransInfo>
  <TransInfo Description="Autocorrect" HashKey="808012801212808012">
    <MapTiles>
      <MapTile TileID="3" AltIDMod="0" />
      <MapTile TileID="4" AltIDMod="0" />
      <MapTile TileID="5" AltIDMod="0" />
      <MapTile TileID="6" AltIDMod="0" />
    </MapTiles>
    <StaticTiles>
    </StaticTiles>
  </TransInfo>
  <TransInfo Description="Autocorrect" HashKey="808012801212121280">
    <MapTiles>
      <MapTile TileID="3" AltIDMod="0" />
      <MapTile TileID="4" AltIDMod="0" />
      <MapTile TileID="5" AltIDMod="0" />
      <MapTile TileID="6" AltIDMod="0" />
    </MapTiles>
    <StaticTiles>
    </StaticTiles>
  </TransInfo>
  <TransInfo Description="Autocorrect" HashKey="808012121212801280">
    <MapTiles>
      <MapTile TileID="3" AltIDMod="0" />
      <MapTile TileID="4" AltIDMod="0" />
      <MapTile TileID="5" AltIDMod="0" />
      <MapTile TileID="6" AltIDMod="0" />
    </MapTiles>
    <StaticTiles>
    </StaticTiles>
  </TransInfo>
  <TransInfo Description="Autocorrect" HashKey="808012801212801280">
    <MapTiles>
      <MapTile TileID="3" AltIDMod="0" />
      <MapTile TileID="4" AltIDMod="0" />
      <MapTile TileID="5" AltIDMod="0" />
      <MapTile TileID="6" AltIDMod="0" />
    </MapTiles>
    <StaticTiles>
    </StaticTiles>
  </TransInfo>
  <TransInfo Description="Autocorrect" HashKey="808012121212128080">
    <MapTiles>
      <MapTile TileID="3" AltIDMod="0" />
      <MapTile TileID="4" AltIDMod="0" />
      <MapTile TileID="5" AltIDMod="0" />
      <MapTile TileID="6" AltIDMod="0" />
    </MapTiles>
    <StaticTiles>
    </StaticTiles>
  </TransInfo>
  <TransInfo Description="Autocorrect" HashKey="808012801212128080">
    <MapTiles>
      <MapTile TileID="3" AltIDMod="0" />
      <MapTile TileID="4" AltIDMod="0" />
      <MapTile TileID="5" AltIDMod="0" />
      <MapTile TileID="6" AltIDMod="0" />
    </MapTiles>
    <StaticTiles>
    </StaticTiles>
  </TransInfo>
  <TransInfo Description="Autocorrect" HashKey="808012121212808080">
    <MapTiles>
      <MapTile TileID="3" AltIDMod="0" />
      <MapTile TileID="4" AltIDMod="0" />
      <MapTile TileID="5" AltIDMod="0" />
      <MapTile TileID="6" AltIDMod="0" />
    </MapTiles>
    <StaticTiles>
    </StaticTiles>
  </TransInfo>
  <TransInfo Description="Autocorrect" HashKey="808012801212808080">
    <MapTiles>
      <MapTile TileID="3" AltIDMod="0" />
      <MapTile TileID="4" AltIDMod="0" />
      <MapTile TileID="5" AltIDMod="0" />
      <MapTile TileID="6" AltIDMod="0" />
    </MapTiles>
    <StaticTiles>
    </StaticTiles>
  </TransInfo>
  <TransInfo Description="Autocorrect" HashKey="808012801280121212">
    <MapTiles>
      <MapTile TileID="3" AltIDMod="0" />
      <MapTile TileID="4" AltIDMod="0" />
      <MapTile TileID="5" AltIDMod="0" />
      <MapTile TileID="6" AltIDMod="0" />
    </MapTiles>
    <StaticTiles>
    </StaticTiles>
  </TransInfo>
  <TransInfo Description="Autocorrect" HashKey="808012121280801212">
    <MapTiles>
      <MapTile TileID="3" AltIDMod="0" />
      <MapTile TileID="4" AltIDMod="0" />
      <MapTile TileID="5" AltIDMod="0" />
      <MapTile TileID="6" AltIDMod="0" />
    </MapTiles>
    <StaticTiles>
    </StaticTiles>
  </TransInfo>
  <TransInfo Description="Autocorrect" HashKey="808012801280801212">
    <MapTiles>
      <MapTile TileID="3" AltIDMod="0" />
      <MapTile TileID="4" AltIDMod="0" />
      <MapTile TileID="5" AltIDMod="0" />
      <MapTile TileID="6" AltIDMod="0" />
    </MapTiles>
    <StaticTiles>
    </StaticTiles>
  </TransInfo>
  <TransInfo Description="Autocorrect" HashKey="808012121280128012">
    <MapTiles>
      <MapTile TileID="3" AltIDMod="0" />
      <MapTile TileID="4" AltIDMod="0" />
      <MapTile TileID="5" AltIDMod="0" />
      <MapTile TileID="6" AltIDMod="0" />
    </MapTiles>
    <StaticTiles>
    </StaticTiles>
  </TransInfo>
  <TransInfo Description="Autocorrect" HashKey="808012801280128012">
    <MapTiles>
      <MapTile TileID="3" AltIDMod="0" />
      <MapTile TileID="4" AltIDMod="0" />
      <MapTile TileID="5" AltIDMod="0" />
      <MapTile TileID="6" AltIDMod="0" />
    </MapTiles>
    <StaticTiles>
    </StaticTiles>
  </TransInfo>
  <TransInfo Description="Autocorrect" HashKey="808012121280808012">
    <MapTiles>
      <MapTile TileID="3" AltIDMod="0" />
      <MapTile TileID="4" AltIDMod="0" />
      <MapTile TileID="5" AltIDMod="0" />
      <MapTile TileID="6" AltIDMod="0" />
    </MapTiles>
    <StaticTiles>
    </StaticTiles>
  </TransInfo>
  <TransInfo Description="Autocorrect" HashKey="808012801280808012">
    <MapTiles>
      <MapTile TileID="3" AltIDMod="0" />
      <MapTile TileID="4" AltIDMod="0" />
      <MapTile TileID="5" AltIDMod="0" />
      <MapTile TileID="6" AltIDMod="0" />
    </MapTiles>
    <StaticTiles>
    </StaticTiles>
  </TransInfo>
  <TransInfo Description="Autocorrect" HashKey="808012801280121280">
    <MapTiles>
      <MapTile TileID="3" AltIDMod="0" />
      <MapTile TileID="4" AltIDMod="0" />
      <MapTile TileID="5" AltIDMod="0" />
      <MapTile TileID="6" AltIDMod="0" />
    </MapTiles>
    <StaticTiles>
    </StaticTiles>
  </TransInfo>
  <TransInfo Description="Autocorrect" HashKey="808012121280801280">
    <MapTiles>
      <MapTile TileID="3" AltIDMod="0" />
      <MapTile TileID="4" AltIDMod="0" />
      <MapTile TileID="5" AltIDMod="0" />
      <MapTile TileID="6" AltIDMod="0" />
    </MapTiles>
    <StaticTiles>
    </StaticTiles>
  </TransInfo>
  <TransInfo Description="Autocorrect" HashKey="808012801280801280">
    <MapTiles>
      <MapTile TileID="3" AltIDMod="0" />
      <MapTile TileID="4" AltIDMod="0" />
      <MapTile TileID="5" AltIDMod="0" />
      <MapTile TileID="6" AltIDMod="0" />
    </MapTiles>
    <StaticTiles>
    </StaticTiles>
  </TransInfo>
  <TransInfo Description="Autocorrect" HashKey="808012121280128080">
    <MapTiles>
      <MapTile TileID="3" AltIDMod="0" />
      <MapTile TileID="4" AltIDMod="0" />
      <MapTile TileID="5" AltIDMod="0" />
      <MapTile TileID="6" AltIDMod="0" />
    </MapTiles>
    <StaticTiles>
    </StaticTiles>
  </TransInfo>
  <TransInfo Description="Autocorrect" HashKey="808012801280128080">
    <MapTiles>
      <MapTile TileID="3" AltIDMod="0" />
      <MapTile TileID="4" AltIDMod="0" />
      <MapTile TileID="5" AltIDMod="0" />
      <MapTile TileID="6" AltIDMod="0" />
    </MapTiles>
    <StaticTiles>
    </StaticTiles>
  </TransInfo>
  <TransInfo Description="Autocorrect" HashKey="808012121280808080">
    <MapTiles>
      <MapTile TileID="3" AltIDMod="0" />
      <MapTile TileID="4" AltIDMod="0" />
      <MapTile TileID="5" AltIDMod="0" />
      <MapTile TileID="6" AltIDMod="0" />
    </MapTiles>
    <StaticTiles>
    </StaticTiles>
  </TransInfo>
  <TransInfo Description="Autocorrect" HashKey="808012801280808080">
    <MapTiles>
      <MapTile TileID="3" AltIDMod="0" />
      <MapTile TileID="4" AltIDMod="0" />
      <MapTile TileID="5" AltIDMod="0" />
      <MapTile TileID="6" AltIDMod="0" />
    </MapTiles>
    <StaticTiles>
    </StaticTiles>
  </TransInfo>
  <TransInfo Description="Autocorrect" HashKey="808080121212128012">
    <MapTiles>
      <MapTile TileID="3" AltIDMod="0" />
      <MapTile TileID="4" AltIDMod="0" />
      <MapTile TileID="5" AltIDMod="0" />
      <MapTile TileID="6" AltIDMod="0" />
    </MapTiles>
    <StaticTiles>
    </StaticTiles>
  </TransInfo>
  <TransInfo Description="Autocorrect" HashKey="808080801212128012">
    <MapTiles>
      <MapTile TileID="3" AltIDMod="0" />
      <MapTile TileID="4" AltIDMod="0" />
      <MapTile TileID="5" AltIDMod="0" />
      <MapTile TileID="6" AltIDMod="0" />
    </MapTiles>
    <StaticTiles>
    </StaticTiles>
  </TransInfo>
  <TransInfo Description="Autocorrect" HashKey="808080121212808012">
    <MapTiles>
      <MapTile TileID="3" AltIDMod="0" />
      <MapTile TileID="4" AltIDMod="0" />
      <MapTile TileID="5" AltIDMod="0" />
      <MapTile TileID="6" AltIDMod="0" />
    </MapTiles>
    <StaticTiles>
    </StaticTiles>
  </TransInfo>
  <TransInfo Description="Autocorrect" HashKey="808080801212808012">
    <MapTiles>
      <MapTile TileID="3" AltIDMod="0" />
      <MapTile TileID="4" AltIDMod="0" />
      <MapTile TileID="5" AltIDMod="0" />
      <MapTile TileID="6" AltIDMod="0" />
    </MapTiles>
    <StaticTiles>
    </StaticTiles>
  </TransInfo>
  <TransInfo Description="Autocorrect" HashKey="808080801212121280">
    <MapTiles>
      <MapTile TileID="3" AltIDMod="0" />
      <MapTile TileID="4" AltIDMod="0" />
      <MapTile TileID="5" AltIDMod="0" />
      <MapTile TileID="6" AltIDMod="0" />
    </MapTiles>
    <StaticTiles>
    </StaticTiles>
  </TransInfo>
  <TransInfo Description="Autocorrect" HashKey="808080121212801280">
    <MapTiles>
      <MapTile TileID="3" AltIDMod="0" />
      <MapTile TileID="4" AltIDMod="0" />
      <MapTile TileID="5" AltIDMod="0" />
      <MapTile TileID="6" AltIDMod="0" />
    </MapTiles>
    <StaticTiles>
    </StaticTiles>
  </TransInfo>
  <TransInfo Description="Autocorrect" HashKey="808080801212801280">
    <MapTiles>
      <MapTile TileID="3" AltIDMod="0" />
      <MapTile TileID="4" AltIDMod="0" />
      <MapTile TileID="5" AltIDMod="0" />
      <MapTile TileID="6" AltIDMod="0" />
    </MapTiles>
    <StaticTiles>
    </StaticTiles>
  </TransInfo>
  <TransInfo Description="Autocorrect" HashKey="808080121212128080">
    <MapTiles>
      <MapTile TileID="3" AltIDMod="0" />
      <MapTile TileID="4" AltIDMod="0" />
      <MapTile TileID="5" AltIDMod="0" />
      <MapTile TileID="6" AltIDMod="0" />
    </MapTiles>
    <StaticTiles>
    </StaticTiles>
  </TransInfo>
  <TransInfo Description="Autocorrect" HashKey="808080801212128080">
    <MapTiles>
      <MapTile TileID="3" AltIDMod="0" />
      <MapTile TileID="4" AltIDMod="0" />
      <MapTile TileID="5" AltIDMod="0" />
      <MapTile TileID="6" AltIDMod="0" />
    </MapTiles>
    <StaticTiles>
    </StaticTiles>
  </TransInfo>
  <TransInfo Description="Autocorrect" HashKey="808080121212808080">
    <MapTiles>
      <MapTile TileID="3" AltIDMod="0" />
      <MapTile TileID="4" AltIDMod="0" />
      <MapTile TileID="5" AltIDMod="0" />
      <MapTile TileID="6" AltIDMod="0" />
    </MapTiles>
    <StaticTiles>
    </StaticTiles>
  </TransInfo>
  <TransInfo Description="Autocorrect" HashKey="808080801212808080">
    <MapTiles>
      <MapTile TileID="3" AltIDMod="0" />
      <MapTile TileID="4" AltIDMod="0" />
      <MapTile TileID="5" AltIDMod="0" />
      <MapTile TileID="6" AltIDMod="0" />
    </MapTiles>
    <StaticTiles>
    </StaticTiles>
  </TransInfo>
  <TransInfo Description="Autocorrect" HashKey="808080801280121212">
    <MapTiles>
      <MapTile TileID="3" AltIDMod="0" />
      <MapTile TileID="4" AltIDMod="0" />
      <MapTile TileID="5" AltIDMod="0" />
      <MapTile TileID="6" AltIDMod="0" />
    </MapTiles>
    <StaticTiles>
    </StaticTiles>
  </TransInfo>
  <TransInfo Description="Autocorrect" HashKey="808080121280801212">
    <MapTiles>
      <MapTile TileID="3" AltIDMod="0" />
      <MapTile TileID="4" AltIDMod="0" />
      <MapTile TileID="5" AltIDMod="0" />
      <MapTile TileID="6" AltIDMod="0" />
    </MapTiles>
    <StaticTiles>
    </StaticTiles>
  </TransInfo>
  <TransInfo Description="Autocorrect" HashKey="808080801280801212">
    <MapTiles>
      <MapTile TileID="3" AltIDMod="0" />
      <MapTile TileID="4" AltIDMod="0" />
      <MapTile TileID="5" AltIDMod="0" />
      <MapTile TileID="6" AltIDMod="0" />
    </MapTiles>
    <StaticTiles>
    </StaticTiles>
  </TransInfo>
  <TransInfo Description="Autocorrect" HashKey="808080121280128012">
    <MapTiles>
      <MapTile TileID="3" AltIDMod="0" />
      <MapTile TileID="4" AltIDMod="0" />
      <MapTile TileID="5" AltIDMod="0" />
      <MapTile TileID="6" AltIDMod="0" />
    </MapTiles>
    <StaticTiles>
    </StaticTiles>
  </TransInfo>
  <TransInfo Description="Autocorrect" HashKey="808080801280128012">
    <MapTiles>
      <MapTile TileID="3" AltIDMod="0" />
      <MapTile TileID="4" AltIDMod="0" />
      <MapTile TileID="5" AltIDMod="0" />
      <MapTile TileID="6" AltIDMod="0" />
    </MapTiles>
    <StaticTiles>
    </StaticTiles>
  </TransInfo>
  <TransInfo Description="Autocorrect" HashKey="808080121280808012">
    <MapTiles>
      <MapTile TileID="3" AltIDMod="0" />
      <MapTile TileID="4" AltIDMod="0" />
      <MapTile TileID="5" AltIDMod="0" />
      <MapTile TileID="6" AltIDMod="0" />
    </MapTiles>
    <StaticTiles>
    </StaticTiles>
  </TransInfo>
  <TransInfo Description="Autocorrect" HashKey="808080801280808012">
    <MapTiles>
      <MapTile TileID="3" AltIDMod="0" />
      <MapTile TileID="4" AltIDMod="0" />
      <MapTile TileID="5" AltIDMod="0" />
      <MapTile TileID="6" AltIDMod="0" />
    </MapTiles>
    <StaticTiles>
    </StaticTiles>
  </TransInfo>
  <TransInfo Description="Autocorrect" HashKey="808080801280121280">
    <MapTiles>
      <MapTile TileID="3" AltIDMod="0" />
      <MapTile TileID="4" AltIDMod="0" />
      <MapTile TileID="5" AltIDMod="0" />
      <MapTile TileID="6" AltIDMod="0" />
    </MapTiles>
    <StaticTiles>
    </StaticTiles>
  </TransInfo>
  <TransInfo Description="Autocorrect" HashKey="808080121280801280">
    <MapTiles>
      <MapTile TileID="3" AltIDMod="0" />
      <MapTile TileID="4" AltIDMod="0" />
      <MapTile TileID="5" AltIDMod="0" />
      <MapTile TileID="6" AltIDMod="0" />
    </MapTiles>
    <StaticTiles>
    </StaticTiles>
  </TransInfo>
  <TransInfo Description="Autocorrect" HashKey="808080801280801280">
    <MapTiles>
      <MapTile TileID="3" AltIDMod="0" />
      <MapTile TileID="4" AltIDMod="0" />
      <MapTile TileID="5" AltIDMod="0" />
      <MapTile TileID="6" AltIDMod="0" />
    </MapTiles>
    <StaticTiles>
    </StaticTiles>
  </TransInfo>
  <TransInfo Description="Autocorrect" HashKey="808080121280128080">
    <MapTiles>
      <MapTile TileID="3" AltIDMod="0" />
      <MapTile TileID="4" AltIDMod="0" />
      <MapTile TileID="5" AltIDMod="0" />
      <MapTile TileID="6" AltIDMod="0" />
    </MapTiles>
    <StaticTiles>
    </StaticTiles>
  </TransInfo>
  <TransInfo Description="Autocorrect" HashKey="808080801280128080">
    <MapTiles>
      <MapTile TileID="3" AltIDMod="0" />
      <MapTile TileID="4" AltIDMod="0" />
      <MapTile TileID="5" AltIDMod="0" />
      <MapTile TileID="6" AltIDMod="0" />
    </MapTiles>
    <StaticTiles>
    </StaticTiles>
  </TransInfo>
  <TransInfo Description="Autocorrect" HashKey="808080121280808080">
    <MapTiles>
      <MapTile TileID="3" AltIDMod="0" />
      <MapTile TileID="4" AltIDMod="0" />
      <MapTile TileID="5" AltIDMod="0" />
      <MapTile TileID="6" AltIDMod="0" />
    </MapTiles>
    <StaticTiles>
    </StaticTiles>
  </TransInfo>
  <TransInfo Description="Autocorrect" HashKey="808080801280808080">
    <MapTiles>
      <MapTile TileID="3" AltIDMod="0" />
      <MapTile TileID="4" AltIDMod="0" />
      <MapTile TileID="5" AltIDMod="0" />
      <MapTile TileID="6" AltIDMod="0" />
    </MapTiles>
    <StaticTiles>
    </StaticTiles>
  </TransInfo>
  <TransInfo Description="Invalid" HashKey="801212121212121280">
    <MapTiles>
      <MapTile TileID="556" AltIDMod="0" />
      <MapTile TileID="557" AltIDMod="0" />
      <MapTile TileID="558" AltIDMod="0" />
      <MapTile TileID="559" AltIDMod="0" />
    </MapTiles>
    <StaticTiles>
    </StaticTiles>
  </TransInfo>
  <TransInfo Description="Invalid" HashKey="121280121212801212">
    <MapTiles>
      <MapTile TileID="556" AltIDMod="0" />
      <MapTile TileID="557" AltIDMod="0" />
      <MapTile TileID="558" AltIDMod="0" />
      <MapTile TileID="559" AltIDMod="0" />
    </MapTiles>
    <StaticTiles>
    </StaticTiles>
  </TransInfo>
</Trans>