<?xml version="1.0" encoding="utf-8"?>
<Trans>
  <TransInfo Description="Top" HashKey="292929474747474747">
    <MapTiles>
      <MapTile TileID="282" AltIDMod="0" />
      <MapTile TileID="283" AltIDMod="0" />
      <MapTile TileID="284" AltIDMod="0" />
      <MapTile TileID="285" AltIDMod="0" />
    </MapTiles>
    <StaticTiles>
      <StaticTile TileID="12916" AltIDMod="0" />
      <StaticTile TileID="12917" AltIDMod="0" />
    </StaticTiles>
  </TransInfo>
  <TransInfo Description="Top" HashKey="472929474747474747">
    <MapTiles>
      <MapTile TileID="282" AltIDMod="0" />
      <MapTile TileID="283" AltIDMod="0" />
      <MapTile TileID="284" AltIDMod="0" />
      <MapTile TileID="285" AltIDMod="0" />
    </MapTiles>
    <StaticTiles>
      <StaticTile TileID="12916" AltIDMod="0" />
      <StaticTile TileID="12917" AltIDMod="0" />
    </StaticTiles>
  </TransInfo>
  <TransInfo Description="Top" HashKey="292947474747474747">
    <MapTiles>
      <MapTile TileID="282" AltIDMod="0" />
      <MapTile TileID="283" AltIDMod="0" />
      <MapTile TileID="284" AltIDMod="0" />
      <MapTile TileID="285" AltIDMod="0" />
    </MapTiles>
    <StaticTiles>
      <StaticTile TileID="12916" AltIDMod="0" />
      <StaticTile TileID="12917" AltIDMod="0" />
    </StaticTiles>
  </TransInfo>
  <TransInfo Description="Top" HashKey="472947474747474747">
    <MapTiles>
      <MapTile TileID="282" AltIDMod="0" />
      <MapTile TileID="283" AltIDMod="0" />
      <MapTile TileID="284" AltIDMod="0" />
      <MapTile TileID="285" AltIDMod="0" />
    </MapTiles>
    <StaticTiles>
      <StaticTile TileID="12916" AltIDMod="0" />
      <StaticTile TileID="12917" AltIDMod="0" />
    </StaticTiles>
  </TransInfo>
  <TransInfo Description="Top" HashKey="294729474747474747">
    <MapTiles>
      <MapTile TileID="282" AltIDMod="0" />
      <MapTile TileID="283" AltIDMod="0" />
      <MapTile TileID="284" AltIDMod="0" />
      <MapTile TileID="285" AltIDMod="0" />
    </MapTiles>
    <StaticTiles>
      <StaticTile TileID="12916" AltIDMod="0" />
      <StaticTile TileID="12917" AltIDMod="0" />
    </StaticTiles>
  </TransInfo>
  <TransInfo Description="Left" HashKey="294747294747294747">
    <MapTiles>
      <MapTile TileID="282" AltIDMod="0" />
      <MapTile TileID="283" AltIDMod="0" />
      <MapTile TileID="284" AltIDMod="0" />
      <MapTile TileID="285" AltIDMod="0" />
    </MapTiles>
    <StaticTiles>
      <StaticTile TileID="12912" AltIDMod="0" />
      <StaticTile TileID="12913" AltIDMod="0" />
    </StaticTiles>
  </TransInfo>
  <TransInfo Description="Left" HashKey="294747294747474747">
    <MapTiles>
      <MapTile TileID="282" AltIDMod="0" />
      <MapTile TileID="283" AltIDMod="0" />
      <MapTile TileID="284" AltIDMod="0" />
      <MapTile TileID="285" AltIDMod="0" />
    </MapTiles>
    <StaticTiles>
      <StaticTile TileID="12912" AltIDMod="0" />
      <StaticTile TileID="12913" AltIDMod="0" />
    </StaticTiles>
  </TransInfo>
  <TransInfo Description="Left" HashKey="474747294747294747">
    <MapTiles>
      <MapTile TileID="282" AltIDMod="0" />
      <MapTile TileID="283" AltIDMod="0" />
      <MapTile TileID="284" AltIDMod="0" />
      <MapTile TileID="285" AltIDMod="0" />
    </MapTiles>
    <StaticTiles>
      <StaticTile TileID="12912" AltIDMod="0" />
      <StaticTile TileID="12913" AltIDMod="0" />
    </StaticTiles>
  </TransInfo>
  <TransInfo Description="Left" HashKey="474747294747474747">
    <MapTiles>
      <MapTile TileID="282" AltIDMod="0" />
      <MapTile TileID="283" AltIDMod="0" />
      <MapTile TileID="284" AltIDMod="0" />
      <MapTile TileID="285" AltIDMod="0" />
    </MapTiles>
    <StaticTiles>
      <StaticTile TileID="12912" AltIDMod="0" />
      <StaticTile TileID="12913" AltIDMod="0" />
    </StaticTiles>
  </TransInfo>
  <TransInfo Description="Left" HashKey="294747474747294747">
    <MapTiles>
      <MapTile TileID="282" AltIDMod="0" />
      <MapTile TileID="283" AltIDMod="0" />
      <MapTile TileID="284" AltIDMod="0" />
      <MapTile TileID="285" AltIDMod="0" />
    </MapTiles>
    <StaticTiles>
      <StaticTile TileID="12912" AltIDMod="0" />
      <StaticTile TileID="12913" AltIDMod="0" />
    </StaticTiles>
  </TransInfo>
  <TransInfo Description="Right" HashKey="474729474729474729">
    <MapTiles>
      <MapTile TileID="282" AltIDMod="0" />
      <MapTile TileID="283" AltIDMod="0" />
      <MapTile TileID="284" AltIDMod="0" />
      <MapTile TileID="285" AltIDMod="0" />
    </MapTiles>
    <StaticTiles>
      <StaticTile TileID="12918" AltIDMod="0" />
      <StaticTile TileID="12919" AltIDMod="0" />
    </StaticTiles>
  </TransInfo>
  <TransInfo Description="Right" HashKey="474747474729474729">
    <MapTiles>
      <MapTile TileID="282" AltIDMod="0" />
      <MapTile TileID="283" AltIDMod="0" />
      <MapTile TileID="284" AltIDMod="0" />
      <MapTile TileID="285" AltIDMod="0" />
    </MapTiles>
    <StaticTiles>
      <StaticTile TileID="12918" AltIDMod="0" />
      <StaticTile TileID="12919" AltIDMod="0" />
    </StaticTiles>
  </TransInfo>
  <TransInfo Description="Right" HashKey="474729474729474747">
    <MapTiles>
      <MapTile TileID="282" AltIDMod="0" />
      <MapTile TileID="283" AltIDMod="0" />
      <MapTile TileID="284" AltIDMod="0" />
      <MapTile TileID="285" AltIDMod="0" />
    </MapTiles>
    <StaticTiles>
      <StaticTile TileID="12918" AltIDMod="0" />
      <StaticTile TileID="12919" AltIDMod="0" />
    </StaticTiles>
  </TransInfo>
  <TransInfo Description="Right" HashKey="474747474729474747">
    <MapTiles>
      <MapTile TileID="282" AltIDMod="0" />
      <MapTile TileID="283" AltIDMod="0" />
      <MapTile TileID="284" AltIDMod="0" />
      <MapTile TileID="285" AltIDMod="0" />
    </MapTiles>
    <StaticTiles>
      <StaticTile TileID="12918" AltIDMod="0" />
      <StaticTile TileID="12919" AltIDMod="0" />
    </StaticTiles>
  </TransInfo>
  <TransInfo Description="Right" HashKey="474729474747474729">
    <MapTiles>
      <MapTile TileID="282" AltIDMod="0" />
      <MapTile TileID="283" AltIDMod="0" />
      <MapTile TileID="284" AltIDMod="0" />
      <MapTile TileID="285" AltIDMod="0" />
    </MapTiles>
    <StaticTiles>
      <StaticTile TileID="12918" AltIDMod="0" />
      <StaticTile TileID="12919" AltIDMod="0" />
    </StaticTiles>
  </TransInfo>
  <TransInfo Description="Bottom" HashKey="474747474747292929">
    <MapTiles>
      <MapTile TileID="282" AltIDMod="0" />
      <MapTile TileID="283" AltIDMod="0" />
      <MapTile TileID="284" AltIDMod="0" />
      <MapTile TileID="285" AltIDMod="0" />
    </MapTiles>
    <StaticTiles>
      <StaticTile TileID="12914" AltIDMod="0" />
      <StaticTile TileID="12915" AltIDMod="0" />
    </StaticTiles>
  </TransInfo>
  <TransInfo Description="Bottom" HashKey="474747474747292947">
    <MapTiles>
      <MapTile TileID="282" AltIDMod="0" />
      <MapTile TileID="283" AltIDMod="0" />
      <MapTile TileID="284" AltIDMod="0" />
      <MapTile TileID="285" AltIDMod="0" />
    </MapTiles>
    <StaticTiles>
      <StaticTile TileID="12914" AltIDMod="0" />
      <StaticTile TileID="12915" AltIDMod="0" />
    </StaticTiles>
  </TransInfo>
  <TransInfo Description="Bottom" HashKey="474747474747472929">
    <MapTiles>
      <MapTile TileID="282" AltIDMod="0" />
      <MapTile TileID="283" AltIDMod="0" />
      <MapTile TileID="284" AltIDMod="0" />
      <MapTile TileID="285" AltIDMod="0" />
    </MapTiles>
    <StaticTiles>
      <StaticTile TileID="12914" AltIDMod="0" />
      <StaticTile TileID="12915" AltIDMod="0" />
    </StaticTiles>
  </TransInfo>
  <TransInfo Description="Bottom" HashKey="474747474747472947">
    <MapTiles>
      <MapTile TileID="282" AltIDMod="0" />
      <MapTile TileID="283" AltIDMod="0" />
      <MapTile TileID="284" AltIDMod="0" />
      <MapTile TileID="285" AltIDMod="0" />
    </MapTiles>
    <StaticTiles>
      <StaticTile TileID="12914" AltIDMod="0" />
      <StaticTile TileID="12915" AltIDMod="0" />
    </StaticTiles>
  </TransInfo>
  <TransInfo Description="Bottom" HashKey="474747474747294729">
    <MapTiles>
      <MapTile TileID="282" AltIDMod="0" />
      <MapTile TileID="283" AltIDMod="0" />
      <MapTile TileID="284" AltIDMod="0" />
      <MapTile TileID="285" AltIDMod="0" />
    </MapTiles>
    <StaticTiles>
      <StaticTile TileID="12914" AltIDMod="0" />
      <StaticTile TileID="12915" AltIDMod="0" />
    </StaticTiles>
  </TransInfo>
  <TransInfo Description="Bottom Right" HashKey="474729474729292929">
    <MapTiles>
      <MapTile TileID="282" AltIDMod="0" />
      <MapTile TileID="283" AltIDMod="0" />
      <MapTile TileID="284" AltIDMod="0" />
      <MapTile TileID="285" AltIDMod="0" />
    </MapTiles>
    <StaticTiles>
      <StaticTile TileID="12927" AltIDMod="0" />
    </StaticTiles>
  </TransInfo>
  <TransInfo Description="Bottom Right" HashKey="474747474729292929">
    <MapTiles>
      <MapTile TileID="282" AltIDMod="0" />
      <MapTile TileID="283" AltIDMod="0" />
      <MapTile TileID="284" AltIDMod="0" />
      <MapTile TileID="285" AltIDMod="0" />
    </MapTiles>
    <StaticTiles>
      <StaticTile TileID="12927" AltIDMod="0" />
    </StaticTiles>
  </TransInfo>
  <TransInfo Description="Bottom Right" HashKey="474729474729472929">
    <MapTiles>
      <MapTile TileID="282" AltIDMod="0" />
      <MapTile TileID="283" AltIDMod="0" />
      <MapTile TileID="284" AltIDMod="0" />
      <MapTile TileID="285" AltIDMod="0" />
    </MapTiles>
    <StaticTiles>
      <StaticTile TileID="12927" AltIDMod="0" />
    </StaticTiles>
  </TransInfo>
  <TransInfo Description="Bottom Right" HashKey="474747474729472929">
    <MapTiles>
      <MapTile TileID="282" AltIDMod="0" />
      <MapTile TileID="283" AltIDMod="0" />
      <MapTile TileID="284" AltIDMod="0" />
      <MapTile TileID="285" AltIDMod="0" />
    </MapTiles>
    <StaticTiles>
      <StaticTile TileID="12927" AltIDMod="0" />
    </StaticTiles>
  </TransInfo>
  <TransInfo Description="Bottom Right" HashKey="474747474729472947">
    <MapTiles>
      <MapTile TileID="282" AltIDMod="0" />
      <MapTile TileID="283" AltIDMod="0" />
      <MapTile TileID="284" AltIDMod="0" />
      <MapTile TileID="285" AltIDMod="0" />
    </MapTiles>
    <StaticTiles>
      <StaticTile TileID="12927" AltIDMod="0" />
    </StaticTiles>
  </TransInfo>
  <TransInfo Description="Bottom Right" HashKey="474729474747472929">
    <MapTiles>
      <MapTile TileID="282" AltIDMod="0" />
      <MapTile TileID="283" AltIDMod="0" />
      <MapTile TileID="284" AltIDMod="0" />
      <MapTile TileID="285" AltIDMod="0" />
    </MapTiles>
    <StaticTiles>
      <StaticTile TileID="12927" AltIDMod="0" />
    </StaticTiles>
  </TransInfo>
  <TransInfo Description="Bottom Right" HashKey="474729474747292929">
    <MapTiles>
      <MapTile TileID="282" AltIDMod="0" />
      <MapTile TileID="283" AltIDMod="0" />
      <MapTile TileID="284" AltIDMod="0" />
      <MapTile TileID="285" AltIDMod="0" />
    </MapTiles>
    <StaticTiles>
      <StaticTile TileID="12927" AltIDMod="0" />
    </StaticTiles>
  </TransInfo>
  <TransInfo Description="Bottom Right" HashKey="474729474747292947">
    <MapTiles>
      <MapTile TileID="282" AltIDMod="0" />
      <MapTile TileID="283" AltIDMod="0" />
      <MapTile TileID="284" AltIDMod="0" />
      <MapTile TileID="285" AltIDMod="0" />
    </MapTiles>
    <StaticTiles>
      <StaticTile TileID="12927" AltIDMod="0" />
    </StaticTiles>
  </TransInfo>
  <TransInfo Description="Bottom Right" HashKey="474747474729294729">
    <MapTiles>
      <MapTile TileID="282" AltIDMod="0" />
      <MapTile TileID="283" AltIDMod="0" />
      <MapTile TileID="284" AltIDMod="0" />
      <MapTile TileID="285" AltIDMod="0" />
    </MapTiles>
    <StaticTiles>
      <StaticTile TileID="12927" AltIDMod="0" />
    </StaticTiles>
  </TransInfo>
  <TransInfo Description="Bottom Right" HashKey="474729474729294729">
    <MapTiles>
      <MapTile TileID="282" AltIDMod="0" />
      <MapTile TileID="283" AltIDMod="0" />
      <MapTile TileID="284" AltIDMod="0" />
      <MapTile TileID="285" AltIDMod="0" />
    </MapTiles>
    <StaticTiles>
      <StaticTile TileID="12927" AltIDMod="0" />
    </StaticTiles>
  </TransInfo>
  <TransInfo Description="Bottom Right" HashKey="474729474729292947">
    <MapTiles>
      <MapTile TileID="282" AltIDMod="0" />
      <MapTile TileID="283" AltIDMod="0" />
      <MapTile TileID="284" AltIDMod="0" />
      <MapTile TileID="285" AltIDMod="0" />
    </MapTiles>
    <StaticTiles>
      <StaticTile TileID="12927" AltIDMod="0" />
    </StaticTiles>
  </TransInfo>
  <TransInfo Description="Bottom Right" HashKey="474729474729294747">
    <MapTiles>
      <MapTile TileID="282" AltIDMod="0" />
      <MapTile TileID="283" AltIDMod="0" />
      <MapTile TileID="284" AltIDMod="0" />
      <MapTile TileID="285" AltIDMod="0" />
    </MapTiles>
    <StaticTiles>
      <StaticTile TileID="12927" AltIDMod="0" />
    </StaticTiles>
  </TransInfo>
  <TransInfo Description="Bottom Right" HashKey="474729474747472947">
    <MapTiles>
      <MapTile TileID="282" AltIDMod="0" />
      <MapTile TileID="283" AltIDMod="0" />
      <MapTile TileID="284" AltIDMod="0" />
      <MapTile TileID="285" AltIDMod="0" />
    </MapTiles>
    <StaticTiles>
      <StaticTile TileID="12927" AltIDMod="0" />
    </StaticTiles>
  </TransInfo>
  <TransInfo Description="Bottom Right" HashKey="474747474729294747">
    <MapTiles>
      <MapTile TileID="282" AltIDMod="0" />
      <MapTile TileID="283" AltIDMod="0" />
      <MapTile TileID="284" AltIDMod="0" />
      <MapTile TileID="285" AltIDMod="0" />
    </MapTiles>
    <StaticTiles>
      <StaticTile TileID="12927" AltIDMod="0" />
    </StaticTiles>
  </TransInfo>
  <TransInfo Description="Bottom Right" HashKey="474729474729472947">
    <MapTiles>
      <MapTile TileID="282" AltIDMod="0" />
      <MapTile TileID="283" AltIDMod="0" />
      <MapTile TileID="284" AltIDMod="0" />
      <MapTile TileID="285" AltIDMod="0" />
    </MapTiles>
    <StaticTiles>
      <StaticTile TileID="12927" AltIDMod="0" />
    </StaticTiles>
  </TransInfo>
  <TransInfo Description="Bottom Right" HashKey="474729474747294729">
    <MapTiles>
      <MapTile TileID="282" AltIDMod="0" />
      <MapTile TileID="283" AltIDMod="0" />
      <MapTile TileID="284" AltIDMod="0" />
      <MapTile TileID="285" AltIDMod="0" />
    </MapTiles>
    <StaticTiles>
      <StaticTile TileID="12927" AltIDMod="0" />
    </StaticTiles>
  </TransInfo>
  <TransInfo Description="Bottom Right" HashKey="474747474729292947">
    <MapTiles>
      <MapTile TileID="282" AltIDMod="0" />
      <MapTile TileID="283" AltIDMod="0" />
      <MapTile TileID="284" AltIDMod="0" />
      <MapTile TileID="285" AltIDMod="0" />
    </MapTiles>
    <StaticTiles>
      <StaticTile TileID="12927" AltIDMod="0" />
    </StaticTiles>
  </TransInfo>
  <TransInfo Description="Top Left" HashKey="292929294747294747">
    <MapTiles>
      <MapTile TileID="282" AltIDMod="0" />
      <MapTile TileID="283" AltIDMod="0" />
      <MapTile TileID="284" AltIDMod="0" />
      <MapTile TileID="285" AltIDMod="0" />
    </MapTiles>
    <StaticTiles>
      <StaticTile TileID="12925" AltIDMod="0" />
    </StaticTiles>
  </TransInfo>
  <TransInfo Description="Top Left" HashKey="292947294747294747">
    <MapTiles>
      <MapTile TileID="282" AltIDMod="0" />
      <MapTile TileID="283" AltIDMod="0" />
      <MapTile TileID="284" AltIDMod="0" />
      <MapTile TileID="285" AltIDMod="0" />
    </MapTiles>
    <StaticTiles>
      <StaticTile TileID="12925" AltIDMod="0" />
    </StaticTiles>
  </TransInfo>
  <TransInfo Description="Top Left" HashKey="292929294747474747">
    <MapTiles>
      <MapTile TileID="282" AltIDMod="0" />
      <MapTile TileID="283" AltIDMod="0" />
      <MapTile TileID="284" AltIDMod="0" />
      <MapTile TileID="285" AltIDMod="0" />
    </MapTiles>
    <StaticTiles>
      <StaticTile TileID="12925" AltIDMod="0" />
    </StaticTiles>
  </TransInfo>
  <TransInfo Description="Top Left" HashKey="292947294747474747">
    <MapTiles>
      <MapTile TileID="282" AltIDMod="0" />
      <MapTile TileID="283" AltIDMod="0" />
      <MapTile TileID="284" AltIDMod="0" />
      <MapTile TileID="285" AltIDMod="0" />
    </MapTiles>
    <StaticTiles>
      <StaticTile TileID="12925" AltIDMod="0" />
    </StaticTiles>
  </TransInfo>
  <TransInfo Description="Top Left" HashKey="294729294747474747">
    <MapTiles>
      <MapTile TileID="282" AltIDMod="0" />
      <MapTile TileID="283" AltIDMod="0" />
      <MapTile TileID="284" AltIDMod="0" />
      <MapTile TileID="285" AltIDMod="0" />
    </MapTiles>
    <StaticTiles>
      <StaticTile TileID="12925" AltIDMod="0" />
    </StaticTiles>
  </TransInfo>
  <TransInfo Description="Top Left" HashKey="292947474747294747">
    <MapTiles>
      <MapTile TileID="282" AltIDMod="0" />
      <MapTile TileID="283" AltIDMod="0" />
      <MapTile TileID="284" AltIDMod="0" />
      <MapTile TileID="285" AltIDMod="0" />
    </MapTiles>
    <StaticTiles>
      <StaticTile TileID="12925" AltIDMod="0" />
    </StaticTiles>
  </TransInfo>
  <TransInfo Description="Top Left" HashKey="472929474747294747">
    <MapTiles>
      <MapTile TileID="282" AltIDMod="0" />
      <MapTile TileID="283" AltIDMod="0" />
      <MapTile TileID="284" AltIDMod="0" />
      <MapTile TileID="285" AltIDMod="0" />
    </MapTiles>
    <StaticTiles>
      <StaticTile TileID="12925" AltIDMod="0" />
    </StaticTiles>
  </TransInfo>
  <TransInfo Description="Top Left" HashKey="294729474747294747">
    <MapTiles>
      <MapTile TileID="282" AltIDMod="0" />
      <MapTile TileID="283" AltIDMod="0" />
      <MapTile TileID="284" AltIDMod="0" />
      <MapTile TileID="285" AltIDMod="0" />
    </MapTiles>
    <StaticTiles>
      <StaticTile TileID="12925" AltIDMod="0" />
    </StaticTiles>
  </TransInfo>
  <TransInfo Description="Top Left" HashKey="292929474747294747">
    <MapTiles>
      <MapTile TileID="282" AltIDMod="0" />
      <MapTile TileID="283" AltIDMod="0" />
      <MapTile TileID="284" AltIDMod="0" />
      <MapTile TileID="285" AltIDMod="0" />
    </MapTiles>
    <StaticTiles>
      <StaticTile TileID="12925" AltIDMod="0" />
    </StaticTiles>
  </TransInfo>
  <TransInfo Description="Top Left" HashKey="472947294747474747">
    <MapTiles>
      <MapTile TileID="282" AltIDMod="0" />
      <MapTile TileID="283" AltIDMod="0" />
      <MapTile TileID="284" AltIDMod="0" />
      <MapTile TileID="285" AltIDMod="0" />
    </MapTiles>
    <StaticTiles>
      <StaticTile TileID="12925" AltIDMod="0" />
    </StaticTiles>
  </TransInfo>
  <TransInfo Description="Top Left" HashKey="294729294747294747">
    <MapTiles>
      <MapTile TileID="282" AltIDMod="0" />
      <MapTile TileID="283" AltIDMod="0" />
      <MapTile TileID="284" AltIDMod="0" />
      <MapTile TileID="285" AltIDMod="0" />
    </MapTiles>
    <StaticTiles>
      <StaticTile TileID="12925" AltIDMod="0" />
    </StaticTiles>
  </TransInfo>
  <TransInfo Description="Top Left" HashKey="474729294747294747">
    <MapTiles>
      <MapTile TileID="282" AltIDMod="0" />
      <MapTile TileID="283" AltIDMod="0" />
      <MapTile TileID="284" AltIDMod="0" />
      <MapTile TileID="285" AltIDMod="0" />
    </MapTiles>
    <StaticTiles>
      <StaticTile TileID="12925" AltIDMod="0" />
    </StaticTiles>
  </TransInfo>
  <TransInfo Description="Top Left" HashKey="472929294747294747">
    <MapTiles>
      <MapTile TileID="282" AltIDMod="0" />
      <MapTile TileID="283" AltIDMod="0" />
      <MapTile TileID="284" AltIDMod="0" />
      <MapTile TileID="285" AltIDMod="0" />
    </MapTiles>
    <StaticTiles>
      <StaticTile TileID="12925" AltIDMod="0" />
    </StaticTiles>
  </TransInfo>
  <TransInfo Description="Top Left" HashKey="474729294747474747">
    <MapTiles>
      <MapTile TileID="282" AltIDMod="0" />
      <MapTile TileID="283" AltIDMod="0" />
      <MapTile TileID="284" AltIDMod="0" />
      <MapTile TileID="285" AltIDMod="0" />
    </MapTiles>
    <StaticTiles>
      <StaticTile TileID="12925" AltIDMod="0" />
    </StaticTiles>
  </TransInfo>
  <TransInfo Description="Top Left" HashKey="472947294747294747">
    <MapTiles>
      <MapTile TileID="282" AltIDMod="0" />
      <MapTile TileID="283" AltIDMod="0" />
      <MapTile TileID="284" AltIDMod="0" />
      <MapTile TileID="285" AltIDMod="0" />
    </MapTiles>
    <StaticTiles>
      <StaticTile TileID="12925" AltIDMod="0" />
    </StaticTiles>
  </TransInfo>
  <TransInfo Description="Top Left" HashKey="472947474747294747">
    <MapTiles>
      <MapTile TileID="282" AltIDMod="0" />
      <MapTile TileID="283" AltIDMod="0" />
      <MapTile TileID="284" AltIDMod="0" />
      <MapTile TileID="285" AltIDMod="0" />
    </MapTiles>
    <StaticTiles>
      <StaticTile TileID="12925" AltIDMod="0" />
    </StaticTiles>
  </TransInfo>
  <TransInfo Description="Top Left" HashKey="472929294747474747">
    <MapTiles>
      <MapTile TileID="282" AltIDMod="0" />
      <MapTile TileID="283" AltIDMod="0" />
      <MapTile TileID="284" AltIDMod="0" />
      <MapTile TileID="285" AltIDMod="0" />
    </MapTiles>
    <StaticTiles>
      <StaticTile TileID="12925" AltIDMod="0" />
    </StaticTiles>
  </TransInfo>
  <TransInfo Description="Bottom Left" HashKey="294747294747292929">
    <MapTiles>
      <MapTile TileID="282" AltIDMod="0" />
      <MapTile TileID="283" AltIDMod="0" />
      <MapTile TileID="284" AltIDMod="0" />
      <MapTile TileID="285" AltIDMod="0" />
    </MapTiles>
    <StaticTiles>
      <StaticTile TileID="12924" AltIDMod="0" />
    </StaticTiles>
  </TransInfo>
  <TransInfo Description="Bottom Left" HashKey="474747294747292929">
    <MapTiles>
      <MapTile TileID="282" AltIDMod="0" />
      <MapTile TileID="283" AltIDMod="0" />
      <MapTile TileID="284" AltIDMod="0" />
      <MapTile TileID="285" AltIDMod="0" />
    </MapTiles>
    <StaticTiles>
      <StaticTile TileID="12924" AltIDMod="0" />
    </StaticTiles>
  </TransInfo>
  <TransInfo Description="Bottom Left" HashKey="294747294747292947">
    <MapTiles>
      <MapTile TileID="282" AltIDMod="0" />
      <MapTile TileID="283" AltIDMod="0" />
      <MapTile TileID="284" AltIDMod="0" />
      <MapTile TileID="285" AltIDMod="0" />
    </MapTiles>
    <StaticTiles>
      <StaticTile TileID="12924" AltIDMod="0" />
    </StaticTiles>
  </TransInfo>
  <TransInfo Description="Bottom Left" HashKey="474747294747292947">
    <MapTiles>
      <MapTile TileID="282" AltIDMod="0" />
      <MapTile TileID="283" AltIDMod="0" />
      <MapTile TileID="284" AltIDMod="0" />
      <MapTile TileID="285" AltIDMod="0" />
    </MapTiles>
    <StaticTiles>
      <StaticTile TileID="12924" AltIDMod="0" />
    </StaticTiles>
  </TransInfo>
  <TransInfo Description="Bottom Left" HashKey="474747294747472947">
    <MapTiles>
      <MapTile TileID="282" AltIDMod="0" />
      <MapTile TileID="283" AltIDMod="0" />
      <MapTile TileID="284" AltIDMod="0" />
      <MapTile TileID="285" AltIDMod="0" />
    </MapTiles>
    <StaticTiles>
      <StaticTile TileID="12924" AltIDMod="0" />
    </StaticTiles>
  </TransInfo>
  <TransInfo Description="Bottom Left" HashKey="294747294747474729">
    <MapTiles>
      <MapTile TileID="282" AltIDMod="0" />
      <MapTile TileID="283" AltIDMod="0" />
      <MapTile TileID="284" AltIDMod="0" />
      <MapTile TileID="285" AltIDMod="0" />
    </MapTiles>
    <StaticTiles>
      <StaticTile TileID="12924" AltIDMod="0" />
    </StaticTiles>
  </TransInfo>
  <TransInfo Description="Bottom Left" HashKey="294747474747292929">
    <MapTiles>
      <MapTile TileID="282" AltIDMod="0" />
      <MapTile TileID="283" AltIDMod="0" />
      <MapTile TileID="284" AltIDMod="0" />
      <MapTile TileID="285" AltIDMod="0" />
    </MapTiles>
    <StaticTiles>
      <StaticTile TileID="12924" AltIDMod="0" />
    </StaticTiles>
  </TransInfo>
  <TransInfo Description="Bottom Left" HashKey="294747474747292947">
    <MapTiles>
      <MapTile TileID="282" AltIDMod="0" />
      <MapTile TileID="283" AltIDMod="0" />
      <MapTile TileID="284" AltIDMod="0" />
      <MapTile TileID="285" AltIDMod="0" />
    </MapTiles>
    <StaticTiles>
      <StaticTile TileID="12924" AltIDMod="0" />
    </StaticTiles>
  </TransInfo>
  <TransInfo Description="Bottom Left" HashKey="294747474747472947">
    <MapTiles>
      <MapTile TileID="282" AltIDMod="0" />
      <MapTile TileID="283" AltIDMod="0" />
      <MapTile TileID="284" AltIDMod="0" />
      <MapTile TileID="285" AltIDMod="0" />
    </MapTiles>
    <StaticTiles>
      <StaticTile TileID="12924" AltIDMod="0" />
    </StaticTiles>
  </TransInfo>
  <TransInfo Description="Bottom Left" HashKey="474747294747294729">
    <MapTiles>
      <MapTile TileID="282" AltIDMod="0" />
      <MapTile TileID="283" AltIDMod="0" />
      <MapTile TileID="284" AltIDMod="0" />
      <MapTile TileID="285" AltIDMod="0" />
    </MapTiles>
    <StaticTiles>
      <StaticTile TileID="12924" AltIDMod="0" />
    </StaticTiles>
  </TransInfo>
  <TransInfo Description="Bottom Left" HashKey="294747294747294729">
    <MapTiles>
      <MapTile TileID="282" AltIDMod="0" />
      <MapTile TileID="283" AltIDMod="0" />
      <MapTile TileID="284" AltIDMod="0" />
      <MapTile TileID="285" AltIDMod="0" />
    </MapTiles>
    <StaticTiles>
      <StaticTile TileID="12924" AltIDMod="0" />
    </StaticTiles>
  </TransInfo>
  <TransInfo Description="Bottom Left" HashKey="294747474747472929">
    <MapTiles>
      <MapTile TileID="282" AltIDMod="0" />
      <MapTile TileID="283" AltIDMod="0" />
      <MapTile TileID="284" AltIDMod="0" />
      <MapTile TileID="285" AltIDMod="0" />
    </MapTiles>
    <StaticTiles>
      <StaticTile TileID="12924" AltIDMod="0" />
    </StaticTiles>
  </TransInfo>
  <TransInfo Description="Bottom Left" HashKey="294747294747472929">
    <MapTiles>
      <MapTile TileID="282" AltIDMod="0" />
      <MapTile TileID="283" AltIDMod="0" />
      <MapTile TileID="284" AltIDMod="0" />
      <MapTile TileID="285" AltIDMod="0" />
    </MapTiles>
    <StaticTiles>
      <StaticTile TileID="12924" AltIDMod="0" />
    </StaticTiles>
  </TransInfo>
  <TransInfo Description="Bottom Left" HashKey="474747294747472929">
    <MapTiles>
      <MapTile TileID="282" AltIDMod="0" />
      <MapTile TileID="283" AltIDMod="0" />
      <MapTile TileID="284" AltIDMod="0" />
      <MapTile TileID="285" AltIDMod="0" />
    </MapTiles>
    <StaticTiles>
      <StaticTile TileID="12924" AltIDMod="0" />
    </StaticTiles>
  </TransInfo>
  <TransInfo Description="Bottom Left" HashKey="474747294747474729">
    <MapTiles>
      <MapTile TileID="282" AltIDMod="0" />
      <MapTile TileID="283" AltIDMod="0" />
      <MapTile TileID="284" AltIDMod="0" />
      <MapTile TileID="285" AltIDMod="0" />
    </MapTiles>
    <StaticTiles>
      <StaticTile TileID="12924" AltIDMod="0" />
    </StaticTiles>
  </TransInfo>
  <TransInfo Description="Bottom Left" HashKey="294747474747294729">
    <MapTiles>
      <MapTile TileID="282" AltIDMod="0" />
      <MapTile TileID="283" AltIDMod="0" />
      <MapTile TileID="284" AltIDMod="0" />
      <MapTile TileID="285" AltIDMod="0" />
    </MapTiles>
    <StaticTiles>
      <StaticTile TileID="12924" AltIDMod="0" />
    </StaticTiles>
  </TransInfo>
  <TransInfo Description="Bottom Left" HashKey="294747294747472947">
    <MapTiles>
      <MapTile TileID="282" AltIDMod="0" />
      <MapTile TileID="283" AltIDMod="0" />
      <MapTile TileID="284" AltIDMod="0" />
      <MapTile TileID="285" AltIDMod="0" />
    </MapTiles>
    <StaticTiles>
      <StaticTile TileID="12924" AltIDMod="0" />
    </StaticTiles>
  </TransInfo>
  <TransInfo Description="Top Right" HashKey="292929474729474729">
    <MapTiles>
      <MapTile TileID="282" AltIDMod="0" />
      <MapTile TileID="283" AltIDMod="0" />
      <MapTile TileID="284" AltIDMod="0" />
      <MapTile TileID="285" AltIDMod="0" />
    </MapTiles>
    <StaticTiles>
      <StaticTile TileID="12926" AltIDMod="0" />
    </StaticTiles>
  </TransInfo>
  <TransInfo Description="Top Right" HashKey="292929474729474747">
    <MapTiles>
      <MapTile TileID="282" AltIDMod="0" />
      <MapTile TileID="283" AltIDMod="0" />
      <MapTile TileID="284" AltIDMod="0" />
      <MapTile TileID="285" AltIDMod="0" />
    </MapTiles>
    <StaticTiles>
      <StaticTile TileID="12926" AltIDMod="0" />
    </StaticTiles>
  </TransInfo>
  <TransInfo Description="Top Right" HashKey="472929474729474729">
    <MapTiles>
      <MapTile TileID="282" AltIDMod="0" />
      <MapTile TileID="283" AltIDMod="0" />
      <MapTile TileID="284" AltIDMod="0" />
      <MapTile TileID="285" AltIDMod="0" />
    </MapTiles>
    <StaticTiles>
      <StaticTile TileID="12926" AltIDMod="0" />
    </StaticTiles>
  </TransInfo>
  <TransInfo Description="Top Right" HashKey="472929474729474747">
    <MapTiles>
      <MapTile TileID="282" AltIDMod="0" />
      <MapTile TileID="283" AltIDMod="0" />
      <MapTile TileID="284" AltIDMod="0" />
      <MapTile TileID="285" AltIDMod="0" />
    </MapTiles>
    <StaticTiles>
      <StaticTile TileID="12926" AltIDMod="0" />
    </StaticTiles>
  </TransInfo>
  <TransInfo Description="Top Right" HashKey="294747474729474729">
    <MapTiles>
      <MapTile TileID="282" AltIDMod="0" />
      <MapTile TileID="283" AltIDMod="0" />
      <MapTile TileID="284" AltIDMod="0" />
      <MapTile TileID="285" AltIDMod="0" />
    </MapTiles>
    <StaticTiles>
      <StaticTile TileID="12926" AltIDMod="0" />
    </StaticTiles>
  </TransInfo>
  <TransInfo Description="Top Right" HashKey="294729474729474747">
    <MapTiles>
      <MapTile TileID="282" AltIDMod="0" />
      <MapTile TileID="283" AltIDMod="0" />
      <MapTile TileID="284" AltIDMod="0" />
      <MapTile TileID="285" AltIDMod="0" />
    </MapTiles>
    <StaticTiles>
      <StaticTile TileID="12926" AltIDMod="0" />
    </StaticTiles>
  </TransInfo>
  <TransInfo Description="Top Right" HashKey="294729474729474729">
    <MapTiles>
      <MapTile TileID="282" AltIDMod="0" />
      <MapTile TileID="283" AltIDMod="0" />
      <MapTile TileID="284" AltIDMod="0" />
      <MapTile TileID="285" AltIDMod="0" />
    </MapTiles>
    <StaticTiles>
      <StaticTile TileID="12926" AltIDMod="0" />
    </StaticTiles>
  </TransInfo>
  <TransInfo Description="Top Right" HashKey="292947474747474729">
    <MapTiles>
      <MapTile TileID="282" AltIDMod="0" />
      <MapTile TileID="283" AltIDMod="0" />
      <MapTile TileID="284" AltIDMod="0" />
      <MapTile TileID="285" AltIDMod="0" />
    </MapTiles>
    <StaticTiles>
      <StaticTile TileID="12926" AltIDMod="0" />
    </StaticTiles>
  </TransInfo>
  <TransInfo Description="Top Right" HashKey="472947474747474729">
    <MapTiles>
      <MapTile TileID="282" AltIDMod="0" />
      <MapTile TileID="283" AltIDMod="0" />
      <MapTile TileID="284" AltIDMod="0" />
      <MapTile TileID="285" AltIDMod="0" />
    </MapTiles>
    <StaticTiles>
      <StaticTile TileID="12926" AltIDMod="0" />
    </StaticTiles>
  </TransInfo>
  <TransInfo Description="Top Right" HashKey="292929474747474729">
    <MapTiles>
      <MapTile TileID="282" AltIDMod="0" />
      <MapTile TileID="283" AltIDMod="0" />
      <MapTile TileID="284" AltIDMod="0" />
      <MapTile TileID="285" AltIDMod="0" />
    </MapTiles>
    <StaticTiles>
      <StaticTile TileID="12926" AltIDMod="0" />
    </StaticTiles>
  </TransInfo>
  <TransInfo Description="Top Right" HashKey="292947474729474747">
    <MapTiles>
      <MapTile TileID="282" AltIDMod="0" />
      <MapTile TileID="283" AltIDMod="0" />
      <MapTile TileID="284" AltIDMod="0" />
      <MapTile TileID="285" AltIDMod="0" />
    </MapTiles>
    <StaticTiles>
      <StaticTile TileID="12926" AltIDMod="0" />
    </StaticTiles>
  </TransInfo>
  <TransInfo Description="Top Right" HashKey="472929474747474729">
    <MapTiles>
      <MapTile TileID="282" AltIDMod="0" />
      <MapTile TileID="283" AltIDMod="0" />
      <MapTile TileID="284" AltIDMod="0" />
      <MapTile TileID="285" AltIDMod="0" />
    </MapTiles>
    <StaticTiles>
      <StaticTile TileID="12926" AltIDMod="0" />
    </StaticTiles>
  </TransInfo>
  <TransInfo Description="Top Right" HashKey="472947474729474747">
    <MapTiles>
      <MapTile TileID="282" AltIDMod="0" />
      <MapTile TileID="283" AltIDMod="0" />
      <MapTile TileID="284" AltIDMod="0" />
      <MapTile TileID="285" AltIDMod="0" />
    </MapTiles>
    <StaticTiles>
      <StaticTile TileID="12926" AltIDMod="0" />
    </StaticTiles>
  </TransInfo>
  <TransInfo Description="Top Right" HashKey="294747474729474747">
    <MapTiles>
      <MapTile TileID="282" AltIDMod="0" />
      <MapTile TileID="283" AltIDMod="0" />
      <MapTile TileID="284" AltIDMod="0" />
      <MapTile TileID="285" AltIDMod="0" />
    </MapTiles>
    <StaticTiles>
      <StaticTile TileID="12926" AltIDMod="0" />
    </StaticTiles>
  </TransInfo>
  <TransInfo Description="Top Right" HashKey="294729474747474729">
    <MapTiles>
      <MapTile TileID="282" AltIDMod="0" />
      <MapTile TileID="283" AltIDMod="0" />
      <MapTile TileID="284" AltIDMod="0" />
      <MapTile TileID="285" AltIDMod="0" />
    </MapTiles>
    <StaticTiles>
      <StaticTile TileID="12926" AltIDMod="0" />
    </StaticTiles>
  </TransInfo>
  <TransInfo Description="Top Right" HashKey="472947474729474729">
    <MapTiles>
      <MapTile TileID="282" AltIDMod="0" />
      <MapTile TileID="283" AltIDMod="0" />
      <MapTile TileID="284" AltIDMod="0" />
      <MapTile TileID="285" AltIDMod="0" />
    </MapTiles>
    <StaticTiles>
      <StaticTile TileID="12926" AltIDMod="0" />
    </StaticTiles>
  </TransInfo>
  <TransInfo Description="Top Right" HashKey="292947474729474729">
    <MapTiles>
      <MapTile TileID="282" AltIDMod="0" />
      <MapTile TileID="283" AltIDMod="0" />
      <MapTile TileID="284" AltIDMod="0" />
      <MapTile TileID="285" AltIDMod="0" />
    </MapTiles>
    <StaticTiles>
      <StaticTile TileID="12926" AltIDMod="0" />
    </StaticTiles>
  </TransInfo>
  <TransInfo Description="Outer Top Left" HashKey="294747474747474747">
    <MapTiles>
      <MapTile TileID="282" AltIDMod="0" />
      <MapTile TileID="283" AltIDMod="0" />
      <MapTile TileID="284" AltIDMod="0" />
      <MapTile TileID="285" AltIDMod="0" />
    </MapTiles>
    <StaticTiles>
      <StaticTile TileID="12922" AltIDMod="0" />
      <StaticTile TileID="12932" AltIDMod="0" />
    </StaticTiles>
  </TransInfo>
  <TransInfo Description="Outer Bottom Right" HashKey="474747474747474729">
    <MapTiles>
      <MapTile TileID="282" AltIDMod="0" />
      <MapTile TileID="283" AltIDMod="0" />
      <MapTile TileID="284" AltIDMod="0" />
      <MapTile TileID="285" AltIDMod="0" />
    </MapTiles>
    <StaticTiles>
      <StaticTile TileID="12921" AltIDMod="0" />
      <StaticTile TileID="12930" AltIDMod="0" />
    </StaticTiles>
  </TransInfo>
  <TransInfo Description="Outer Top Right" HashKey="474729474747474747">
    <MapTiles>
      <MapTile TileID="282" AltIDMod="0" />
      <MapTile TileID="283" AltIDMod="0" />
      <MapTile TileID="284" AltIDMod="0" />
      <MapTile TileID="285" AltIDMod="0" />
    </MapTiles>
    <StaticTiles>
      <StaticTile TileID="12923" AltIDMod="0" />
      <StaticTile TileID="12931" AltIDMod="0" />
    </StaticTiles>
  </TransInfo>
  <TransInfo Description="Outer Bottom Left" HashKey="474747474747294747">
    <MapTiles>
      <MapTile TileID="282" AltIDMod="0" />
      <MapTile TileID="283" AltIDMod="0" />
      <MapTile TileID="284" AltIDMod="0" />
      <MapTile TileID="285" AltIDMod="0" />
    </MapTiles>
    <StaticTiles>
      <StaticTile TileID="12920" AltIDMod="0" />
    </StaticTiles>
  </TransInfo>
  <TransInfo Description="Autocorrect" HashKey="474747294729474747">
    <MapTiles>
      <MapTile TileID="15849" AltIDMod="0" />
      <MapTile TileID="15850" AltIDMod="0" />
      <MapTile TileID="15851" AltIDMod="0" />
      <MapTile TileID="15852" AltIDMod="0" />
    </MapTiles>
    <StaticTiles>
    </StaticTiles>
  </TransInfo>
  <TransInfo Description="Autocorrect" HashKey="474747294729294747">
    <MapTiles>
      <MapTile TileID="15849" AltIDMod="0" />
      <MapTile TileID="15850" AltIDMod="0" />
      <MapTile TileID="15851" AltIDMod="0" />
      <MapTile TileID="15852" AltIDMod="0" />
    </MapTiles>
    <StaticTiles>
    </StaticTiles>
  </TransInfo>
  <TransInfo Description="Autocorrect" HashKey="474747294729472947">
    <MapTiles>
      <MapTile TileID="15849" AltIDMod="0" />
      <MapTile TileID="15850" AltIDMod="0" />
      <MapTile TileID="15851" AltIDMod="0" />
      <MapTile TileID="15852" AltIDMod="0" />
    </MapTiles>
    <StaticTiles>
    </StaticTiles>
  </TransInfo>
  <TransInfo Description="Autocorrect" HashKey="474747294729292947">
    <MapTiles>
      <MapTile TileID="15849" AltIDMod="0" />
      <MapTile TileID="15850" AltIDMod="0" />
      <MapTile TileID="15851" AltIDMod="0" />
      <MapTile TileID="15852" AltIDMod="0" />
    </MapTiles>
    <StaticTiles>
    </StaticTiles>
  </TransInfo>
  <TransInfo Description="Autocorrect" HashKey="474747294729474729">
    <MapTiles>
      <MapTile TileID="15849" AltIDMod="0" />
      <MapTile TileID="15850" AltIDMod="0" />
      <MapTile TileID="15851" AltIDMod="0" />
      <MapTile TileID="15852" AltIDMod="0" />
    </MapTiles>
    <StaticTiles>
    </StaticTiles>
  </TransInfo>
  <TransInfo Description="Autocorrect" HashKey="474747294729294729">
    <MapTiles>
      <MapTile TileID="15849" AltIDMod="0" />
      <MapTile TileID="15850" AltIDMod="0" />
      <MapTile TileID="15851" AltIDMod="0" />
      <MapTile TileID="15852" AltIDMod="0" />
    </MapTiles>
    <StaticTiles>
    </StaticTiles>
  </TransInfo>
  <TransInfo Description="Autocorrect" HashKey="474747294729472929">
    <MapTiles>
      <MapTile TileID="15849" AltIDMod="0" />
      <MapTile TileID="15850" AltIDMod="0" />
      <MapTile TileID="15851" AltIDMod="0" />
      <MapTile TileID="15852" AltIDMod="0" />
    </MapTiles>
    <StaticTiles>
    </StaticTiles>
  </TransInfo>
  <TransInfo Description="Autocorrect" HashKey="474747294729292929">
    <MapTiles>
      <MapTile TileID="15849" AltIDMod="0" />
      <MapTile TileID="15850" AltIDMod="0" />
      <MapTile TileID="15851" AltIDMod="0" />
      <MapTile TileID="15852" AltIDMod="0" />
    </MapTiles>
    <StaticTiles>
    </StaticTiles>
  </TransInfo>
  <TransInfo Description="Autocorrect" HashKey="474729294747472947">
    <MapTiles>
      <MapTile TileID="15849" AltIDMod="0" />
      <MapTile TileID="15850" AltIDMod="0" />
      <MapTile TileID="15851" AltIDMod="0" />
      <MapTile TileID="15852" AltIDMod="0" />
    </MapTiles>
    <StaticTiles>
    </StaticTiles>
  </TransInfo>
  <TransInfo Description="Autocorrect" HashKey="474729294747292947">
    <MapTiles>
      <MapTile TileID="15849" AltIDMod="0" />
      <MapTile TileID="15850" AltIDMod="0" />
      <MapTile TileID="15851" AltIDMod="0" />
      <MapTile TileID="15852" AltIDMod="0" />
    </MapTiles>
    <StaticTiles>
    </StaticTiles>
  </TransInfo>
  <TransInfo Description="Autocorrect" HashKey="474729294747474729">
    <MapTiles>
      <MapTile TileID="15849" AltIDMod="0" />
      <MapTile TileID="15850" AltIDMod="0" />
      <MapTile TileID="15851" AltIDMod="0" />
      <MapTile TileID="15852" AltIDMod="0" />
    </MapTiles>
    <StaticTiles>
    </StaticTiles>
  </TransInfo>
  <TransInfo Description="Autocorrect" HashKey="474729294747294729">
    <MapTiles>
      <MapTile TileID="15849" AltIDMod="0" />
      <MapTile TileID="15850" AltIDMod="0" />
      <MapTile TileID="15851" AltIDMod="0" />
      <MapTile TileID="15852" AltIDMod="0" />
    </MapTiles>
    <StaticTiles>
    </StaticTiles>
  </TransInfo>
  <TransInfo Description="Autocorrect" HashKey="474729294747472929">
    <MapTiles>
      <MapTile TileID="15849" AltIDMod="0" />
      <MapTile TileID="15850" AltIDMod="0" />
      <MapTile TileID="15851" AltIDMod="0" />
      <MapTile TileID="15852" AltIDMod="0" />
    </MapTiles>
    <StaticTiles>
    </StaticTiles>
  </TransInfo>
  <TransInfo Description="Autocorrect" HashKey="474729294747292929">
    <MapTiles>
      <MapTile TileID="15849" AltIDMod="0" />
      <MapTile TileID="15850" AltIDMod="0" />
      <MapTile TileID="15851" AltIDMod="0" />
      <MapTile TileID="15852" AltIDMod="0" />
    </MapTiles>
    <StaticTiles>
    </StaticTiles>
  </TransInfo>
  <TransInfo Description="Autocorrect" HashKey="474729294729474747">
    <MapTiles>
      <MapTile TileID="15849" AltIDMod="0" />
      <MapTile TileID="15850" AltIDMod="0" />
      <MapTile TileID="15851" AltIDMod="0" />
      <MapTile TileID="15852" AltIDMod="0" />
    </MapTiles>
    <StaticTiles>
    </StaticTiles>
  </TransInfo>
  <TransInfo Description="Autocorrect" HashKey="474729294729294747">
    <MapTiles>
      <MapTile TileID="15849" AltIDMod="0" />
      <MapTile TileID="15850" AltIDMod="0" />
      <MapTile TileID="15851" AltIDMod="0" />
      <MapTile TileID="15852" AltIDMod="0" />
    </MapTiles>
    <StaticTiles>
    </StaticTiles>
  </TransInfo>
  <TransInfo Description="Autocorrect" HashKey="474729294729472947">
    <MapTiles>
      <MapTile TileID="15849" AltIDMod="0" />
      <MapTile TileID="15850" AltIDMod="0" />
      <MapTile TileID="15851" AltIDMod="0" />
      <MapTile TileID="15852" AltIDMod="0" />
    </MapTiles>
    <StaticTiles>
    </StaticTiles>
  </TransInfo>
  <TransInfo Description="Autocorrect" HashKey="474729294729292947">
    <MapTiles>
      <MapTile TileID="15849" AltIDMod="0" />
      <MapTile TileID="15850" AltIDMod="0" />
      <MapTile TileID="15851" AltIDMod="0" />
      <MapTile TileID="15852" AltIDMod="0" />
    </MapTiles>
    <StaticTiles>
    </StaticTiles>
  </TransInfo>
  <TransInfo Description="Autocorrect" HashKey="474729294729474729">
    <MapTiles>
      <MapTile TileID="15849" AltIDMod="0" />
      <MapTile TileID="15850" AltIDMod="0" />
      <MapTile TileID="15851" AltIDMod="0" />
      <MapTile TileID="15852" AltIDMod="0" />
    </MapTiles>
    <StaticTiles>
    </StaticTiles>
  </TransInfo>
  <TransInfo Description="Autocorrect" HashKey="474729294729294729">
    <MapTiles>
      <MapTile TileID="15849" AltIDMod="0" />
      <MapTile TileID="15850" AltIDMod="0" />
      <MapTile TileID="15851" AltIDMod="0" />
      <MapTile TileID="15852" AltIDMod="0" />
    </MapTiles>
    <StaticTiles>
    </StaticTiles>
  </TransInfo>
  <TransInfo Description="Autocorrect" HashKey="474729294729472929">
    <MapTiles>
      <MapTile TileID="15849" AltIDMod="0" />
      <MapTile TileID="15850" AltIDMod="0" />
      <MapTile TileID="15851" AltIDMod="0" />
      <MapTile TileID="15852" AltIDMod="0" />
    </MapTiles>
    <StaticTiles>
    </StaticTiles>
  </TransInfo>
  <TransInfo Description="Autocorrect" HashKey="474729294729292929">
    <MapTiles>
      <MapTile TileID="15849" AltIDMod="0" />
      <MapTile TileID="15850" AltIDMod="0" />
      <MapTile TileID="15851" AltIDMod="0" />
      <MapTile TileID="15852" AltIDMod="0" />
    </MapTiles>
    <StaticTiles>
    </StaticTiles>
  </TransInfo>
  <TransInfo Description="Autocorrect" HashKey="472947474747472947">
    <MapTiles>
      <MapTile TileID="15849" AltIDMod="0" />
      <MapTile TileID="15850" AltIDMod="0" />
      <MapTile TileID="15851" AltIDMod="0" />
      <MapTile TileID="15852" AltIDMod="0" />
    </MapTiles>
    <StaticTiles>
    </StaticTiles>
  </TransInfo>
  <TransInfo Description="Autocorrect" HashKey="472947294747472947">
    <MapTiles>
      <MapTile TileID="15849" AltIDMod="0" />
      <MapTile TileID="15850" AltIDMod="0" />
      <MapTile TileID="15851" AltIDMod="0" />
      <MapTile TileID="15852" AltIDMod="0" />
    </MapTiles>
    <StaticTiles>
    </StaticTiles>
  </TransInfo>
  <TransInfo Description="Autocorrect" HashKey="472947474747292947">
    <MapTiles>
      <MapTile TileID="15849" AltIDMod="0" />
      <MapTile TileID="15850" AltIDMod="0" />
      <MapTile TileID="15851" AltIDMod="0" />
      <MapTile TileID="15852" AltIDMod="0" />
    </MapTiles>
    <StaticTiles>
    </StaticTiles>
  </TransInfo>
  <TransInfo Description="Autocorrect" HashKey="472947294747292947">
    <MapTiles>
      <MapTile TileID="15849" AltIDMod="0" />
      <MapTile TileID="15850" AltIDMod="0" />
      <MapTile TileID="15851" AltIDMod="0" />
      <MapTile TileID="15852" AltIDMod="0" />
    </MapTiles>
    <StaticTiles>
    </StaticTiles>
  </TransInfo>
  <TransInfo Description="Autocorrect" HashKey="472947294747474729">
    <MapTiles>
      <MapTile TileID="15849" AltIDMod="0" />
      <MapTile TileID="15850" AltIDMod="0" />
      <MapTile TileID="15851" AltIDMod="0" />
      <MapTile TileID="15852" AltIDMod="0" />
    </MapTiles>
    <StaticTiles>
    </StaticTiles>
  </TransInfo>
  <TransInfo Description="Autocorrect" HashKey="472947474747294729">
    <MapTiles>
      <MapTile TileID="15849" AltIDMod="0" />
      <MapTile TileID="15850" AltIDMod="0" />
      <MapTile TileID="15851" AltIDMod="0" />
      <MapTile TileID="15852" AltIDMod="0" />
    </MapTiles>
    <StaticTiles>
    </StaticTiles>
  </TransInfo>
  <TransInfo Description="Autocorrect" HashKey="472947294747294729">
    <MapTiles>
      <MapTile TileID="15849" AltIDMod="0" />
      <MapTile TileID="15850" AltIDMod="0" />
      <MapTile TileID="15851" AltIDMod="0" />
      <MapTile TileID="15852" AltIDMod="0" />
    </MapTiles>
    <StaticTiles>
    </StaticTiles>
  </TransInfo>
  <TransInfo Description="Autocorrect" HashKey="472947474747472929">
    <MapTiles>
      <MapTile TileID="15849" AltIDMod="0" />
      <MapTile TileID="15850" AltIDMod="0" />
      <MapTile TileID="15851" AltIDMod="0" />
      <MapTile TileID="15852" AltIDMod="0" />
    </MapTiles>
    <StaticTiles>
    </StaticTiles>
  </TransInfo>
  <TransInfo Description="Autocorrect" HashKey="472947294747472929">
    <MapTiles>
      <MapTile TileID="15849" AltIDMod="0" />
      <MapTile TileID="15850" AltIDMod="0" />
      <MapTile TileID="15851" AltIDMod="0" />
      <MapTile TileID="15852" AltIDMod="0" />
    </MapTiles>
    <StaticTiles>
    </StaticTiles>
  </TransInfo>
  <TransInfo Description="Autocorrect" HashKey="472947474747292929">
    <MapTiles>
      <MapTile TileID="15849" AltIDMod="0" />
      <MapTile TileID="15850" AltIDMod="0" />
      <MapTile TileID="15851" AltIDMod="0" />
      <MapTile TileID="15852" AltIDMod="0" />
    </MapTiles>
    <StaticTiles>
    </StaticTiles>
  </TransInfo>
  <TransInfo Description="Autocorrect" HashKey="472947294747292929">
    <MapTiles>
      <MapTile TileID="15849" AltIDMod="0" />
      <MapTile TileID="15850" AltIDMod="0" />
      <MapTile TileID="15851" AltIDMod="0" />
      <MapTile TileID="15852" AltIDMod="0" />
    </MapTiles>
    <StaticTiles>
    </StaticTiles>
  </TransInfo>
  <TransInfo Description="Autocorrect" HashKey="472947294729474747">
    <MapTiles>
      <MapTile TileID="15849" AltIDMod="0" />
      <MapTile TileID="15850" AltIDMod="0" />
      <MapTile TileID="15851" AltIDMod="0" />
      <MapTile TileID="15852" AltIDMod="0" />
    </MapTiles>
    <StaticTiles>
    </StaticTiles>
  </TransInfo>
  <TransInfo Description="Autocorrect" HashKey="472947474729294747">
    <MapTiles>
      <MapTile TileID="15849" AltIDMod="0" />
      <MapTile TileID="15850" AltIDMod="0" />
      <MapTile TileID="15851" AltIDMod="0" />
      <MapTile TileID="15852" AltIDMod="0" />
    </MapTiles>
    <StaticTiles>
    </StaticTiles>
  </TransInfo>
  <TransInfo Description="Autocorrect" HashKey="472947294729294747">
    <MapTiles>
      <MapTile TileID="15849" AltIDMod="0" />
      <MapTile TileID="15850" AltIDMod="0" />
      <MapTile TileID="15851" AltIDMod="0" />
      <MapTile TileID="15852" AltIDMod="0" />
    </MapTiles>
    <StaticTiles>
    </StaticTiles>
  </TransInfo>
  <TransInfo Description="Autocorrect" HashKey="472947474729472947">
    <MapTiles>
      <MapTile TileID="15849" AltIDMod="0" />
      <MapTile TileID="15850" AltIDMod="0" />
      <MapTile TileID="15851" AltIDMod="0" />
      <MapTile TileID="15852" AltIDMod="0" />
    </MapTiles>
    <StaticTiles>
    </StaticTiles>
  </TransInfo>
  <TransInfo Description="Autocorrect" HashKey="472947294729472947">
    <MapTiles>
      <MapTile TileID="15849" AltIDMod="0" />
      <MapTile TileID="15850" AltIDMod="0" />
      <MapTile TileID="15851" AltIDMod="0" />
      <MapTile TileID="15852" AltIDMod="0" />
    </MapTiles>
    <StaticTiles>
    </StaticTiles>
  </TransInfo>
  <TransInfo Description="Autocorrect" HashKey="472947474729292947">
    <MapTiles>
      <MapTile TileID="15849" AltIDMod="0" />
      <MapTile TileID="15850" AltIDMod="0" />
      <MapTile TileID="15851" AltIDMod="0" />
      <MapTile TileID="15852" AltIDMod="0" />
    </MapTiles>
    <StaticTiles>
    </StaticTiles>
  </TransInfo>
  <TransInfo Description="Autocorrect" HashKey="472947294729292947">
    <MapTiles>
      <MapTile TileID="15849" AltIDMod="0" />
      <MapTile TileID="15850" AltIDMod="0" />
      <MapTile TileID="15851" AltIDMod="0" />
      <MapTile TileID="15852" AltIDMod="0" />
    </MapTiles>
    <StaticTiles>
    </StaticTiles>
  </TransInfo>
  <TransInfo Description="Autocorrect" HashKey="472947294729474729">
    <MapTiles>
      <MapTile TileID="15849" AltIDMod="0" />
      <MapTile TileID="15850" AltIDMod="0" />
      <MapTile TileID="15851" AltIDMod="0" />
      <MapTile TileID="15852" AltIDMod="0" />
    </MapTiles>
    <StaticTiles>
    </StaticTiles>
  </TransInfo>
  <TransInfo Description="Autocorrect" HashKey="472947474729294729">
    <MapTiles>
      <MapTile TileID="15849" AltIDMod="0" />
      <MapTile TileID="15850" AltIDMod="0" />
      <MapTile TileID="15851" AltIDMod="0" />
      <MapTile TileID="15852" AltIDMod="0" />
    </MapTiles>
    <StaticTiles>
    </StaticTiles>
  </TransInfo>
  <TransInfo Description="Autocorrect" HashKey="472947294729294729">
    <MapTiles>
      <MapTile TileID="15849" AltIDMod="0" />
      <MapTile TileID="15850" AltIDMod="0" />
      <MapTile TileID="15851" AltIDMod="0" />
      <MapTile TileID="15852" AltIDMod="0" />
    </MapTiles>
    <StaticTiles>
    </StaticTiles>
  </TransInfo>
  <TransInfo Description="Autocorrect" HashKey="472947474729472929">
    <MapTiles>
      <MapTile TileID="15849" AltIDMod="0" />
      <MapTile TileID="15850" AltIDMod="0" />
      <MapTile TileID="15851" AltIDMod="0" />
      <MapTile TileID="15852" AltIDMod="0" />
    </MapTiles>
    <StaticTiles>
    </StaticTiles>
  </TransInfo>
  <TransInfo Description="Autocorrect" HashKey="472947294729472929">
    <MapTiles>
      <MapTile TileID="15849" AltIDMod="0" />
      <MapTile TileID="15850" AltIDMod="0" />
      <MapTile TileID="15851" AltIDMod="0" />
      <MapTile TileID="15852" AltIDMod="0" />
    </MapTiles>
    <StaticTiles>
    </StaticTiles>
  </TransInfo>
  <TransInfo Description="Autocorrect" HashKey="472947474729292929">
    <MapTiles>
      <MapTile TileID="15849" AltIDMod="0" />
      <MapTile TileID="15850" AltIDMod="0" />
      <MapTile TileID="15851" AltIDMod="0" />
      <MapTile TileID="15852" AltIDMod="0" />
    </MapTiles>
    <StaticTiles>
    </StaticTiles>
  </TransInfo>
  <TransInfo Description="Autocorrect" HashKey="472947294729292929">
    <MapTiles>
      <MapTile TileID="15849" AltIDMod="0" />
      <MapTile TileID="15850" AltIDMod="0" />
      <MapTile TileID="15851" AltIDMod="0" />
      <MapTile TileID="15852" AltIDMod="0" />
    </MapTiles>
    <StaticTiles>
    </StaticTiles>
  </TransInfo>
  <TransInfo Description="Autocorrect" HashKey="472929474747472947">
    <MapTiles>
      <MapTile TileID="15849" AltIDMod="0" />
      <MapTile TileID="15850" AltIDMod="0" />
      <MapTile TileID="15851" AltIDMod="0" />
      <MapTile TileID="15852" AltIDMod="0" />
    </MapTiles>
    <StaticTiles>
    </StaticTiles>
  </TransInfo>
  <TransInfo Description="Autocorrect" HashKey="472929294747472947">
    <MapTiles>
      <MapTile TileID="15849" AltIDMod="0" />
      <MapTile TileID="15850" AltIDMod="0" />
      <MapTile TileID="15851" AltIDMod="0" />
      <MapTile TileID="15852" AltIDMod="0" />
    </MapTiles>
    <StaticTiles>
    </StaticTiles>
  </TransInfo>
  <TransInfo Description="Autocorrect" HashKey="472929474747292947">
    <MapTiles>
      <MapTile TileID="15849" AltIDMod="0" />
      <MapTile TileID="15850" AltIDMod="0" />
      <MapTile TileID="15851" AltIDMod="0" />
      <MapTile TileID="15852" AltIDMod="0" />
    </MapTiles>
    <StaticTiles>
    </StaticTiles>
  </TransInfo>
  <TransInfo Description="Autocorrect" HashKey="472929294747292947">
    <MapTiles>
      <MapTile TileID="15849" AltIDMod="0" />
      <MapTile TileID="15850" AltIDMod="0" />
      <MapTile TileID="15851" AltIDMod="0" />
      <MapTile TileID="15852" AltIDMod="0" />
    </MapTiles>
    <StaticTiles>
    </StaticTiles>
  </TransInfo>
  <TransInfo Description="Autocorrect" HashKey="472929294747474729">
    <MapTiles>
      <MapTile TileID="15849" AltIDMod="0" />
      <MapTile TileID="15850" AltIDMod="0" />
      <MapTile TileID="15851" AltIDMod="0" />
      <MapTile TileID="15852" AltIDMod="0" />
    </MapTiles>
    <StaticTiles>
    </StaticTiles>
  </TransInfo>
  <TransInfo Description="Autocorrect" HashKey="472929474747294729">
    <MapTiles>
      <MapTile TileID="15849" AltIDMod="0" />
      <MapTile TileID="15850" AltIDMod="0" />
      <MapTile TileID="15851" AltIDMod="0" />
      <MapTile TileID="15852" AltIDMod="0" />
    </MapTiles>
    <StaticTiles>
    </StaticTiles>
  </TransInfo>
  <TransInfo Description="Autocorrect" HashKey="472929294747294729">
    <MapTiles>
      <MapTile TileID="15849" AltIDMod="0" />
      <MapTile TileID="15850" AltIDMod="0" />
      <MapTile TileID="15851" AltIDMod="0" />
      <MapTile TileID="15852" AltIDMod="0" />
    </MapTiles>
    <StaticTiles>
    </StaticTiles>
  </TransInfo>
  <TransInfo Description="Autocorrect" HashKey="472929474747472929">
    <MapTiles>
      <MapTile TileID="15849" AltIDMod="0" />
      <MapTile TileID="15850" AltIDMod="0" />
      <MapTile TileID="15851" AltIDMod="0" />
      <MapTile TileID="15852" AltIDMod="0" />
    </MapTiles>
    <StaticTiles>
    </StaticTiles>
  </TransInfo>
  <TransInfo Description="Autocorrect" HashKey="472929294747472929">
    <MapTiles>
      <MapTile TileID="15849" AltIDMod="0" />
      <MapTile TileID="15850" AltIDMod="0" />
      <MapTile TileID="15851" AltIDMod="0" />
      <MapTile TileID="15852" AltIDMod="0" />
    </MapTiles>
    <StaticTiles>
    </StaticTiles>
  </TransInfo>
  <TransInfo Description="Autocorrect" HashKey="472929474747292929">
    <MapTiles>
      <MapTile TileID="15849" AltIDMod="0" />
      <MapTile TileID="15850" AltIDMod="0" />
      <MapTile TileID="15851" AltIDMod="0" />
      <MapTile TileID="15852" AltIDMod="0" />
    </MapTiles>
    <StaticTiles>
    </StaticTiles>
  </TransInfo>
  <TransInfo Description="Autocorrect" HashKey="472929294747292929">
    <MapTiles>
      <MapTile TileID="15849" AltIDMod="0" />
      <MapTile TileID="15850" AltIDMod="0" />
      <MapTile TileID="15851" AltIDMod="0" />
      <MapTile TileID="15852" AltIDMod="0" />
    </MapTiles>
    <StaticTiles>
    </StaticTiles>
  </TransInfo>
  <TransInfo Description="Autocorrect" HashKey="472929294729474747">
    <MapTiles>
      <MapTile TileID="15849" AltIDMod="0" />
      <MapTile TileID="15850" AltIDMod="0" />
      <MapTile TileID="15851" AltIDMod="0" />
      <MapTile TileID="15852" AltIDMod="0" />
    </MapTiles>
    <StaticTiles>
    </StaticTiles>
  </TransInfo>
  <TransInfo Description="Autocorrect" HashKey="472929474729294747">
    <MapTiles>
      <MapTile TileID="15849" AltIDMod="0" />
      <MapTile TileID="15850" AltIDMod="0" />
      <MapTile TileID="15851" AltIDMod="0" />
      <MapTile TileID="15852" AltIDMod="0" />
    </MapTiles>
    <StaticTiles>
    </StaticTiles>
  </TransInfo>
  <TransInfo Description="Autocorrect" HashKey="472929294729294747">
    <MapTiles>
      <MapTile TileID="15849" AltIDMod="0" />
      <MapTile TileID="15850" AltIDMod="0" />
      <MapTile TileID="15851" AltIDMod="0" />
      <MapTile TileID="15852" AltIDMod="0" />
    </MapTiles>
    <StaticTiles>
    </StaticTiles>
  </TransInfo>
  <TransInfo Description="Autocorrect" HashKey="472929474729472947">
    <MapTiles>
      <MapTile TileID="15849" AltIDMod="0" />
      <MapTile TileID="15850" AltIDMod="0" />
      <MapTile TileID="15851" AltIDMod="0" />
      <MapTile TileID="15852" AltIDMod="0" />
    </MapTiles>
    <StaticTiles>
    </StaticTiles>
  </TransInfo>
  <TransInfo Description="Autocorrect" HashKey="472929294729472947">
    <MapTiles>
      <MapTile TileID="15849" AltIDMod="0" />
      <MapTile TileID="15850" AltIDMod="0" />
      <MapTile TileID="15851" AltIDMod="0" />
      <MapTile TileID="15852" AltIDMod="0" />
    </MapTiles>
    <StaticTiles>
    </StaticTiles>
  </TransInfo>
  <TransInfo Description="Autocorrect" HashKey="472929474729292947">
    <MapTiles>
      <MapTile TileID="15849" AltIDMod="0" />
      <MapTile TileID="15850" AltIDMod="0" />
      <MapTile TileID="15851" AltIDMod="0" />
      <MapTile TileID="15852" AltIDMod="0" />
    </MapTiles>
    <StaticTiles>
    </StaticTiles>
  </TransInfo>
  <TransInfo Description="Autocorrect" HashKey="472929294729292947">
    <MapTiles>
      <MapTile TileID="15849" AltIDMod="0" />
      <MapTile TileID="15850" AltIDMod="0" />
      <MapTile TileID="15851" AltIDMod="0" />
      <MapTile TileID="15852" AltIDMod="0" />
    </MapTiles>
    <StaticTiles>
    </StaticTiles>
  </TransInfo>
  <TransInfo Description="Autocorrect" HashKey="472929294729474729">
    <MapTiles>
      <MapTile TileID="15849" AltIDMod="0" />
      <MapTile TileID="15850" AltIDMod="0" />
      <MapTile TileID="15851" AltIDMod="0" />
      <MapTile TileID="15852" AltIDMod="0" />
    </MapTiles>
    <StaticTiles>
    </StaticTiles>
  </TransInfo>
  <TransInfo Description="Autocorrect" HashKey="472929474729294729">
    <MapTiles>
      <MapTile TileID="15849" AltIDMod="0" />
      <MapTile TileID="15850" AltIDMod="0" />
      <MapTile TileID="15851" AltIDMod="0" />
      <MapTile TileID="15852" AltIDMod="0" />
    </MapTiles>
    <StaticTiles>
    </StaticTiles>
  </TransInfo>
  <TransInfo Description="Autocorrect" HashKey="472929294729294729">
    <MapTiles>
      <MapTile TileID="15849" AltIDMod="0" />
      <MapTile TileID="15850" AltIDMod="0" />
      <MapTile TileID="15851" AltIDMod="0" />
      <MapTile TileID="15852" AltIDMod="0" />
    </MapTiles>
    <StaticTiles>
    </StaticTiles>
  </TransInfo>
  <TransInfo Description="Autocorrect" HashKey="472929474729472929">
    <MapTiles>
      <MapTile TileID="15849" AltIDMod="0" />
      <MapTile TileID="15850" AltIDMod="0" />
      <MapTile TileID="15851" AltIDMod="0" />
      <MapTile TileID="15852" AltIDMod="0" />
    </MapTiles>
    <StaticTiles>
    </StaticTiles>
  </TransInfo>
  <TransInfo Description="Autocorrect" HashKey="472929294729472929">
    <MapTiles>
      <MapTile TileID="15849" AltIDMod="0" />
      <MapTile TileID="15850" AltIDMod="0" />
      <MapTile TileID="15851" AltIDMod="0" />
      <MapTile TileID="15852" AltIDMod="0" />
    </MapTiles>
    <StaticTiles>
    </StaticTiles>
  </TransInfo>
  <TransInfo Description="Autocorrect" HashKey="472929474729292929">
    <MapTiles>
      <MapTile TileID="15849" AltIDMod="0" />
      <MapTile TileID="15850" AltIDMod="0" />
      <MapTile TileID="15851" AltIDMod="0" />
      <MapTile TileID="15852" AltIDMod="0" />
    </MapTiles>
    <StaticTiles>
    </StaticTiles>
  </TransInfo>
  <TransInfo Description="Autocorrect" HashKey="472929294729292929">
    <MapTiles>
      <MapTile TileID="15849" AltIDMod="0" />
      <MapTile TileID="15850" AltIDMod="0" />
      <MapTile TileID="15851" AltIDMod="0" />
      <MapTile TileID="15852" AltIDMod="0" />
    </MapTiles>
    <StaticTiles>
    </StaticTiles>
  </TransInfo>
  <TransInfo Description="Autocorrect" HashKey="294747294729474747">
    <MapTiles>
      <MapTile TileID="15849" AltIDMod="0" />
      <MapTile TileID="15850" AltIDMod="0" />
      <MapTile TileID="15851" AltIDMod="0" />
      <MapTile TileID="15852" AltIDMod="0" />
    </MapTiles>
    <StaticTiles>
    </StaticTiles>
  </TransInfo>
  <TransInfo Description="Autocorrect" HashKey="294747474729294747">
    <MapTiles>
      <MapTile TileID="15849" AltIDMod="0" />
      <MapTile TileID="15850" AltIDMod="0" />
      <MapTile TileID="15851" AltIDMod="0" />
      <MapTile TileID="15852" AltIDMod="0" />
    </MapTiles>
    <StaticTiles>
    </StaticTiles>
  </TransInfo>
  <TransInfo Description="Autocorrect" HashKey="294747294729294747">
    <MapTiles>
      <MapTile TileID="15849" AltIDMod="0" />
      <MapTile TileID="15850" AltIDMod="0" />
      <MapTile TileID="15851" AltIDMod="0" />
      <MapTile TileID="15852" AltIDMod="0" />
    </MapTiles>
    <StaticTiles>
    </StaticTiles>
  </TransInfo>
  <TransInfo Description="Autocorrect" HashKey="294747474729472947">
    <MapTiles>
      <MapTile TileID="15849" AltIDMod="0" />
      <MapTile TileID="15850" AltIDMod="0" />
      <MapTile TileID="15851" AltIDMod="0" />
      <MapTile TileID="15852" AltIDMod="0" />
    </MapTiles>
    <StaticTiles>
    </StaticTiles>
  </TransInfo>
  <TransInfo Description="Autocorrect" HashKey="294747294729472947">
    <MapTiles>
      <MapTile TileID="15849" AltIDMod="0" />
      <MapTile TileID="15850" AltIDMod="0" />
      <MapTile TileID="15851" AltIDMod="0" />
      <MapTile TileID="15852" AltIDMod="0" />
    </MapTiles>
    <StaticTiles>
    </StaticTiles>
  </TransInfo>
  <TransInfo Description="Autocorrect" HashKey="294747474729292947">
    <MapTiles>
      <MapTile TileID="15849" AltIDMod="0" />
      <MapTile TileID="15850" AltIDMod="0" />
      <MapTile TileID="15851" AltIDMod="0" />
      <MapTile TileID="15852" AltIDMod="0" />
    </MapTiles>
    <StaticTiles>
    </StaticTiles>
  </TransInfo>
  <TransInfo Description="Autocorrect" HashKey="294747294729292947">
    <MapTiles>
      <MapTile TileID="15849" AltIDMod="0" />
      <MapTile TileID="15850" AltIDMod="0" />
      <MapTile TileID="15851" AltIDMod="0" />
      <MapTile TileID="15852" AltIDMod="0" />
    </MapTiles>
    <StaticTiles>
    </StaticTiles>
  </TransInfo>
  <TransInfo Description="Autocorrect" HashKey="294747294729474729">
    <MapTiles>
      <MapTile TileID="15849" AltIDMod="0" />
      <MapTile TileID="15850" AltIDMod="0" />
      <MapTile TileID="15851" AltIDMod="0" />
      <MapTile TileID="15852" AltIDMod="0" />
    </MapTiles>
    <StaticTiles>
    </StaticTiles>
  </TransInfo>
  <TransInfo Description="Autocorrect" HashKey="294747474729294729">
    <MapTiles>
      <MapTile TileID="15849" AltIDMod="0" />
      <MapTile TileID="15850" AltIDMod="0" />
      <MapTile TileID="15851" AltIDMod="0" />
      <MapTile TileID="15852" AltIDMod="0" />
    </MapTiles>
    <StaticTiles>
    </StaticTiles>
  </TransInfo>
  <TransInfo Description="Autocorrect" HashKey="294747294729294729">
    <MapTiles>
      <MapTile TileID="15849" AltIDMod="0" />
      <MapTile TileID="15850" AltIDMod="0" />
      <MapTile TileID="15851" AltIDMod="0" />
      <MapTile TileID="15852" AltIDMod="0" />
    </MapTiles>
    <StaticTiles>
    </StaticTiles>
  </TransInfo>
  <TransInfo Description="Autocorrect" HashKey="294747474729472929">
    <MapTiles>
      <MapTile TileID="15849" AltIDMod="0" />
      <MapTile TileID="15850" AltIDMod="0" />
      <MapTile TileID="15851" AltIDMod="0" />
      <MapTile TileID="15852" AltIDMod="0" />
    </MapTiles>
    <StaticTiles>
    </StaticTiles>
  </TransInfo>
  <TransInfo Description="Autocorrect" HashKey="294747294729472929">
    <MapTiles>
      <MapTile TileID="15849" AltIDMod="0" />
      <MapTile TileID="15850" AltIDMod="0" />
      <MapTile TileID="15851" AltIDMod="0" />
      <MapTile TileID="15852" AltIDMod="0" />
    </MapTiles>
    <StaticTiles>
    </StaticTiles>
  </TransInfo>
  <TransInfo Description="Autocorrect" HashKey="294747474729292929">
    <MapTiles>
      <MapTile TileID="15849" AltIDMod="0" />
      <MapTile TileID="15850" AltIDMod="0" />
      <MapTile TileID="15851" AltIDMod="0" />
      <MapTile TileID="15852" AltIDMod="0" />
    </MapTiles>
    <StaticTiles>
    </StaticTiles>
  </TransInfo>
  <TransInfo Description="Autocorrect" HashKey="294747294729292929">
    <MapTiles>
      <MapTile TileID="15849" AltIDMod="0" />
      <MapTile TileID="15850" AltIDMod="0" />
      <MapTile TileID="15851" AltIDMod="0" />
      <MapTile TileID="15852" AltIDMod="0" />
    </MapTiles>
    <StaticTiles>
    </StaticTiles>
  </TransInfo>
  <TransInfo Description="Autocorrect" HashKey="294729474747472947">
    <MapTiles>
      <MapTile TileID="15849" AltIDMod="0" />
      <MapTile TileID="15850" AltIDMod="0" />
      <MapTile TileID="15851" AltIDMod="0" />
      <MapTile TileID="15852" AltIDMod="0" />
    </MapTiles>
    <StaticTiles>
    </StaticTiles>
  </TransInfo>
  <TransInfo Description="Autocorrect" HashKey="294729294747472947">
    <MapTiles>
      <MapTile TileID="15849" AltIDMod="0" />
      <MapTile TileID="15850" AltIDMod="0" />
      <MapTile TileID="15851" AltIDMod="0" />
      <MapTile TileID="15852" AltIDMod="0" />
    </MapTiles>
    <StaticTiles>
    </StaticTiles>
  </TransInfo>
  <TransInfo Description="Autocorrect" HashKey="294729474747292947">
    <MapTiles>
      <MapTile TileID="15849" AltIDMod="0" />
      <MapTile TileID="15850" AltIDMod="0" />
      <MapTile TileID="15851" AltIDMod="0" />
      <MapTile TileID="15852" AltIDMod="0" />
    </MapTiles>
    <StaticTiles>
    </StaticTiles>
  </TransInfo>
  <TransInfo Description="Autocorrect" HashKey="294729294747292947">
    <MapTiles>
      <MapTile TileID="15849" AltIDMod="0" />
      <MapTile TileID="15850" AltIDMod="0" />
      <MapTile TileID="15851" AltIDMod="0" />
      <MapTile TileID="15852" AltIDMod="0" />
    </MapTiles>
    <StaticTiles>
    </StaticTiles>
  </TransInfo>
  <TransInfo Description="Autocorrect" HashKey="294729294747474729">
    <MapTiles>
      <MapTile TileID="15849" AltIDMod="0" />
      <MapTile TileID="15850" AltIDMod="0" />
      <MapTile TileID="15851" AltIDMod="0" />
      <MapTile TileID="15852" AltIDMod="0" />
    </MapTiles>
    <StaticTiles>
    </StaticTiles>
  </TransInfo>
  <TransInfo Description="Autocorrect" HashKey="294729474747294729">
    <MapTiles>
      <MapTile TileID="15849" AltIDMod="0" />
      <MapTile TileID="15850" AltIDMod="0" />
      <MapTile TileID="15851" AltIDMod="0" />
      <MapTile TileID="15852" AltIDMod="0" />
    </MapTiles>
    <StaticTiles>
    </StaticTiles>
  </TransInfo>
  <TransInfo Description="Autocorrect" HashKey="294729294747294729">
    <MapTiles>
      <MapTile TileID="15849" AltIDMod="0" />
      <MapTile TileID="15850" AltIDMod="0" />
      <MapTile TileID="15851" AltIDMod="0" />
      <MapTile TileID="15852" AltIDMod="0" />
    </MapTiles>
    <StaticTiles>
    </StaticTiles>
  </TransInfo>
  <TransInfo Description="Autocorrect" HashKey="294729474747472929">
    <MapTiles>
      <MapTile TileID="15849" AltIDMod="0" />
      <MapTile TileID="15850" AltIDMod="0" />
      <MapTile TileID="15851" AltIDMod="0" />
      <MapTile TileID="15852" AltIDMod="0" />
    </MapTiles>
    <StaticTiles>
    </StaticTiles>
  </TransInfo>
  <TransInfo Description="Autocorrect" HashKey="294729294747472929">
    <MapTiles>
      <MapTile TileID="15849" AltIDMod="0" />
      <MapTile TileID="15850" AltIDMod="0" />
      <MapTile TileID="15851" AltIDMod="0" />
      <MapTile TileID="15852" AltIDMod="0" />
    </MapTiles>
    <StaticTiles>
    </StaticTiles>
  </TransInfo>
  <TransInfo Description="Autocorrect" HashKey="294729474747292929">
    <MapTiles>
      <MapTile TileID="15849" AltIDMod="0" />
      <MapTile TileID="15850" AltIDMod="0" />
      <MapTile TileID="15851" AltIDMod="0" />
      <MapTile TileID="15852" AltIDMod="0" />
    </MapTiles>
    <StaticTiles>
    </StaticTiles>
  </TransInfo>
  <TransInfo Description="Autocorrect" HashKey="294729294747292929">
    <MapTiles>
      <MapTile TileID="15849" AltIDMod="0" />
      <MapTile TileID="15850" AltIDMod="0" />
      <MapTile TileID="15851" AltIDMod="0" />
      <MapTile TileID="15852" AltIDMod="0" />
    </MapTiles>
    <StaticTiles>
    </StaticTiles>
  </TransInfo>
  <TransInfo Description="Autocorrect" HashKey="294729294729474747">
    <MapTiles>
      <MapTile TileID="15849" AltIDMod="0" />
      <MapTile TileID="15850" AltIDMod="0" />
      <MapTile TileID="15851" AltIDMod="0" />
      <MapTile TileID="15852" AltIDMod="0" />
    </MapTiles>
    <StaticTiles>
    </StaticTiles>
  </TransInfo>
  <TransInfo Description="Autocorrect" HashKey="294729474729294747">
    <MapTiles>
      <MapTile TileID="15849" AltIDMod="0" />
      <MapTile TileID="15850" AltIDMod="0" />
      <MapTile TileID="15851" AltIDMod="0" />
      <MapTile TileID="15852" AltIDMod="0" />
    </MapTiles>
    <StaticTiles>
    </StaticTiles>
  </TransInfo>
  <TransInfo Description="Autocorrect" HashKey="294729294729294747">
    <MapTiles>
      <MapTile TileID="15849" AltIDMod="0" />
      <MapTile TileID="15850" AltIDMod="0" />
      <MapTile TileID="15851" AltIDMod="0" />
      <MapTile TileID="15852" AltIDMod="0" />
    </MapTiles>
    <StaticTiles>
    </StaticTiles>
  </TransInfo>
  <TransInfo Description="Autocorrect" HashKey="294729474729472947">
    <MapTiles>
      <MapTile TileID="15849" AltIDMod="0" />
      <MapTile TileID="15850" AltIDMod="0" />
      <MapTile TileID="15851" AltIDMod="0" />
      <MapTile TileID="15852" AltIDMod="0" />
    </MapTiles>
    <StaticTiles>
    </StaticTiles>
  </TransInfo>
  <TransInfo Description="Autocorrect" HashKey="294729294729472947">
    <MapTiles>
      <MapTile TileID="15849" AltIDMod="0" />
      <MapTile TileID="15850" AltIDMod="0" />
      <MapTile TileID="15851" AltIDMod="0" />
      <MapTile TileID="15852" AltIDMod="0" />
    </MapTiles>
    <StaticTiles>
    </StaticTiles>
  </TransInfo>
  <TransInfo Description="Autocorrect" HashKey="294729474729292947">
    <MapTiles>
      <MapTile TileID="15849" AltIDMod="0" />
      <MapTile TileID="15850" AltIDMod="0" />
      <MapTile TileID="15851" AltIDMod="0" />
      <MapTile TileID="15852" AltIDMod="0" />
    </MapTiles>
    <StaticTiles>
    </StaticTiles>
  </TransInfo>
  <TransInfo Description="Autocorrect" HashKey="294729294729292947">
    <MapTiles>
      <MapTile TileID="15849" AltIDMod="0" />
      <MapTile TileID="15850" AltIDMod="0" />
      <MapTile TileID="15851" AltIDMod="0" />
      <MapTile TileID="15852" AltIDMod="0" />
    </MapTiles>
    <StaticTiles>
    </StaticTiles>
  </TransInfo>
  <TransInfo Description="Autocorrect" HashKey="294729294729474729">
    <MapTiles>
      <MapTile TileID="15849" AltIDMod="0" />
      <MapTile TileID="15850" AltIDMod="0" />
      <MapTile TileID="15851" AltIDMod="0" />
      <MapTile TileID="15852" AltIDMod="0" />
    </MapTiles>
    <StaticTiles>
    </StaticTiles>
  </TransInfo>
  <TransInfo Description="Autocorrect" HashKey="294729474729294729">
    <MapTiles>
      <MapTile TileID="15849" AltIDMod="0" />
      <MapTile TileID="15850" AltIDMod="0" />
      <MapTile TileID="15851" AltIDMod="0" />
      <MapTile TileID="15852" AltIDMod="0" />
    </MapTiles>
    <StaticTiles>
    </StaticTiles>
  </TransInfo>
  <TransInfo Description="Autocorrect" HashKey="294729294729294729">
    <MapTiles>
      <MapTile TileID="15849" AltIDMod="0" />
      <MapTile TileID="15850" AltIDMod="0" />
      <MapTile TileID="15851" AltIDMod="0" />
      <MapTile TileID="15852" AltIDMod="0" />
    </MapTiles>
    <StaticTiles>
    </StaticTiles>
  </TransInfo>
  <TransInfo Description="Autocorrect" HashKey="294729474729472929">
    <MapTiles>
      <MapTile TileID="15849" AltIDMod="0" />
      <MapTile TileID="15850" AltIDMod="0" />
      <MapTile TileID="15851" AltIDMod="0" />
      <MapTile TileID="15852" AltIDMod="0" />
    </MapTiles>
    <StaticTiles>
    </StaticTiles>
  </TransInfo>
  <TransInfo Description="Autocorrect" HashKey="294729294729472929">
    <MapTiles>
      <MapTile TileID="15849" AltIDMod="0" />
      <MapTile TileID="15850" AltIDMod="0" />
      <MapTile TileID="15851" AltIDMod="0" />
      <MapTile TileID="15852" AltIDMod="0" />
    </MapTiles>
    <StaticTiles>
    </StaticTiles>
  </TransInfo>
  <TransInfo Description="Autocorrect" HashKey="294729474729292929">
    <MapTiles>
      <MapTile TileID="15849" AltIDMod="0" />
      <MapTile TileID="15850" AltIDMod="0" />
      <MapTile TileID="15851" AltIDMod="0" />
      <MapTile TileID="15852" AltIDMod="0" />
    </MapTiles>
    <StaticTiles>
    </StaticTiles>
  </TransInfo>
  <TransInfo Description="Autocorrect" HashKey="294729294729292929">
    <MapTiles>
      <MapTile TileID="15849" AltIDMod="0" />
      <MapTile TileID="15850" AltIDMod="0" />
      <MapTile TileID="15851" AltIDMod="0" />
      <MapTile TileID="15852" AltIDMod="0" />
    </MapTiles>
    <StaticTiles>
    </StaticTiles>
  </TransInfo>
  <TransInfo Description="Autocorrect" HashKey="292947474747472947">
    <MapTiles>
      <MapTile TileID="15849" AltIDMod="0" />
      <MapTile TileID="15850" AltIDMod="0" />
      <MapTile TileID="15851" AltIDMod="0" />
      <MapTile TileID="15852" AltIDMod="0" />
    </MapTiles>
    <StaticTiles>
    </StaticTiles>
  </TransInfo>
  <TransInfo Description="Autocorrect" HashKey="292947294747472947">
    <MapTiles>
      <MapTile TileID="15849" AltIDMod="0" />
      <MapTile TileID="15850" AltIDMod="0" />
      <MapTile TileID="15851" AltIDMod="0" />
      <MapTile TileID="15852" AltIDMod="0" />
    </MapTiles>
    <StaticTiles>
    </StaticTiles>
  </TransInfo>
  <TransInfo Description="Autocorrect" HashKey="292947474747292947">
    <MapTiles>
      <MapTile TileID="15849" AltIDMod="0" />
      <MapTile TileID="15850" AltIDMod="0" />
      <MapTile TileID="15851" AltIDMod="0" />
      <MapTile TileID="15852" AltIDMod="0" />
    </MapTiles>
    <StaticTiles>
    </StaticTiles>
  </TransInfo>
  <TransInfo Description="Autocorrect" HashKey="292947294747292947">
    <MapTiles>
      <MapTile TileID="15849" AltIDMod="0" />
      <MapTile TileID="15850" AltIDMod="0" />
      <MapTile TileID="15851" AltIDMod="0" />
      <MapTile TileID="15852" AltIDMod="0" />
    </MapTiles>
    <StaticTiles>
    </StaticTiles>
  </TransInfo>
  <TransInfo Description="Autocorrect" HashKey="292947294747474729">
    <MapTiles>
      <MapTile TileID="15849" AltIDMod="0" />
      <MapTile TileID="15850" AltIDMod="0" />
      <MapTile TileID="15851" AltIDMod="0" />
      <MapTile TileID="15852" AltIDMod="0" />
    </MapTiles>
    <StaticTiles>
    </StaticTiles>
  </TransInfo>
  <TransInfo Description="Autocorrect" HashKey="292947474747294729">
    <MapTiles>
      <MapTile TileID="15849" AltIDMod="0" />
      <MapTile TileID="15850" AltIDMod="0" />
      <MapTile TileID="15851" AltIDMod="0" />
      <MapTile TileID="15852" AltIDMod="0" />
    </MapTiles>
    <StaticTiles>
    </StaticTiles>
  </TransInfo>
  <TransInfo Description="Autocorrect" HashKey="292947294747294729">
    <MapTiles>
      <MapTile TileID="15849" AltIDMod="0" />
      <MapTile TileID="15850" AltIDMod="0" />
      <MapTile TileID="15851" AltIDMod="0" />
      <MapTile TileID="15852" AltIDMod="0" />
    </MapTiles>
    <StaticTiles>
    </StaticTiles>
  </TransInfo>
  <TransInfo Description="Autocorrect" HashKey="292947474747472929">
    <MapTiles>
      <MapTile TileID="15849" AltIDMod="0" />
      <MapTile TileID="15850" AltIDMod="0" />
      <MapTile TileID="15851" AltIDMod="0" />
      <MapTile TileID="15852" AltIDMod="0" />
    </MapTiles>
    <StaticTiles>
    </StaticTiles>
  </TransInfo>
  <TransInfo Description="Autocorrect" HashKey="292947294747472929">
    <MapTiles>
      <MapTile TileID="15849" AltIDMod="0" />
      <MapTile TileID="15850" AltIDMod="0" />
      <MapTile TileID="15851" AltIDMod="0" />
      <MapTile TileID="15852" AltIDMod="0" />
    </MapTiles>
    <StaticTiles>
    </StaticTiles>
  </TransInfo>
  <TransInfo Description="Autocorrect" HashKey="292947474747292929">
    <MapTiles>
      <MapTile TileID="15849" AltIDMod="0" />
      <MapTile TileID="15850" AltIDMod="0" />
      <MapTile TileID="15851" AltIDMod="0" />
      <MapTile TileID="15852" AltIDMod="0" />
    </MapTiles>
    <StaticTiles>
    </StaticTiles>
  </TransInfo>
  <TransInfo Description="Autocorrect" HashKey="292947294747292929">
    <MapTiles>
      <MapTile TileID="15849" AltIDMod="0" />
      <MapTile TileID="15850" AltIDMod="0" />
      <MapTile TileID="15851" AltIDMod="0" />
      <MapTile TileID="15852" AltIDMod="0" />
    </MapTiles>
    <StaticTiles>
    </StaticTiles>
  </TransInfo>
  <TransInfo Description="Autocorrect" HashKey="292947294729474747">
    <MapTiles>
      <MapTile TileID="15849" AltIDMod="0" />
      <MapTile TileID="15850" AltIDMod="0" />
      <MapTile TileID="15851" AltIDMod="0" />
      <MapTile TileID="15852" AltIDMod="0" />
    </MapTiles>
    <StaticTiles>
    </StaticTiles>
  </TransInfo>
  <TransInfo Description="Autocorrect" HashKey="292947474729294747">
    <MapTiles>
      <MapTile TileID="15849" AltIDMod="0" />
      <MapTile TileID="15850" AltIDMod="0" />
      <MapTile TileID="15851" AltIDMod="0" />
      <MapTile TileID="15852" AltIDMod="0" />
    </MapTiles>
    <StaticTiles>
    </StaticTiles>
  </TransInfo>
  <TransInfo Description="Autocorrect" HashKey="292947294729294747">
    <MapTiles>
      <MapTile TileID="15849" AltIDMod="0" />
      <MapTile TileID="15850" AltIDMod="0" />
      <MapTile TileID="15851" AltIDMod="0" />
      <MapTile TileID="15852" AltIDMod="0" />
    </MapTiles>
    <StaticTiles>
    </StaticTiles>
  </TransInfo>
  <TransInfo Description="Autocorrect" HashKey="292947474729472947">
    <MapTiles>
      <MapTile TileID="15849" AltIDMod="0" />
      <MapTile TileID="15850" AltIDMod="0" />
      <MapTile TileID="15851" AltIDMod="0" />
      <MapTile TileID="15852" AltIDMod="0" />
    </MapTiles>
    <StaticTiles>
    </StaticTiles>
  </TransInfo>
  <TransInfo Description="Autocorrect" HashKey="292947294729472947">
    <MapTiles>
      <MapTile TileID="15849" AltIDMod="0" />
      <MapTile TileID="15850" AltIDMod="0" />
      <MapTile TileID="15851" AltIDMod="0" />
      <MapTile TileID="15852" AltIDMod="0" />
    </MapTiles>
    <StaticTiles>
    </StaticTiles>
  </TransInfo>
  <TransInfo Description="Autocorrect" HashKey="292947474729292947">
    <MapTiles>
      <MapTile TileID="15849" AltIDMod="0" />
      <MapTile TileID="15850" AltIDMod="0" />
      <MapTile TileID="15851" AltIDMod="0" />
      <MapTile TileID="15852" AltIDMod="0" />
    </MapTiles>
    <StaticTiles>
    </StaticTiles>
  </TransInfo>
  <TransInfo Description="Autocorrect" HashKey="292947294729292947">
    <MapTiles>
      <MapTile TileID="15849" AltIDMod="0" />
      <MapTile TileID="15850" AltIDMod="0" />
      <MapTile TileID="15851" AltIDMod="0" />
      <MapTile TileID="15852" AltIDMod="0" />
    </MapTiles>
    <StaticTiles>
    </StaticTiles>
  </TransInfo>
  <TransInfo Description="Autocorrect" HashKey="292947294729474729">
    <MapTiles>
      <MapTile TileID="15849" AltIDMod="0" />
      <MapTile TileID="15850" AltIDMod="0" />
      <MapTile TileID="15851" AltIDMod="0" />
      <MapTile TileID="15852" AltIDMod="0" />
    </MapTiles>
    <StaticTiles>
    </StaticTiles>
  </TransInfo>
  <TransInfo Description="Autocorrect" HashKey="292947474729294729">
    <MapTiles>
      <MapTile TileID="15849" AltIDMod="0" />
      <MapTile TileID="15850" AltIDMod="0" />
      <MapTile TileID="15851" AltIDMod="0" />
      <MapTile TileID="15852" AltIDMod="0" />
    </MapTiles>
    <StaticTiles>
    </StaticTiles>
  </TransInfo>
  <TransInfo Description="Autocorrect" HashKey="292947294729294729">
    <MapTiles>
      <MapTile TileID="15849" AltIDMod="0" />
      <MapTile TileID="15850" AltIDMod="0" />
      <MapTile TileID="15851" AltIDMod="0" />
      <MapTile TileID="15852" AltIDMod="0" />
    </MapTiles>
    <StaticTiles>
    </StaticTiles>
  </TransInfo>
  <TransInfo Description="Autocorrect" HashKey="292947474729472929">
    <MapTiles>
      <MapTile TileID="15849" AltIDMod="0" />
      <MapTile TileID="15850" AltIDMod="0" />
      <MapTile TileID="15851" AltIDMod="0" />
      <MapTile TileID="15852" AltIDMod="0" />
    </MapTiles>
    <StaticTiles>
    </StaticTiles>
  </TransInfo>
  <TransInfo Description="Autocorrect" HashKey="292947294729472929">
    <MapTiles>
      <MapTile TileID="15849" AltIDMod="0" />
      <MapTile TileID="15850" AltIDMod="0" />
      <MapTile TileID="15851" AltIDMod="0" />
      <MapTile TileID="15852" AltIDMod="0" />
    </MapTiles>
    <StaticTiles>
    </StaticTiles>
  </TransInfo>
  <TransInfo Description="Autocorrect" HashKey="292947474729292929">
    <MapTiles>
      <MapTile TileID="15849" AltIDMod="0" />
      <MapTile TileID="15850" AltIDMod="0" />
      <MapTile TileID="15851" AltIDMod="0" />
      <MapTile TileID="15852" AltIDMod="0" />
    </MapTiles>
    <StaticTiles>
    </StaticTiles>
  </TransInfo>
  <TransInfo Description="Autocorrect" HashKey="292947294729292929">
    <MapTiles>
      <MapTile TileID="15849" AltIDMod="0" />
      <MapTile TileID="15850" AltIDMod="0" />
      <MapTile TileID="15851" AltIDMod="0" />
      <MapTile TileID="15852" AltIDMod="0" />
    </MapTiles>
    <StaticTiles>
    </StaticTiles>
  </TransInfo>
  <TransInfo Description="Autocorrect" HashKey="292929474747472947">
    <MapTiles>
      <MapTile TileID="15849" AltIDMod="0" />
      <MapTile TileID="15850" AltIDMod="0" />
      <MapTile TileID="15851" AltIDMod="0" />
      <MapTile TileID="15852" AltIDMod="0" />
    </MapTiles>
    <StaticTiles>
    </StaticTiles>
  </TransInfo>
  <TransInfo Description="Autocorrect" HashKey="292929294747472947">
    <MapTiles>
      <MapTile TileID="15849" AltIDMod="0" />
      <MapTile TileID="15850" AltIDMod="0" />
      <MapTile TileID="15851" AltIDMod="0" />
      <MapTile TileID="15852" AltIDMod="0" />
    </MapTiles>
    <StaticTiles>
    </StaticTiles>
  </TransInfo>
  <TransInfo Description="Autocorrect" HashKey="292929474747292947">
    <MapTiles>
      <MapTile TileID="15849" AltIDMod="0" />
      <MapTile TileID="15850" AltIDMod="0" />
      <MapTile TileID="15851" AltIDMod="0" />
      <MapTile TileID="15852" AltIDMod="0" />
    </MapTiles>
    <StaticTiles>
    </StaticTiles>
  </TransInfo>
  <TransInfo Description="Autocorrect" HashKey="292929294747292947">
    <MapTiles>
      <MapTile TileID="15849" AltIDMod="0" />
      <MapTile TileID="15850" AltIDMod="0" />
      <MapTile TileID="15851" AltIDMod="0" />
      <MapTile TileID="15852" AltIDMod="0" />
    </MapTiles>
    <StaticTiles>
    </StaticTiles>
  </TransInfo>
  <TransInfo Description="Autocorrect" HashKey="292929294747474729">
    <MapTiles>
      <MapTile TileID="15849" AltIDMod="0" />
      <MapTile TileID="15850" AltIDMod="0" />
      <MapTile TileID="15851" AltIDMod="0" />
      <MapTile TileID="15852" AltIDMod="0" />
    </MapTiles>
    <StaticTiles>
    </StaticTiles>
  </TransInfo>
  <TransInfo Description="Autocorrect" HashKey="292929474747294729">
    <MapTiles>
      <MapTile TileID="15849" AltIDMod="0" />
      <MapTile TileID="15850" AltIDMod="0" />
      <MapTile TileID="15851" AltIDMod="0" />
      <MapTile TileID="15852" AltIDMod="0" />
    </MapTiles>
    <StaticTiles>
    </StaticTiles>
  </TransInfo>
  <TransInfo Description="Autocorrect" HashKey="292929294747294729">
    <MapTiles>
      <MapTile TileID="15849" AltIDMod="0" />
      <MapTile TileID="15850" AltIDMod="0" />
      <MapTile TileID="15851" AltIDMod="0" />
      <MapTile TileID="15852" AltIDMod="0" />
    </MapTiles>
    <StaticTiles>
    </StaticTiles>
  </TransInfo>
  <TransInfo Description="Autocorrect" HashKey="292929474747472929">
    <MapTiles>
      <MapTile TileID="15849" AltIDMod="0" />
      <MapTile TileID="15850" AltIDMod="0" />
      <MapTile TileID="15851" AltIDMod="0" />
      <MapTile TileID="15852" AltIDMod="0" />
    </MapTiles>
    <StaticTiles>
    </StaticTiles>
  </TransInfo>
  <TransInfo Description="Autocorrect" HashKey="292929294747472929">
    <MapTiles>
      <MapTile TileID="15849" AltIDMod="0" />
      <MapTile TileID="15850" AltIDMod="0" />
      <MapTile TileID="15851" AltIDMod="0" />
      <MapTile TileID="15852" AltIDMod="0" />
    </MapTiles>
    <StaticTiles>
    </StaticTiles>
  </TransInfo>
  <TransInfo Description="Autocorrect" HashKey="292929474747292929">
    <MapTiles>
      <MapTile TileID="15849" AltIDMod="0" />
      <MapTile TileID="15850" AltIDMod="0" />
      <MapTile TileID="15851" AltIDMod="0" />
      <MapTile TileID="15852" AltIDMod="0" />
    </MapTiles>
    <StaticTiles>
    </StaticTiles>
  </TransInfo>
  <TransInfo Description="Autocorrect" HashKey="292929294747292929">
    <MapTiles>
      <MapTile TileID="15849" AltIDMod="0" />
      <MapTile TileID="15850" AltIDMod="0" />
      <MapTile TileID="15851" AltIDMod="0" />
      <MapTile TileID="15852" AltIDMod="0" />
    </MapTiles>
    <StaticTiles>
    </StaticTiles>
  </TransInfo>
  <TransInfo Description="Autocorrect" HashKey="292929294729474747">
    <MapTiles>
      <MapTile TileID="15849" AltIDMod="0" />
      <MapTile TileID="15850" AltIDMod="0" />
      <MapTile TileID="15851" AltIDMod="0" />
      <MapTile TileID="15852" AltIDMod="0" />
    </MapTiles>
    <StaticTiles>
    </StaticTiles>
  </TransInfo>
  <TransInfo Description="Autocorrect" HashKey="292929474729294747">
    <MapTiles>
      <MapTile TileID="15849" AltIDMod="0" />
      <MapTile TileID="15850" AltIDMod="0" />
      <MapTile TileID="15851" AltIDMod="0" />
      <MapTile TileID="15852" AltIDMod="0" />
    </MapTiles>
    <StaticTiles>
    </StaticTiles>
  </TransInfo>
  <TransInfo Description="Autocorrect" HashKey="292929294729294747">
    <MapTiles>
      <MapTile TileID="15849" AltIDMod="0" />
      <MapTile TileID="15850" AltIDMod="0" />
      <MapTile TileID="15851" AltIDMod="0" />
      <MapTile TileID="15852" AltIDMod="0" />
    </MapTiles>
    <StaticTiles>
    </StaticTiles>
  </TransInfo>
  <TransInfo Description="Autocorrect" HashKey="292929474729472947">
    <MapTiles>
      <MapTile TileID="15849" AltIDMod="0" />
      <MapTile TileID="15850" AltIDMod="0" />
      <MapTile TileID="15851" AltIDMod="0" />
      <MapTile TileID="15852" AltIDMod="0" />
    </MapTiles>
    <StaticTiles>
    </StaticTiles>
  </TransInfo>
  <TransInfo Description="Autocorrect" HashKey="292929294729472947">
    <MapTiles>
      <MapTile TileID="15849" AltIDMod="0" />
      <MapTile TileID="15850" AltIDMod="0" />
      <MapTile TileID="15851" AltIDMod="0" />
      <MapTile TileID="15852" AltIDMod="0" />
    </MapTiles>
    <StaticTiles>
    </StaticTiles>
  </TransInfo>
  <TransInfo Description="Autocorrect" HashKey="292929474729292947">
    <MapTiles>
      <MapTile TileID="15849" AltIDMod="0" />
      <MapTile TileID="15850" AltIDMod="0" />
      <MapTile TileID="15851" AltIDMod="0" />
      <MapTile TileID="15852" AltIDMod="0" />
    </MapTiles>
    <StaticTiles>
    </StaticTiles>
  </TransInfo>
  <TransInfo Description="Autocorrect" HashKey="292929294729292947">
    <MapTiles>
      <MapTile TileID="15849" AltIDMod="0" />
      <MapTile TileID="15850" AltIDMod="0" />
      <MapTile TileID="15851" AltIDMod="0" />
      <MapTile TileID="15852" AltIDMod="0" />
    </MapTiles>
    <StaticTiles>
    </StaticTiles>
  </TransInfo>
  <TransInfo Description="Autocorrect" HashKey="292929294729474729">
    <MapTiles>
      <MapTile TileID="15849" AltIDMod="0" />
      <MapTile TileID="15850" AltIDMod="0" />
      <MapTile TileID="15851" AltIDMod="0" />
      <MapTile TileID="15852" AltIDMod="0" />
    </MapTiles>
    <StaticTiles>
    </StaticTiles>
  </TransInfo>
  <TransInfo Description="Autocorrect" HashKey="292929474729294729">
    <MapTiles>
      <MapTile TileID="15849" AltIDMod="0" />
      <MapTile TileID="15850" AltIDMod="0" />
      <MapTile TileID="15851" AltIDMod="0" />
      <MapTile TileID="15852" AltIDMod="0" />
    </MapTiles>
    <StaticTiles>
    </StaticTiles>
  </TransInfo>
  <TransInfo Description="Autocorrect" HashKey="292929294729294729">
    <MapTiles>
      <MapTile TileID="15849" AltIDMod="0" />
      <MapTile TileID="15850" AltIDMod="0" />
      <MapTile TileID="15851" AltIDMod="0" />
      <MapTile TileID="15852" AltIDMod="0" />
    </MapTiles>
    <StaticTiles>
    </StaticTiles>
  </TransInfo>
  <TransInfo Description="Autocorrect" HashKey="292929474729472929">
    <MapTiles>
      <MapTile TileID="15849" AltIDMod="0" />
      <MapTile TileID="15850" AltIDMod="0" />
      <MapTile TileID="15851" AltIDMod="0" />
      <MapTile TileID="15852" AltIDMod="0" />
    </MapTiles>
    <StaticTiles>
    </StaticTiles>
  </TransInfo>
  <TransInfo Description="Autocorrect" HashKey="292929294729472929">
    <MapTiles>
      <MapTile TileID="15849" AltIDMod="0" />
      <MapTile TileID="15850" AltIDMod="0" />
      <MapTile TileID="15851" AltIDMod="0" />
      <MapTile TileID="15852" AltIDMod="0" />
    </MapTiles>
    <StaticTiles>
    </StaticTiles>
  </TransInfo>
  <TransInfo Description="Autocorrect" HashKey="292929474729292929">
    <MapTiles>
      <MapTile TileID="15849" AltIDMod="0" />
      <MapTile TileID="15850" AltIDMod="0" />
      <MapTile TileID="15851" AltIDMod="0" />
      <MapTile TileID="15852" AltIDMod="0" />
    </MapTiles>
    <StaticTiles>
    </StaticTiles>
  </TransInfo>
  <TransInfo Description="Autocorrect" HashKey="292929294729292929">
    <MapTiles>
      <MapTile TileID="15849" AltIDMod="0" />
      <MapTile TileID="15850" AltIDMod="0" />
      <MapTile TileID="15851" AltIDMod="0" />
      <MapTile TileID="15852" AltIDMod="0" />
    </MapTiles>
    <StaticTiles>
    </StaticTiles>
  </TransInfo>
  <TransInfo Description="Invalid" HashKey="294747474747474729">
    <MapTiles>
      <MapTile TileID="282" AltIDMod="0" />
      <MapTile TileID="283" AltIDMod="0" />
      <MapTile TileID="284" AltIDMod="0" />
      <MapTile TileID="285" AltIDMod="0" />
    </MapTiles>
    <StaticTiles>
    </StaticTiles>
  </TransInfo>
  <TransInfo Description="Invalid" HashKey="474729474747294747">
    <MapTiles>
      <MapTile TileID="282" AltIDMod="0" />
      <MapTile TileID="283" AltIDMod="0" />
      <MapTile TileID="284" AltIDMod="0" />
      <MapTile TileID="285" AltIDMod="0" />
    </MapTiles>
    <StaticTiles>
    </StaticTiles>
  </TransInfo>
</Trans>